Workbook

Sheet 账单总览
B1: 客户月结总览
B5: 客户名称: | D5: 深圳市嘉嘉电科技有限公司 | H5: 顺丰对账人: | J5: 丰晓易
B6: 月结卡号: | D6: 7551083218 | H6: 对账热线: | J6: 4001095338
B7: 账单周期: | D7: 20260101-20260131 | H7: 联系邮箱: | J7: sfcscs@sf-express.com
B8: 最晚汇款日: | D8: 2026-02-28 | H8: 服务时间: | J8: 工作日周一至周五9:00-17:30
B11: 本期应付总额: | E11: ¥298.00
B12: 本期应付金额： | E12: ¥298.00
B13: 月结券抵扣: | E13: ¥0.00
B16: 费用类型 | D16: 费用 | G16: 折扣/促销 | J16: 应付金额
B17: 速运费用 | D17: 298 | G17: 0 | J17: 298
B18: 小计 | D18: 298 | G18: 0 | J18: 298
B21: 对公账户信息
B22: 速运公司
B23: 公司名称: | C23: 顺丰速运有限公司
B24: 银行名称: | C24: 中国工商银行股份有限公司前海分行
B25: 银行账号: | C25: 4000025319200395130
B28: 客户经理联系信息
B29: 联系人: | C29: 刘剑 | H29: 联系电话: | I29: 18676798627
B31: 温馨提示：
B32: ◆若您的账单地址、电邮地址等联系方式发生变化，为确保您能准确无误的收到账单，您可访问微信公众号“顺丰速运
B33: 月结服务”，及时更新您的信息。
B34: ◆您可通过银行转账、微信、支付宝等方式直接支付到我司账户，请勿将资金以现金或其他方式交付给我司员工个人账
B35: 户。如因支付给我司员工个人 账户造成的纠纷，我司不承担相关责任。
B36: ◆若您使用了我司国际件免税（增值税）产品服务需开具发票，请特别注意该服务发票开具主体为广东顺丰电子商务有
B37: 限公司，发票类型为普通发票；但您的款项请支付至上方所列公司及账号。
B38: ◆免税产品：顺丰国际电商专递、顺丰国际小包挂号、顺丰国际小包平邮、国际海运、国际重货-港到港、国际铁路整
B39: 柜、国际铁路散货、国际重货-陆运、国际重货-海外仓空+派、国际重货-海外仓海+派、国际重货-海外仓铁+派、国际仓
B40: 储、国际填舱。
B41: ◆我司自2019年4月开始向中国内地始发的国际标快+、国际标快、国际特惠产品收取燃油附加费， https://www.sf-express
B42: .com/chn/sc/support-more/international_fuel_surcharge_introduction查看当月燃油费率及计算方法。
... B45: ◆若贵司需变更开票信息或对账单内容有疑问，请联系顺丰对账联系人。

Sheet 账单明细
A1: 快递运单费用
A2: 序号 | B2: 日期 | C2: 运单号码 | D2: 寄件地区 | E2: 到件地区 | F2: 对方公司名称 | G2: 计费重量 | H2: 产品类型 | I2: 付款方式 | J2: 费用(元) | K2: 折扣/促销 | L2: 应付金额 | M2: 经手人 | N2: 服务 | O2: 任务类型 | P2: 下单账号 | Q2: 账号所属公司 | R2: 公司性质 | S2: 备注
A3: 1 | B3: 01-01 | C3: SF3268714509952 | D3: 东莞 | E3: 东莞 | F3: 邹小华 | G3: 0.000 | H3: 顺丰标快 | I3: 寄付 | J3: 6.00 | K3: 0.00 | L3: 6.00 | M3: 邹小华 | N3: 收件微派 | O3: =VLOOKUP(C3,Sheet2!A:C,2,FALSE) -> 取宝-物流服务 | P3: =VLOOKUP(C3,Sheet2!G:H,2,FALSE) -> 186****6788 | Q3: 东莞市中汇信息技术有限公司
A4: 2 | B4: 01-01 | C4: SF3268714724220 | D4: 东莞 | E4: 东莞 | F4: 邹小华 | G4: 0.000 | H4: 顺丰标快 | I4: 寄付 | J4: 3.00 | K4: 0.00 | L4: 3.00 | M4: 邹小华 | N4: 收件微派 | O4: =VLOOKUP(C4,Sheet2!A:C,2,FALSE) -> 立充充电宝取机柜-物流服务 | P4: =VLOOKUP(C4,Sheet2!G:H,2,FALSE) -> 186****6788 | Q4: 东莞市中汇信息技术有限公司
A5: 3 | B5: 01-01 | C5: SF5106970421620 | D5: 东莞 | E5: 东莞 | F5: 邹小华 | G5: 0.000 | H5: 顺丰标快 | I5: 寄付 | J5: 6.00 | K5: 0.00 | L5: 6.00 | M5: 邹小华 | N5: 收件微派 | O5: 取宝-物流服务 | P5: =VLOOKUP(C5,Sheet2!G:H,2,FALSE) -> 186****6788 | Q5: 东莞市中汇信息技术有限公司
A6: 4 | B6: 01-01 | C6: SF5127722204781 | D6: 东莞 | E6: 东莞 | F6: 邹小华 | G6: 0.000 | H6: 顺丰标快 | I6: 寄付 | J6: 3.00 | K6: 0.00 | L6: 3.00 | M6: 邹小华 | N6: 收件微派 | O6: 立充充电宝取机柜-物流服务 | P6: =VLOOKUP(C6,Sheet2!G:H,2,FALSE) -> 186****6788 | Q6: 东莞市中汇信息技术有限公司
A7: 5 | B7: 01-01 | C7: SF5127722665550 | D7: 东莞 | E7: 东莞 | F7: 邹小华 | G7: 0.000 | H7: 顺丰标快 | I7: 寄付 | J7: 6.00 | K7: 0.00 | L7: 6.00 | M7: 邹小华 | N7: 收件微派 | O7: =VLOOKUP(C7,Sheet2!A:C,2,FALSE) -> 取宝-物流服务 | P7: =VLOOKUP(C7,Sheet2!G:H,2,FALSE) -> 186****6788 | Q7: 东莞市中汇信息技术有限公司
A8: 6 | B8: 01-01 | C8: SF5127754205822 | D8: 东莞 | E8: 东莞 | F8: 邹小华 | G8: 0.000 | H8: 顺丰标快 | I8: 寄付 | J8: 6.00 | K8: 0.00 | L8: 6.00 | M8: 邹小华 | N8: 收件微派 | O8: 取宝-物流服务 | P8: =VLOOKUP(C8,Sheet2!G:H,2,FALSE) -> 186****6788 | Q8: 东莞市中汇信息技术有限公司
A9: 7 | B9: 01-01 | C9: SF5127766316133 | D9: 大连 | E9: 大连 | F9: 大连浩源满航空服务有限公司 | G9: 0.000 | H9: 顺丰标快 | I9: 寄转第三方 | J9: 3.00 | K9: 0.00 | L9: 3.00 | M9: 刘志强 | N9: 收件微派 | O9: 立充充电宝取机柜-物流服务 | P9: =VLOOKUP(C9,Sheet2!G:H,2,FALSE) -> 155****0885 | Q9: 大连浩源满航空服务有限公司
A10: 8 | B10: 01-04 | C10: SF5106805081938 | D10: 东莞 | E10: 东莞 | F10: 邹小华 | G10: 2.600 | H10: 顺丰标快 | I10: 寄转第三方 | J10: 13.00 | K10: 0.00 | L10: 13.00 | M10: 邹小华 | N10: 运费 | O10: =VLOOKUP(C10,Sheet2!A:C,2,FALSE) -> 立充充电宝取机柜-物流服务 | P10: =VLOOKUP(C10,Sheet2!G:H,2,FALSE) -> 186****6788 | Q10: 东莞市中汇信息技术有限公司
A11: 9 | B11: 01-04 | C11: SF5106805081938 | D11: 东莞 | E11: 东莞 | F11: 邹小华 | G11: 0.000 | H11: 顺丰标快 | I11: 寄转第三方 | J11: 4.00 | K11: 0.00 | L11: 4.00 | M11: 邹小华 | N11: 包装服务 | O11: =VLOOKUP(C11,Sheet2!A:C,2,FALSE) -> 立充充电宝取机柜-物流服务 | P11: =VLOOKUP(C11,Sheet2!G:H,2,FALSE) -> 186****6788 | Q11: 东莞市中汇信息技术有限公司
A12: 10 | B12: 01-04 | C12: SF5106805988745 | D12: 东莞 | E12: 东莞 | F12: 邹小华 | G12: 1.000 | H12: 顺丰标快 | I12: 寄转第三方 | J12: 11.00 | K12: 0.00 | L12: 11.00 | M12: 邹小华 | N12: 运费 | O12: =VLOOKUP(C12,Sheet2!A:C,2,FALSE) -> 取宝-物流服务 | P12: =VLOOKUP(C12,Sheet2!G:H,2,FALSE) -> 186****6788 | Q12: 东莞市中汇信息技术有限公司
A13: 11 | B13: 01-04 | C13: SF5106821124886 | D13: 东莞 | E13: 东莞 | F13: 长安波仕音乐量贩KTV(乌沙店) | G13: 1.000 | H13: 顺丰标快 | I13: 寄转第三方 | J13: 11.00 | K13: 0.00 | L13: 11.00 | M13: 邹小华 | N13: 运费 | O13: =VLOOKUP(C13,Sheet2!A:C,2,FALSE) -> 补宝-物流服务 | P13: =VLOOKUP(C13,Sheet2!G:H,2,FALSE) -> 186****6788 | Q13: 东莞市中汇信息技术有限公司
A14: 12 | B14: 01-04 | C14: SF5106834884492 | D14: 东莞 | E14: 东莞 | F14: 清溪小田湘·湖南土菜馆 | G14: 1.000 | H14: 顺丰标快 | I14: 寄转第三方 | J14: 11.00 | K14: 0.00 | L14: 11.00 | M14: 邹小华 | N14: 运费 | O14: =VLOOKUP(C14,Sheet2!A:C,2,FALSE) -> 补宝-物流服务 | P14: =VLOOKUP(C14,Sheet2!G:H,2,FALSE) -> 186****6788 | Q14: 东莞市中汇信息技术有限公司
A15: 13 | B15: 01-04 | C15: SF5127617611694 | D15: 东莞 | E15: 东莞 | F15: 长安波仕音乐量贩KTV(乌沙店) | G15: 1.000 | H15: 顺丰标快 | I15: 寄转第三方 | J15: 11.00 | K15: 0.00 | L15: 11.00 | M15: 邹小华 | N15: 运费 | O15: =VLOOKUP(C15,Sheet2!A:C,2,FALSE) -> 补宝-物流服务 | P15: =VLOOKUP(C15,Sheet2!G:H,2,FALSE) -> 186****6788 | Q15: 东莞市中汇信息技术有限公司
A16: 14 | B16: 01-05 | C16: SF5106805081938 | D16: 东莞 | E16: 东莞 | F16: 邹小华 | G16: 0.000 | H16: 顺丰标快 | I16: 寄付 | J16: 3.00 | K16: 0.00 | L16: 3.00 | M16: 邹小华 | N16: 收件微派 | O16: =VLOOKUP(C16,Sheet2!A:C,2,FALSE) -> 立充充电宝取机柜-物流服务 | P16: =VLOOKUP(C16,Sheet2!G:H,2,FALSE) -> 186****6788 | Q16: 东莞市中汇信息技术有限公司
A17: 15 | B17: 01-05 | C17: SF5106805988745 | D17: 东莞 | E17: 东莞 | F17: 邹小华 | G17: 0.000 | H17: 顺丰标快 | I17: 寄付 | J17: 6.00 | K17: 0.00 | L17: 6.00 | M17: 邹小华 | N17: 收件微派 | O17: =VLOOKUP(C17,Sheet2!A:C,2,FALSE) -> 取宝-物流服务 | P17: =VLOOKUP(C17,Sheet2!G:H,2,FALSE) -> 186****6788 | Q17: 东莞市中汇信息技术有限公司
A18: 16 | B18: 01-05 | C18: SF5106834884492 | D18: 东莞 | E18: 东莞 | F18: 清溪小田湘·湖南土菜馆 | G18: 0.000 | H18: 顺丰标快 | I18: 寄付 | J18: 6.00 | K18: 0.00 | L18: 6.00 | M18: 邹小华 | N18: 派件微派 | O18: =VLOOKUP(C18,Sheet2!A:C,2,FALSE) -> 补宝-物流服务 | P18: =VLOOKUP(C18,Sheet2!G:H,2,FALSE) -> 186****6788 | Q18: 东莞市中汇信息技术有限公司
A19: 17 | B19: 01-06 | C19: SF5106821124886 | D19: 东莞 | E19: 东莞 | F19: 长安波仕音乐量贩KTV(乌沙店) | G19: 0.000 | H19: 顺丰标快 | I19: 寄付 | J19: 6.00 | K19: 0.00 | L19: 6.00 | M19: 邹小华 | N19: 派件微派 | O19: =VLOOKUP(C19,Sheet2!A:C,2,FALSE) -> 补宝-物流服务 | P19: =VLOOKUP(C19,Sheet2!G:H,2,FALSE) -> 186****6788 | Q19: 东莞市中汇信息技术有限公司
A20: 18 | B20: 01-06 | C20: SF5127617611694 | D20: 东莞 | E20: 东莞 | F20: 长安波仕音乐量贩KTV(乌沙店) | G20: 0.000 | H20: 顺丰标快 | I20: 寄付 | J20: 6.00 | K20: 0.00 | L20: 6.00 | M20: 邹小华 | N20: 派件微派 | O20: =VLOOKUP(C20,Sheet2!A:C,2,FALSE) -> 补宝-物流服务 | P20: =VLOOKUP(C20,Sheet2!G:H,2,FALSE) -> 186****6788 | Q20: 东莞市中汇信息技术有限公司
A21: 19 | B21: 01-07 | C21: SF5103369030090 | D21: 深圳 | E21: 深圳 | F21: 嘉嘉电 | G21: 1.000 | H21: 顺丰标快 | I21: 寄转第三方 | J21: 12.00 | K21: 0.00 | L21: 12.00 | M21: 刘诗雨 | N21: 运费 | O21: =VLOOKUP(C21,Sheet2!A:C,2,FALSE) -> 补宝-仅物流 | P21: =VLOOKUP(C21,Sheet2!G:H,2,FALSE) -> 137****3997 | Q21: 本部
... A39: 37 | B39: 01-17 | C39: SF3267130908673 | D39: 深圳 | E39: 金华 | F39: 甘骞 | G39: 0.000 | H39: 顺丰标快 | I39: 寄付 | J39: 6.00 | K39: 0.00 | L39: 6.00 | M39: 魅KTV | N39: 收件微派 | O39: =VLOOKUP(C39,Sheet2!A:C,2,FALSE) -> 取宝-物流服务 | P39: =VLOOKUP(C39,Sheet2!G:H,2,FALSE) -> 134****9085 | Q39: 深圳市嘉嘉电科技有限公司
A40: 合 计 | J40: 298.00 | K40: 0.00 | L40: 298.00

Sheet 月结报告

Sheet 1月订单明细
A1: 运单号 | B1: 任务类型 | C1: 系统订单号 | D1: 照片是否导出 | E1: 批次号 | F1: 服务状态 | G1: 商户订单号 | H1: 上门小哥手机号 | I1: 物流状态 | J1: 是否打印 | K1: 预计上门时间 | L1: 收件人 | M1: 收件手机 | N1: 收件电话 | O1: 收件公司 | P1: 收件详细地址 | Q1: 寄件人 | R1: 寄件电话 | S1: 寄方备注 | T1: 寄件公司 | U1: 寄件详细地址 | V1: 托寄物内容 | W1: 托寄物数量 | X1: 件数 | Y1: 包裹重量(kg) | Z1: 运费付款方式 | AA1: 物流产品 | AB1: 自取 | AC1: 定额保价金额(元) | AD1: 基础保价金额(元) | AE1: 密钥认证 | AF1: 下单时间 | AG1: 下单账号 | AH1: 接单人姓名 | AI1: 任务完成时间 | AJ1: 接单人手机 | AK1: 签收完成时间 | AL1: 月结卡号 | AM1: 下call上门收件 | AN1: 标记 | AO1: 异常原因
A2: SF5127617611694 | B2: 补宝-物流服务 | C2: WP26010401103205 | D2: 未导出 | E2: BAT260104132187 | F2: 已完成 | I2: 派送成功 | J2: 未打印 | K2: 2026-01-05 12:00 | L2: 邹*华 | M2: 186****6788‎‎‎‬‬‬ | N2: *******6788‎‎‎‬‬‬ | O2: 长安波仕************ | P2: 广东省东莞市长安 镇乌沙社区*****‎‎‎‬‬‬ | Q2: 邹*华 | R2: *******6788‎‎‎‬‬‬ | S2: 补一楼立充机器里面 | U2: 广东省东莞市东城街道东纵路东城段208号 东城万达中心写**********‎‎‎‬‬‬ | V2: 充电宝 | W2: 2 | X2: 1 | Z2: 寄付月结 | AA2: 顺丰标快 | AE2: 否 | AF2: 2026-01-04 15:59:17 | AG2: 186****6788 | AH2: 林浩 | AI2: 2026-01-05 15:48:25 | AJ2: 132****7218‎‎‎‬‬‬ | AK2: 2026-01-05 15:48:30 | AL2: 7551083218 | AM2: 是
A3: SF5106821124886 | B3: 补宝-物流服务 | C3: WP26010401100701 | D3: 未导出 | E3: BAT260104131990 | F3: 已完成 | I3: 派送成功 | J3: 未打印 | K3: 2026-01-05 12:00 | L3: 邹*华 | M3: 186****6788‎‎‎‬‬‬ | N3: *******6788‎‎‎‬‬‬ | O3: 长安波仕************ | P3: 广东省东莞市长安 镇乌沙社区*****‎‎‎‬‬‬ | Q3: 邹*华 | R3: *******6788‎‎‎‬‬‬ | S3: 补一楼立充机器里面 | U3: 广东省东莞市东城街道东纵路东城段208号 东城万达中心写**********‎‎‎‬‬‬ | V3: 充电宝 | W3: 2 | X3: 1 | Z3: 寄付月结 | AA3: 顺丰标快 | AE3: 否 | AF3: 2026-01-04 15:59:17 | AG3: 186****6788 | AH3: 林浩 | AI3: 2026-01-05 15:47:49 | AJ3: 132****7218‎‎‎‬‬‬ | AK3: 2026-01-05 15:47:54 | AL3: 7551083218 | AM3: 是
A4: SF5106834884492 | B4: 补宝-物流服务 | C4: WP26010400131549 | D4: 未导出 | E4: BAT260104033681 | F4: 已完成 | I4: 派送成功 | J4: 未打印 | K4: 2026-01-05 12:00 | L4: 邹*华 | M4: 186****6788‎‎‎‬‬‬ | N4: *******6788‎‎‎‬‬‬ | O4: 清溪小田******* | P4: 广东省东莞市清溪镇********* ****‎‎‎‬‬‬ | Q4: 邹*华 | R4: *******6788‎‎‎‬‬‬ | S4: 进店插立充充电宝的宝 | U4: 广东省东莞市东城街道东纵路东城段208号 东城万达中心写**********‎‎‎‬‬‬ | V4: 充电宝 | W4: 2 | X4: 1 | Z4: 寄付月结 | AA4: 顺丰标快 | AE4: 否 | AF4: 2026-01-04 10:58:55 | AG4: 186****6788 | AH4: 柴琪 | AI4: 2026-01-04 16:09:35 | AJ4: 176****2551‎‎‎‬‬‬ | AK4: 2026-01-04 16:09:41 | AL4: 7551083218 | AM4: 是
A5: SF5103369030090 | B5: 补宝-仅物流 | C5: WP26010713353562 | E5: BAT260107021473 | I5: 派送成功 | J5: 未打印 | K5: 2026-01-08 12:00 | L5: 吴*欣 | M5: 137****3997‎‎‎‬‬‬ | N5: *******3997‎‎‎‬‬‬ | O5: 嘉** | P5: 深圳市南山区***** ****************‎‎‎‬‬‬ | Q5: 刘*雨 | R5: *******0776‎‎‎‬‬‬ | U5: 广东省 深圳市龙华区********************‎‎‎‬‬‬ | V5: 充电宝 | W5: 1 | X5: 1 | Z5: 寄付月结 | AA5: 顺丰标快 | AE5: 否 | AF5: 2026-01-07 09:46:54 | AG5: 137****3997 | AJ5: 2026-01-07 16:32:45 | AK5: ******3218 | AL5: 是
A6: SF3267130908673 | B6: 取宝-物流服务 | C6: WP26011652740695 | D6: 未导出 | E6: BAT260116265535 | F6: 已完成 | H6: 15778885720 | I6: 派送成功 | J6: 未打印 | K6: 2026-01-17 18:00 | L6: 甘* | M6: 166****7627‎‎‎‬‬‬ | P6: 浙江省兰溪市兰江街道金角路1333号** ********‎‎‎‬‬‬ | Q6: 魅**V | R6: *******2046‎‎‎‬‬‬ | U6: 深圳市罗湖区***** **********‎‎‎‬‬‬ | V6: 充电宝 | W6: 1 | X6: 1 | Z6: 寄付月结 | AA6: 顺丰标快 | AE6: 否 | AF6: 2026-01-16 18:09:37 | AG6: 134****9085 | AH6: 彭云 | AI6: 2026-01-16 18:37:43 | AJ6: 157****5720‎‎‎‬‬‬ | AK6: 2026-01-18 13:20:22 | AL6: 是 | AM6: 7551083218
A7: SF3267046169283 | B7: 取宝-物流服务 | C7: WP26011652045997 | D7: 未导出 | E7: BAT260116196352 | F7: 已取消 | H7: 15778885720 | I7: 已取消 | J7: 未打印 | L7: 甘* | M7: 166****7627‎‎‎‬‬‬ | P7: 浙江省兰溪市兰江街道金角路1333号** ********‎‎‎‬‬‬ | Q7: 魅**V | R7: *******0969‎‎‎‬‬‬ | U7: 深圳市罗湖区***** **********‎‎‎‬‬‬ | V7: 充电宝 | W7: 1 | X7: 1 | Z7: 寄付月结 | AA7: 顺丰标快 | AE7: 否 | AF7: 2026-01-16 16:54:24 | AG7: 134****9085 | AL7: 是 | AM7: 7551083218
A8: SF5127526237848 | B8: 取宝-物流服务 | C8: WP26010923451208 | D8: 未导出 | E8: BAT260109127192 | F8: 待接单 | H8: 15986662914 | I8: 未收件 | J8: 未打印 | L8: 邹*华 | M8: 186****6788‎‎‎‬‬‬ | N8: *******6788‎‎‎‬‬‬ | P8: 广东省东莞市东城街道东纵路东城段208号 东城万达中心写**********‎‎‎‬‬‬ | Q8: 邹*华 | R8: *******6788‎‎‎‬‬‬ | S8: 门口取立充充电宝的宝2个 | T8: 深圳罗湖泉记客家风味食府 | U8: 广东省深圳市罗 湖区**********************‎‎‎‬‬‬ | V8: 充电宝 | W8: 2 | X8: 1 | Z8: 寄付月结 | AA8: 顺丰特快 | AE8: 否 | AF8: 2026-01-09 15:33:16 | AG8: 186****6788 | AL8: 是 | AM8: 7551083218
A9: SF3265855044685 | B9: 取宝-物流服务 | C9: WP26010923448618 | D9: 未导出 | E9: BAT260109126930 | F9: 已完成 | H9: 15986662914 | I9: 派送成功 | J9: 未打印 | K9: 2026-01-10 12:00 | L9: 邹*华 | M9: 186****6788‎‎‎‬‬‬ | N9: *******6788‎‎‎‬‬‬ | P9: 广东省东莞市东城街道东纵路东城段208号 东城万达中心写**********‎‎‎‬‬‬ | Q9: 邹*华 | R9: *******6788‎‎‎‬‬‬ | S9: 进店取立充充电宝的宝2个 | T9: 深圳罗湖泉记客家风味食府 | U9: 广东省深圳市罗 湖区**********************‎‎‎‬‬‬ | V9: 充电宝 | W9: 2 | X9: 1 | Z9: 寄付月结 | AA9: 顺丰特快 | AE9: 否 | AF9: 2026-01-09 15:33:16 | AG9: 186****6788 | AH9: 杨建 | AI9: 2026-01-09 16:14:39 | AJ9: 159****2914‎‎‎‬‬‬ | AK9: 2026-01-10 08:26:12 | AL9: 是 | AM9: 7551083218
A10: SF5103058067049 | B10: 取宝-物流服务 | C10: WP26010922769893 | D10: 未导出 | E10: BAT260109056568 | F10: 已取消 | H10: 13246188810 | I10: 已取消 | J10: 未打印 | L10: 邹*华 | M10: 186****6788‎‎‎‬‬‬ | N10: *******6788‎‎‎‬‬‬ | P10: 广东省东莞市东城街道东纵路东城段208号 东城万达中心写**********‎‎‎‬‬‬ | Q10: 邹*华 | R10: *******6788‎‎‎‬‬‬ | S10: 进店取立充充电宝的宝2个 | T10: 石湾四个朋友龙湾新城一期店 | U10: 广东省惠州市博罗县*** **************‎‎‎‬‬‬ | V10: 充电宝 | W10: 2 | X10: 1 | Z10: 寄付月结 | AA10: 顺丰标快 | AE10: 否 | AF10: 2026-01-09 11:47:06 | AG10: 186****6788 | AL10: 是 | AM10: 7551083218
A11: SF5103058067191 | B11: 取宝-物流服务 | C11: WP26010922767003 | D11: 未导出 | E11: BAT260109056262 | F11: 已取消 | H11: 13246188810 | I11: 已取消 | J11: 未打印 | L11: 邹*华 | M11: 186****6788‎‎‎‬‬‬ | N11: *******6788‎‎‎‬‬‬ | P11: 广东省东莞市东城街道东纵路东城段208号 东城万达中心写**********‎‎‎‬‬‬ | Q11: 邹*华 | R11: *******6788‎‎‎‬‬‬ | S11: 进店取立充充电宝的宝2个 | T11: 石湾四个朋友龙湾新城一期店 | U11: 广东省惠州市博罗县*** **************‎‎‎‬‬‬ | V11: 充电宝 | W11: 2 | X11: 1 | Z11: 寄付月结 | AA11: 顺丰标快 | AE11: 否 | AF11: 2026-01-09 11:47:06 | AG11: 186****6788 | AL11: 是 | AM11: 7551083218
A12: SF5127575538745 | B12: 取宝-物流服务 | C12: WP26010922417043 | D12: 未导出 | E12: BAT260109020664 | F12: 已完成 | H12: 15602486465 | I12: 派送成功 | J12: 未打印 | K12: 2026-01-10 12:00 | L12: 邹*华 | M12: 186****6788‎‎‎‬‬‬ | N12: *******6788‎‎‎‬‬‬ | P12: 广东省东莞市东城街道东纵路东城段208号 东城万达中心写**********‎‎‎‬‬‬ | Q12: 邹*华 | R12: *******6788‎‎‎‬‬‬ | S12: 进店取立充充电宝的宝2个 | T12: 宝安西乡森林汇大牌渔庄(臣田店) | U12: 广东 省深圳市宝安区***************‎‎‎‬‬‬ | V12: 充电宝 | W12: 2 | X12: 1 | Z12: 寄付月结 | AA12: 顺丰标快 | AE12: 否 | AF12: 2026-01-09 09:54:02 | AG12: 186****6788 | AH12: 杨立伟 | AI12: 2026-01-09 10:32:42 | AJ12: 156****6465‎‎‎‬‬‬ | AK12: 2026-01-10 08:26:12 | AL12: 是 | AM12: 7551083218
A13: SF3265863387051 | B13: 取宝-物流服务 | C13: WP26010922411489 | D13: 未导出 | E13: BAT260109020106 | F13: 已完成 | H13: 15602486465 | I13: 派送成功 | J13: 未打印 | K13: 2026-01-10 12:00 | L13: 邹*华 | M13: 186****6788‎‎‎‬‬‬ | N13: *******6788‎‎‎‬‬‬ | P13: 广东省东莞市东城街道东纵路东城段208号 东城万达中心写**********‎‎‎‬‬‬ | Q13: 邹*华 | R13: *******6788‎‎‎‬‬‬ | S13: 进店取立充充电宝的宝2个 | T13: 宝安西乡森林汇大牌渔庄(臣田店) | U13: 广东 省深圳市宝安区***************‎‎‎‬‬‬ | V13: 充电宝 | W13: 2 | X13: 1 | Z13: 寄付月结 | AA13: 顺丰标快 | AE13: 否 | AF13: 2026-01-09 09:54:02 | AG13: 186****6788 | AH13: 杨立伟 | AI13: 2026-01-09 10:33:09 | AJ13: 156****6465‎‎‎‬‬‬ | AK13: 2026-01-10 08:26:12 | AL13: 是 | AM13: 7551083218
A14: SF5106805988745 | B14: 取宝-物流服务 | C14: WP26010400451881 | D14: 未导出 | E14: BAT260104065779 | F14: 已完成 | H14: 18688099345 | I14: 派送成功 | J14: 未打印 | K14: 2026-01-05 12:00 | L14: 邹*华 | M14: 186****6788‎‎‎‬‬‬ | N14: *******6788‎‎‎‬‬‬ | P14: 广东省东莞市东城街道东纵路东城段208号 东城万达中心写**********‎‎‎‬‬‬ | Q14: 邹*华 | R14: *******6788‎‎‎‬‬‬ | S14: 进店取立充充电宝的宝2个 | T14: 企石忆兴39位自助酱骨头火锅 | U14: 广东省东莞市企石镇*** *******‎‎‎‬‬‬ | V14: 充电宝 | W14: 2 | X14: 1 | Z14: 寄付月结 | AA14: 顺丰标快 | AE14: 否 | AF14: 2026-01-04 12:34:12 | AG14: 186****6788 | AH14: 罗流明 | AI14: 2026-01-04 13:18:11 | AJ14: 186****9345‎‎‎‬‬‬ | AK14: 2026-01-05 08:29:00 | AL14: 是 | AM14: 7551083218
A15: SF5106805179236 | B15: 取宝-物流服务 | C15: WP26010400448753 | D15: 未导出 | E15: BAT260104065458 | F15: 已取消 | H15: 18688099345 | I15: 已取消 | J15: 未打印 | L15: 邹*华 | M15: 186****6788‎‎‎‬‬‬ | N15: *******6788‎‎‎‬‬‬ | P15: 广东省东莞市东城街道东纵路东城段208号 东城万达中心写**********‎‎‎‬‬‬ | Q15: 邹*华 | R15: *******6788‎‎‎‬‬‬ | S15: 进店取立充充电宝的宝2个 | T15: 企石忆兴39位自助酱骨头火锅 | U15: 广东省东莞市企石镇*** *******‎‎‎‬‬‬ | V15: 充电宝 | W15: 2 | X15: 1 | Z15: 寄付月结 | AA15: 顺丰标快 | AE15: 否 | AF15: 2026-01-04 12:32:09 | AG15: 186****6788 | AL15: 是 | AM15: 7551083218
A16: SF5103003341641 | B16: 立充充电宝取机柜-物流服务 | C16: WP26010923455169 | D16: 未导出 | E16: BAT260109127596 | F16: 待接单 | H16: 15986662914 | I16: 未收件 | J16: 未打印 | L16: 邹*华 | M16: 186****6788‎‎‎‬‬‬ | N16: *******6788‎‎‎‬‬‬ | P16: 广东省东莞市东城街道东纵路东城段208号 东城万达中心写**********‎‎‎‬‬‬ | Q16: 邹*华 | R16: *******6788‎‎‎‬‬‬ | S16: 进店取立充充电宝的机柜 | T16: 深圳罗湖泉记客家风味食府 | U16: 广东省深圳市罗 湖区**********************‎‎‎‬‬‬ | V16: 充电宝机柜 | W16: 1 | X16: 1 | Z16: 寄付月结 | AA16: 顺丰特快 | AE16: 否 | AF16: 2026-01-09 15:34:07 | AG16: 186****6788 | AL16: 7551083218 | AM16: 是
A17: SF3265889459944 | B17: 立充充电宝取机柜-物流服务 | C17: WP26010922763195 | D17: 未导出 | E17: BAT260109055859 | F17: 已取消 | H17: 13246188810 | I17: 已取消 | J17: 未打印 | L17: 邹*华 | M17: 186****6788‎‎‎‬‬‬ | N17: *******6788‎‎‎‬‬‬ | P17: 广东省东莞市东城街道东纵路东城段208号 东城万达中心写**********‎‎‎‬‬‬ | Q17: 邹*华 | R17: *******6788‎‎‎‬‬‬ | S17: 进店取立充充电宝的架子 | T17: 石湾四个朋友龙湾新城一期店 | U17: 广东省惠州市博罗县*** **************‎‎‎‬‬‬ | V17: 充电宝架子 | W17: 1 | X17: 1 | Z17: 寄付月结 | AA17: 顺丰标快 | AE17: 否 | AF17: 2026-01-09 11:45:20 | AG17: 186****6788 | AL17: 7551083218 | AM17: 是
A18: SF5127508764809 | B18: 立充充电宝取机柜-物流服务 | C18: WP26010922759940 | D18: 未导出 | E18: BAT260109055513 | F18: 已取消 | H18: 13246188810 | I18: 已取消 | J18: 未打印 | L18: 邹*华 | M18: 186****6788‎‎‎‬‬‬ | N18: *******6788‎‎‎‬‬‬ | P18: 广东省东莞市东城街道东纵路东城段208号 东城万达中心写**********‎‎‎‬‬‬ | Q18: 邹*华 | R18: *******6788‎‎‎‬‬‬ | S18: 进店取立充充电宝的机柜 | T18: 石湾四个朋友龙湾新城一期店 | U18: 广东省惠州市博罗县*** **************‎‎‎‬‬‬ | V18: 充电宝机柜 | W18: 1 | X18: 1 | Z18: 寄付月结 | AA18: 顺丰标快 | AE18: 否 | AF18: 2026-01-09 11:45:20 | AG18: 186****6788 | AL18: 7551083218 | AM18: 是
A19: SF5127597048630 | B19: 立充充电宝取机柜-物流服务 | C19: WP26010922420295 | D19: 未导出 | E19: BAT260109021014 | F19: 已完成 | H19: 15602486465 | I19: 派送成功 | J19: 未打印 | K19: 2026-01-10 12:00 | L19: 邹*华 | M19: 186****6788‎‎‎‬‬‬ | N19: *******6788‎‎‎‬‬‬ | P19: 广东省东莞市东城街道东纵路东城段208号 东城万达中心写**********‎‎‎‬‬‬ | Q19: 邹*华 | R19: *******6788‎‎‎‬‬‬ | S19: 进店取立充充电宝的架子 | T19: 宝安西乡森林汇大牌渔庄(臣田店) | U19: 广东 省深圳市宝安区***************‎‎‎‬‬‬ | V19: 充电宝架子 | W19: 1 | X19: 1 | Z19: 寄付月结 | AA19: 顺丰标快 | AE19: 否 | AF19: 2026-01-09 09:55:23 | AG19: 186****6788 | AH19: 杨立伟 | AI19: 2026-01-09 10:41:42 | AJ19: 156****6465‎‎‎‬‬‬ | AK19: 2026-01-10 08:26:12 | AL19: 7551083218 | AM19: 是
A20: SF5103182724031 | B20: 立充充电宝取机柜-物流服务 | C20: WP26010922419036 | D20: 未导出 | E20: BAT260109020881 | F20: 已完成 | H20: 15602486465 | I20: 派送成功 | J20: 未打印 | K20: 2026-01-10 12:00 | L20: 邹*华 | M20: 186****6788‎‎‎‬‬‬ | N20: *******6788‎‎‎‬‬‬ | P20: 广东省东莞市东城街道东纵路东城段208号 东城万达中心写**********‎‎‎‬‬‬ | Q20: 邹*华 | R20: *******6788‎‎‎‬‬‬ | S20: 进店取立充充电宝的机柜 | T20: 宝安西乡森林汇大牌渔庄(臣田店) | U20: 广东 省深圳市宝安区***************‎‎‎‬‬‬ | V20: 充电宝机柜 | W20: 1 | X20: 1 | Z20: 寄付月结 | AA20: 顺丰标快 | AE20: 否 | AF20: 2026-01-09 09:55:23 | AG20: 186****6788 | AH20: 杨立伟 | AI20: 2026-01-09 10:21:37 | AJ20: 156****6465‎‎‎‬‬‬ | AK20: 2026-01-10 08:26:12 | AL20: 7551083218 | AM20: 是
A21: SF5106805081938 | B21: 立充充电宝取机柜-物流服务 | C21: WP26010400450435 | D21: 未导出 | E21: BAT260104065629 | F21: 已完成 | H21: 18688099345 | I21: 派送成功 | J21: 未打印 | K21: 2026-01-05 12:00 | L21: 邹*华 | M21: 186****6788‎‎‎‬‬‬ | N21: *******6788‎‎‎‬‬‬ | P21: 广东省东莞市东城街道东纵路东城段208号 东城万达中心写**********‎‎‎‬‬‬ | Q21: 邹*华 | R21: *******6788‎‎‎‬‬‬ | S21: 进店取立充充电宝的机柜 | T21: 企石忆兴39位自助酱骨头火锅 | U21: 广东省东莞市企石镇*** *******‎‎‎‬‬‬ | V21: 充电宝机柜 | W21: 1 | X21: 1 | Z21: 寄付月结 | AA21: 顺丰标快 | AE21: 否 | AF21: 2026-01-04 12:33:12 | AG21: 186****6788 | AH21: 罗流明 | AI21: 2026-01-04 13:24:29 | AJ21: 186****9345‎‎‎‬‬‬ | AK21: 2026-01-05 08:29:00 | AL21: 7551083218 | AM21: 是

Sheet Sheet2
A1: 运单号 | B1: 任务类型 | C1: 收件手机 | G1: SF5127617611694 | H1: 186****6788 | K1: 手机号 | L1: 账号所属公司 | M1: 公司性质 | AG1: 186****6788
A2: SF5127617611694 | B2: 补宝-物流服务 | C2: 186****6788‎‎‎‬‬‬ | G2: SF5106821124886 | H2: 186****6788 | K2: 165****7666 | L2: 深圳市锐丰伟业科技有限公司 | M2: 服务商 | AG2: 186****6788
A3: SF5106821124886 | B3: 补宝-物流服务 | C3: 186****6788‎‎‎‬‬‬ | G3: SF5106834884492 | H3: 186****6788 | K3: 186****8003 | L3: 河北亘石信息科技有限公司 | M3: 服务商 | AG3: 186****6788
A4: SF5106834884492 | B4: 补宝-物流服务 | C4: 186****6788‎‎‎‬‬‬ | G4: SF5103369030090 | H4: 137****3997 | K4: 155****0885 | L4: 大连浩源满航空服务有限公司 | M4: 服务商 | AG4: 137****3997
A5: SF5103369030090 | B5: 补宝-仅物流 | C5: 137****3997‎‎‎‬‬‬ | G5: SF3267130908673 | H5: 134****9085 | K5: 134****6101 | L5: 成都江源易通信息技术有限公司 | M5: 服务商 | AG5: 134****9085
A6: SF3267130908673 | B6: 取宝-物流服务 | C6: 166****7627‎‎‎‬‬‬ | G6: SF3267046169283 | H6: 134****9085 | K6: 156****1234 | L6: 内蒙古悦盈科技有限公司 | M6: 服务商 | AG6: 134****9085
A7: SF3267046169283 | B7: 取宝-物流服务 | C7: 166****7627‎‎‎‬‬‬ | G7: SF5127526237848 | H7: 186****6788 | K7: 137****1781 | L7: 东莞市聚伴科技有限公司 | M7: 服务商 | AG7: 186****6788
A8: SF5127526237848 | B8: 取宝-物流服务 | C8: 186****6788‎‎‎‬‬‬ | G8: SF3265855044685 | H8: 186****6788 | K8: 181****5776 | L8: 福建无现新生信息科技有限公司 | M8: 服务商 | AG8: 186****6788
A9: SF3265855044685 | B9: 取宝-物流服务 | C9: 186****6788‎‎‎‬‬‬ | G9: SF5103058067049 | H9: 186****6788 | K9: 136****7868 | L9: 山东省点线面网络科技有限公司 | M9: 服务商 | AG9: 186****6788
A10: SF5103058067049 | B10: 取宝-物流服务 | C10: 186****6788‎‎‎‬‬‬ | G10: SF5103058067191 | H10: 186****6788 | K10: 131****2614 | L10: 辽宁深蓝数据服务有限公司 | M10: 服务商 | AG10: 186****6788
A11: SF5103058067191 | B11: 取宝-物流服务 | C11: 186****6788‎‎‎‬‬‬ | G11: SF5127575538745 | H11: 186****6788 | K11: 158****6590 | L11: 江西森楠科技有限公司 | M11: 服务商 | AG11: 186****6788
A12: SF5127575538745 | B12: 取宝-物流服务 | C12: 186****6788‎‎‎‬‬‬ | G12: SF3265863387051 | H12: 186****6788 | K12: 187****4440 | L12: 长治市聚英科技有限公司 | M12: 服务商 | AG12: 186****6788
... A17: SF3265889459944 | B17: 立充充电宝取机柜-物流服务 | C17: 186****6788‎‎‎‬‬‬ | G17: SF5127508764809 | H17: 186****6788 | K17: 134****9085 | L17: 深圳市嘉嘉电科技有限公司 | M17: 服务商 | AG17: 186****6788
A18: SF5127508764809 | B18: 立充充电宝取机柜-物流服务 | C18: 186****6788‎‎‎‬‬‬ | G18: SF5127597048630 | H18: 186****6788 | AG18: 186****6788
A19: SF5127597048630 | B19: 立充充电宝取机柜-物流服务 | C19: 186****6788‎‎‎‬‬‬ | G19: SF5103182724031 | H19: 186****6788 | AG19: 186****6788
A20: SF5103182724031 | B20: 立充充电宝取机柜-物流服务 | C20: 186****6788‎‎‎‬‬‬ | G20: SF5106805081938 | H20: 186****6788 | AG20: 186****6788
A21: SF5106805081938 | B21: 立充充电宝取机柜-物流服务 | C21: 186****6788‎‎‎‬‬‬
G29: SF3268714509952 | H29: 186****6788
A30: SF3268714509952 | B30: 取宝-物流服务 | C30: 186****6788‎‎‎‬‬‬ | G30: SF3268714724220 | H30: 186****6788
A31: SF3268714724220 | B31: 立充充电宝取机柜-物流服务 | C31: 186****6788‎‎‎‬‬‬ | G31: SF5106970421620 | H31: 186****6788
A32: SF5106970421620 | B32: 取宝-物流服务 | C32: 186****6788‎‎‎‬‬‬ | G32: SF5127722204781 | H32: 186****6788
A33: SF5127722204781 | B33: 立充充电宝取机柜-物流服务 | C33: 186****6788‎‎‎‬‬‬ | G33: SF5127722665550 | H33: 186****6788
A34: SF5127722665550 | B34: 取宝-物流服务 | C34: 186****6788‎‎‎‬‬‬ | G34: SF5127766316133 | H34: 155****0885
A35: SF5127766316133 | B35: 立充充电宝取机柜-物流服务 | C35: 155****0885‎‎‎‬‬‬ | G35: SF5127754205822 | H35: 186****6788
A36: SF5127754205822 | B36: 取宝-物流服务 | C36: 186****6788‎‎‎‬‬‬
