Workbook

Sheet 账单总览
B1: 客户月结总览
B5: 客户名称: | D5: 深圳市嘉嘉电科技有限公司 | H5: 顺丰对账人: | J5: 丰晓易
B6: 月结卡号: | D6: 7551083218 | H6: 对账热线: | J6: 4001095338
B7: 账单周期: | D7: 20251201-20251231 | H7: 联系邮箱: | J7: sfcscs@sf-express.com
B8: 最晚汇款日: | D8: 2026-01-31 | H8: 服务时间: | J8: 工作日周一至周五9:00-17:30
B11: 本期应付总额: | E11: ¥4,210.50
B12: 本期应付金额： | E12: ¥4,210.50
B13: 月结券抵扣: | E13: ¥0.00
B16: 费用类型 | D16: 费用 | G16: 折扣/促销 | J16: 应付金额
B17: 速运费用 | D17: 4210.5 | G17: 0 | J17: 4210.5
B18: 小计 | D18: 4210.5 | G18: 0 | J18: 4210.5
B21: 对公账户信息
B22: 速运公司
B23: 公司名称: | C23: 顺丰速运有限公司
B24: 银行名称: | C24: 中国工商银行股份有限公司前海分行
B25: 银行账号: | C25: 4000025319200395130
B28: 客户经理联系信息
B29: 联系人: | C29: 李先亮 | H29: 联系电话: | I29: 18823870296
B31: 温馨提示：
B32: ◆若您的账单地址、电邮地址等联系方式发生变化，为确保您能准确无误的收到账单，您可访问微信公众号“顺丰速运
B33: 月结服务”，及时更新您的信息。
B34: ◆您可通过银行转账、微信、支付宝等方式直接支付到我司账户，请勿将资金以现金或其他方式交付给我司员工个人账
B35: 户。如因支付给我司员工个人 账户造成的纠纷，我司不承担相关责任。
B36: ◆若您使用了我司国际件免税（增值税）产品服务需开具发票，请特别注意该服务发票开具主体为广东顺丰电子商务有
B37: 限公司，发票类型为普通发票；但您的款项请支付至上方所列公司及账号。
B38: ◆免税产品：顺丰国际电商专递、顺丰国际小包挂号、顺丰国际小包平邮、国际海运、国际重货-港到港、国际铁路整
B39: 柜、国际铁路散货、国际重货-陆运、国际重货-海外仓空+派、国际重货-海外仓海+派、国际重货-海外仓铁+派、国际仓
B40: 储、国际填舱。
B41: ◆我司自2019年4月开始向中国内地始发的国际标快+、国际标快、国际特惠产品收取燃油附加费， https://www.sf-express
B42: .com/chn/sc/support-more/international_fuel_surcharge_introduction查看当月燃油费率及计算方法。
... B45: ◆若贵司需变更开票信息或对账单内容有疑问，请联系顺丰对账联系人。

Sheet 账单明细
A1: 快递运单费用
A2: 序号 | B2: 日期 | C2: 运单号码 | D2: 寄件地区 | E2: 到件地区 | F2: 对方公司名称 | G2: 计费重量 | H2: 产品类型 | I2: 付款方式 | J2: 费用(元) | K2: 折扣/促销 | L2: 应付金额 | M2: 经手人 | N2: 服务 | O2: 任务类型 | P2: 下单账号 | Q2: 账号所属公司 | R2: 公司性质 | S2: 备注
A3: 1 | B3: 12-01 | C3: SF3262372117661 | D3: 雅安 | E3: 成都/资阳/眉山 | F3: 文刚 | G3: 1.000 | H3: 顺丰标快 | I3: 寄转第三方 | J3: 13.00 | K3: 0.00 | L3: 13.00 | M3: 文刚 | N3: 运费 | O3: =VLOOKUP(C3,Sheet2!A:C,2,FALSE) -> 取宝-物流服务 | P3: =VLOOKUP(C3,Sheet2!G:H,2,FALSE) -> 134****6101 | Q3: 成都江源易通信息技术有限公司
A4: 2 | B4: 12-01 | C4: SF3262372117661 | D4: 雅安 | E4: 成都/资阳/眉山 | F4: 文刚 | G4: 0.000 | H4: 顺丰标快 | I4: 寄转第三方 | J4: 2.00 | K4: 0.00 | L4: 2.00 | M4: 文刚 | N4: 包装服务 | O4: =VLOOKUP(C4,Sheet2!A:C,2,FALSE) -> 取宝-物流服务 | P4: =VLOOKUP(C4,Sheet2!G:H,2,FALSE) -> 134****6101 | Q4: 成都江源易通信息技术有限公司
A5: 3 | B5: 12-01 | C5: SF3262372954357 | D5: 雅安 | E5: 成都/资阳/眉山 | F5: 文刚 | G5: 4.500 | H5: 顺丰标快 | I5: 寄转第三方 | J5: 20.00 | K5: 0.00 | L5: 20.00 | M5: 文刚 | N5: 运费 | O5: =VLOOKUP(C5,Sheet2!A:C,2,FALSE) -> 立充充电宝取机柜-物流服务 | P5: =VLOOKUP(C5,Sheet2!G:H,2,FALSE) -> 134****6101 | Q5: 成都江源易通信息技术有限公司
A6: 4 | B6: 12-01 | C6: SF3262372954357 | D6: 雅安 | E6: 成都/资阳/眉山 | F6: 文刚 | G6: 0.000 | H6: 顺丰标快 | I6: 寄转第三方 | J6: 7.00 | K6: 0.00 | L6: 7.00 | M6: 文刚 | N6: 包装服务 | O6: =VLOOKUP(C6,Sheet2!A:C,2,FALSE) -> 立充充电宝取机柜-物流服务 | P6: =VLOOKUP(C6,Sheet2!G:H,2,FALSE) -> 134****6101 | Q6: 成都江源易通信息技术有限公司
A7: 5 | B7: 12-01 | C7: SF3262377404072 | D7: 东莞 | E7: 东莞 | F7: 邹小华 | G7: 1.000 | H7: 顺丰标快 | I7: 寄转第三方 | J7: 11.00 | K7: 0.00 | L7: 11.00 | M7: 邹小华 | N7: 运费 | O7: =VLOOKUP(C7,Sheet2!A:C,2,FALSE) -> 取宝-物流服务 | P7: =VLOOKUP(C7,Sheet2!G:H,2,FALSE) -> 186****6788 | Q7: 东莞市中汇信息技术有限公司
A8: 6 | B8: 12-01 | C8: SF3262377404072 | D8: 东莞 | E8: 东莞 | F8: 邹小华 | G8: 0.000 | H8: 顺丰标快 | I8: 寄转第三方 | J8: 2.00 | K8: 0.00 | L8: 2.00 | M8: 邹小华 | N8: 包装服务 | O8: =VLOOKUP(C8,Sheet2!A:C,2,FALSE) -> 取宝-物流服务 | P8: =VLOOKUP(C8,Sheet2!G:H,2,FALSE) -> 186****6788 | Q8: 东莞市中汇信息技术有限公司
A9: 7 | B9: 12-01 | C9: SF3262378607753 | D9: 东莞 | E9: 东莞 | F9: 邹小华 | G9: 1.000 | H9: 顺丰标快 | I9: 寄转第三方 | J9: 11.00 | K9: 0.00 | L9: 11.00 | M9: 邹小华 | N9: 运费 | O9: =VLOOKUP(C9,Sheet2!A:C,2,FALSE) -> 取宝-物流服务 | P9: =VLOOKUP(C9,Sheet2!G:H,2,FALSE) -> 186****6788 | Q9: 东莞市中汇信息技术有限公司
A10: 8 | B10: 12-01 | C10: SF3295326848005 | D10: 东莞 | E10: 东莞 | F10: 邹小华 | G10: 1.000 | H10: 顺丰标快 | I10: 寄转第三方 | J10: 11.00 | K10: 0.00 | L10: 11.00 | M10: 邹小华 | N10: 运费 | O10: =VLOOKUP(C10,Sheet2!A:C,2,FALSE) -> 取宝-物流服务 | P10: =VLOOKUP(C10,Sheet2!G:H,2,FALSE) -> 186****6788 | Q10: 东莞市中汇信息技术有限公司
A11: 9 | B11: 12-01 | C11: SF3295326848005 | D11: 东莞 | E11: 东莞 | F11: 邹小华 | G11: 0.000 | H11: 顺丰标快 | I11: 寄转第三方 | J11: 1.00 | K11: 0.00 | L11: 1.00 | M11: 邹小华 | N11: 包装服务 | O11: =VLOOKUP(C11,Sheet2!A:C,2,FALSE) -> 取宝-物流服务 | P11: =VLOOKUP(C11,Sheet2!G:H,2,FALSE) -> 186****6788 | Q11: 东莞市中汇信息技术有限公司
A12: 10 | B12: 12-01 | C12: SF3295364078732 | D12: 雅安 | E12: 成都/资阳/眉山 | F12: 文刚 | G12: 1.000 | H12: 顺丰标快 | I12: 寄转第三方 | J12: 13.00 | K12: 0.00 | L12: 13.00 | M12: 文刚 | N12: 运费 | O12: =VLOOKUP(C12,Sheet2!A:C,2,FALSE) -> 取宝-物流服务 | P12: =VLOOKUP(C12,Sheet2!G:H,2,FALSE) -> 134****6101 | Q12: 成都江源易通信息技术有限公司
A13: 11 | B13: 12-01 | C13: SF3295364078732 | D13: 雅安 | E13: 成都/资阳/眉山 | F13: 文刚 | G13: 0.000 | H13: 顺丰标快 | I13: 寄转第三方 | J13: 2.00 | K13: 0.00 | L13: 2.00 | M13: 文刚 | N13: 包装服务 | O13: =VLOOKUP(C13,Sheet2!A:C,2,FALSE) -> 取宝-物流服务 | P13: =VLOOKUP(C13,Sheet2!G:H,2,FALSE) -> 134****6101 | Q13: 成都江源易通信息技术有限公司
A14: 12 | B14: 12-01 | C14: SF3295364078769 | D14: 雅安 | E14: 成都/资阳/眉山 | F14: 文刚 | G14: 1.000 | H14: 顺丰标快 | I14: 寄转第三方 | J14: 13.00 | K14: 0.00 | L14: 13.00 | M14: 文刚 | N14: 运费 | O14: =VLOOKUP(C14,Sheet2!A:C,2,FALSE) -> 取宝-物流服务 | P14: =VLOOKUP(C14,Sheet2!G:H,2,FALSE) -> 134****6101 | Q14: 成都江源易通信息技术有限公司
... A20: 18 | B20: 12-02 | C20: SF3262378607753 | D20: 东莞 | E20: 东莞 | F20: 邹小华 | G20: 0.000 | H20: 顺丰标快 | I20: 寄付 | J20: 6.00 | K20: 0.00 | L20: 6.00 | M20: 邹小华 | N20: 收件微派 | O20: =VLOOKUP(C20,Sheet2!A:C,2,FALSE) -> 取宝-物流服务 | P20: =VLOOKUP(C20,Sheet2!G:H,2,FALSE) -> 186****6788 | Q20: 东莞市中汇信息技术有限公司
A21: 19 | B21: 12-02 | C21: SF3262992584639 | D21: 深圳 | E21: 东莞 | F21: 广东久益智付科技有限公司 | G21: 1.000 | H21: 顺丰标快 | I21: 寄转第三方 | J21: 13.00 | K21: 0.00 | L21: 13.00 | M21: 吴广继 | N21: 运费 | O21: =VLOOKUP(C21,Sheet2!A:C,2,FALSE) -> 取宝-仅物流 | P21: 130****4667‎‎‎‬‬‬ | Q21: 广东久益智付科技有限公司
A22: 20 | B22: 12-02 | C22: SF3295326848005 | D22: 东莞 | E22: 东莞 | F22: 邹小华 | G22: 0.000 | H22: 顺丰标快 | I22: 寄付 | J22: 6.00 | K22: 0.00 | L22: 6.00 | M22: 邹小华 | N22: 收件微派 | O22: =VLOOKUP(C22,Sheet2!A:C,2,FALSE) -> 取宝-物流服务 | P22: =VLOOKUP(C22,Sheet2!G:H,2,FALSE) -> 186****6788 | Q22: 东莞市中汇信息技术有限公司
A23: 21 | B23: 12-02 | C23: SF3295364078732 | D23: 雅安 | E23: 成都/资阳/眉山 | F23: 文刚 | G23: 0.000 | H23: 顺丰标快 | I23: 寄付 | J23: 6.00 | K23: 0.00 | L23: 6.00 | M23: 文刚 | N23: 收件微派 | O23: =VLOOKUP(C23,Sheet2!A:C,2,FALSE) -> 取宝-物流服务 | P23: =VLOOKUP(C23,Sheet2!G:H,2,FALSE) -> 134****6101 | Q23: 成都江源易通信息技术有限公司
A24: 22 | B24: 12-02 | C24: SF3295364078769 | D24: 雅安 | E24: 成都/资阳/眉山 | F24: 文刚 | G24: 0.000 | H24: 顺丰标快 | I24: 寄付 | J24: 6.00 | K24: 0.00 | L24: 6.00 | M24: 文刚 | N24: 收件微派 | O24: =VLOOKUP(C24,Sheet2!A:C,2,FALSE) -> 取宝-物流服务 | P24: =VLOOKUP(C24,Sheet2!G:H,2,FALSE) -> 134****6101 | Q24: 成都江源易通信息技术有限公司
A25: 23 | B25: 12-02 | C25: SF3295365022962 | D25: 东莞 | E25: 东莞 | F25: 邹小华 | G25: 0.000 | H25: 顺丰标快 | I25: 寄付 | J25: 3.00 | K25: 0.00 | L25: 3.00 | M25: 邹小华 | N25: 收件微派 | O25: =VLOOKUP(C25,Sheet2!A:C,2,FALSE) -> 立充充电宝取机柜-物流服务 | P25: =VLOOKUP(C25,Sheet2!G:H,2,FALSE) -> 186****6788 | Q25: 东莞市中汇信息技术有限公司
A26: 24 | B26: 12-02 | C26: SF3295365941133 | D26: 东莞 | E26: 东莞 | F26: 邹小华 | G26: 0.000 | H26: 顺丰标快 | I26: 寄付 | J26: 6.00 | K26: 0.00 | L26: 6.00 | M26: 邹小华 | N26: 收件微派 | O26: =VLOOKUP(C26,Sheet2!A:C,2,FALSE) -> 取宝-物流服务 | P26: =VLOOKUP(C26,Sheet2!G:H,2,FALSE) -> 186****6788 | Q26: 东莞市中汇信息技术有限公司
A27: 25 | B27: 12-03 | C27: SF3262004095424 | D27: 深圳 | E27: 东莞 | F27: 吴珊珊 | G27: 1.000 | H27: 顺丰标快 | I27: 寄转第三方 | J27: 13.00 | K27: 0.00 | L27: 13.00 | M27: 饶云普 | N27: 运费 | O27: =VLOOKUP(C27,Sheet2!A:C,2,FALSE) -> 立充充电宝取机柜-仅服务 | P27: =VLOOKUP(C27,Sheet2!G:H,2,FALSE) -> 130****4667 | Q27: 广东久益智付科技有限公司
A28: 26 | B28: 12-03 | C28: SF3262004095424 | D28: 深圳 | E28: 东莞 | F28: 吴珊珊 | G28: 0.000 | H28: 顺丰标快 | I28: 寄转第三方 | J28: 1.00 | K28: 0.00 | L28: 1.00 | M28: 饶云普 | N28: 包装服务 | O28: =VLOOKUP(C28,Sheet2!A:C,2,FALSE) -> 立充充电宝取机柜-仅服务 | P28: =VLOOKUP(C28,Sheet2!G:H,2,FALSE) -> 130****4667 | Q28: 广东久益智付科技有限公司
A29: 27 | B29: 12-03 | C29: SF3262004095497 | D29: 深圳 | E29: 东莞 | F29: 吴珊珊 | G29: 2.300 | H29: 顺丰标快 | I29: 寄转第三方 | J29: 16.00 | K29: 0.00 | L29: 16.00 | M29: 饶云普 | N29: 运费 | O29: =VLOOKUP(C29,Sheet2!A:C,2,FALSE) -> 立充充电宝取机柜-仅服务 | P29: =VLOOKUP(C29,Sheet2!G:H,2,FALSE) -> 130****4667 | Q29: 广东久益智付科技有限公司
A30: 28 | B30: 12-03 | C30: SF3262004095497 | D30: 深圳 | E30: 东莞 | F30: 吴珊珊 | G30: 0.000 | H30: 顺丰标快 | I30: 寄转第三方 | J30: 4.00 | K30: 0.00 | L30: 4.00 | M30: 饶云普 | N30: 包装服务 | O30: =VLOOKUP(C30,Sheet2!A:C,2,FALSE) -> 立充充电宝取机柜-仅服务 | P30: =VLOOKUP(C30,Sheet2!G:H,2,FALSE) -> 130****4667 | Q30: 广东久益智付科技有限公司
A31: 29 | B31: 12-03 | C31: SF3262004095742 | D31: 深圳 | E31: 东莞 | F31: 吴珊珊 | G31: 1.000 | H31: 顺丰标快 | I31: 寄转第三方 | J31: 13.00 | K31: 0.00 | L31: 13.00 | M31: 饶云普 | N31: 运费 | O31: =VLOOKUP(C31,Sheet2!A:C,2,FALSE) -> 立充充电宝取机柜-仅服务 | P31: =VLOOKUP(C31,Sheet2!G:H,2,FALSE) -> 130****4667 | Q31: 广东久益智付科技有限公司
A32: 30 | B32: 12-03 | C32: SF3262004095742 | D32: 深圳 | E32: 东莞 | F32: 吴珊珊 | G32: 0.000 | H32: 顺丰标快 | I32: 寄转第三方 | J32: 1.00 | K32: 0.00 | L32: 1.00 | M32: 饶云普 | N32: 包装服务 | O32: =VLOOKUP(C32,Sheet2!A:C,2,FALSE) -> 立充充电宝取机柜-仅服务 | P32: =VLOOKUP(C32,Sheet2!G:H,2,FALSE) -> 130****4667 | Q32: 广东久益智付科技有限公司
A33: 31 | B33: 12-03 | C33: SF3262004097071 | D33: 深圳 | E33: 东莞 | F33: 吴珊珊 | G33: 1.000 | H33: 顺丰标快 | I33: 寄转第三方 | J33: 13.00 | K33: 0.00 | L33: 13.00 | M33: 饶云普 | N33: 运费 | O33: =VLOOKUP(C33,Sheet2!A:C,2,FALSE) -> 立充充电宝取机柜-仅服务 | P33: =VLOOKUP(C33,Sheet2!G:H,2,FALSE) -> 130****4667 | Q33: 广东久益智付科技有限公司
... A213: 211 | B213: 12-15 | C213: SF3260488516087 | D213: 深圳 | E213: 东莞 | F213: 吴珊珊 | G213: 0.000 | H213: 顺丰标快 | I213: 寄转第三方 | J213: 1.00 | K213: 0.00 | L213: 1.00 | M213: 饶云普 | N213: 包装服务 | O213: =VLOOKUP(C213,Sheet2!A:C,2,FALSE) -> 立充充电宝取机柜-仅服务 | P213: =VLOOKUP(C213,Sheet2!G:H,2,FALSE) -> 130****4667 | Q213: 广东久益智付科技有限公司
A214: 212 | B214: 12-15 | C214: SF3260488516096 | D214: 深圳 | E214: 东莞 | F214: 吴珊珊 | G214: 9.800 | H214: 顺丰标快 | I214: 寄转第三方 | J214: 31.00 | K214: 0.00 | L214: 31.00 | M214: 饶云普 | N214: 运费 | O214: 立充充电宝取机柜-仅服务 | P214: =VLOOKUP(C214,Sheet2!G:H,2,FALSE) -> 130****4667 | Q214: 广东久益智付科技有限公司
A215: 213 | B215: 12-15 | C215: SF3260488516096 | D215: 深圳 | E215: 东莞 | F215: 吴珊珊 | G215: 0.000 | H215: 顺丰标快 | I215: 寄转第三方 | J215: 15.00 | K215: 0.00 | L215: 15.00 | M215: 饶云普 | N215: 包装服务 | O215: 立充充电宝取机柜-仅服务 | P215: =VLOOKUP(C215,Sheet2!G:H,2,FALSE) -> 130****4667 | Q215: 广东久益智付科技有限公司
A216: 214 | B216: 12-15 | C216: SF3260488516906 | D216: 深圳 | E216: 东莞 | F216: 吴珊珊 | G216: 1.000 | H216: 顺丰标快 | I216: 寄转第三方 | J216: 13.00 | K216: 0.00 | L216: 13.00 | M216: 饶云普 | N216: 运费 | O216: =VLOOKUP(C216,Sheet2!A:C,2,FALSE) -> 立充充电宝取机柜-仅服务 | P216: =VLOOKUP(C216,Sheet2!G:H,2,FALSE) -> 130****4667 | Q216: 广东久益智付科技有限公司
A217: 215 | B217: 12-15 | C217: SF3260488516906 | D217: 深圳 | E217: 东莞 | F217: 吴珊珊 | G217: 0.000 | H217: 顺丰标快 | I217: 寄转第三方 | J217: 1.00 | K217: 0.00 | L217: 1.00 | M217: 饶云普 | N217: 包装服务 | O217: =VLOOKUP(C217,Sheet2!A:C,2,FALSE) -> 立充充电宝取机柜-仅服务 | P217: =VLOOKUP(C217,Sheet2!G:H,2,FALSE) -> 130****4667 | Q217: 广东久益智付科技有限公司
A218: 216 | B218: 12-15 | C218: SF3260488516979 | D218: 深圳 | E218: 东莞 | F218: 吴珊珊 | G218: 1.000 | H218: 顺丰标快 | I218: 寄转第三方 | J218: 13.00 | K218: 0.00 | L218: 13.00 | M218: 饶云普 | N218: 运费 | O218: =VLOOKUP(C218,Sheet2!A:C,2,FALSE) -> 立充充电宝取机柜-仅服务 | P218: =VLOOKUP(C218,Sheet2!G:H,2,FALSE) -> 130****4667 | Q218: 广东久益智付科技有限公司
A219: 217 | B219: 12-15 | C219: SF3260488516979 | D219: 深圳 | E219: 东莞 | F219: 吴珊珊 | G219: 0.000 | H219: 顺丰标快 | I219: 寄转第三方 | J219: 1.00 | K219: 0.00 | L219: 1.00 | M219: 饶云普 | N219: 包装服务 | O219: =VLOOKUP(C219,Sheet2!A:C,2,FALSE) -> 立充充电宝取机柜-仅服务 | P219: =VLOOKUP(C219,Sheet2!G:H,2,FALSE) -> 130****4667 | Q219: 广东久益智付科技有限公司
A220: 218 | B220: 12-15 | C220: SF3260488518614 | D220: 深圳 | E220: 东莞 | F220: 吴珊珊 | G220: 3.000 | H220: 顺丰标快 | I220: 寄转第三方 | J220: 17.00 | K220: 0.00 | L220: 17.00 | M220: 饶云普 | N220: 运费 | O220: =VLOOKUP(C220,Sheet2!A:C,2,FALSE) -> 立充充电宝取机柜-仅服务 | P220: =VLOOKUP(C220,Sheet2!G:H,2,FALSE) -> 130****4667 | Q220: 广东久益智付科技有限公司
A221: 219 | B221: 12-15 | C221: SF3260488518614 | D221: 深圳 | E221: 东莞 | F221: 吴珊珊 | G221: 0.000 | H221: 顺丰标快 | I221: 寄转第三方 | J221: 5.00 | K221: 0.00 | L221: 5.00 | M221: 饶云普 | N221: 包装服务 | O221: =VLOOKUP(C221,Sheet2!A:C,2,FALSE) -> 立充充电宝取机柜-仅服务 | P221: =VLOOKUP(C221,Sheet2!G:H,2,FALSE) -> 130****4667 | Q221: 广东久益智付科技有限公司
A222: 220 | B222: 12-15 | C222: SF3260491849237 | D222: 成都/资阳/眉山 | E222: 成都/资阳/眉山 | F222: 周涛 | G222: 1.000 | H222: 顺丰标快 | I222: 寄转第三方 | J222: 11.00 | K222: 0.00 | L222: 11.00 | M222: 江源 | N222: 运费 | O222: =VLOOKUP(C222,Sheet2!A:C,2,FALSE) -> 补宝-物流服务 | P222: =VLOOKUP(C222,Sheet2!G:H,2,FALSE) -> 134****6101 | Q222: 成都江源易通信息技术有限公司
A223: 221 | B223: 12-15 | C223: SF3260491849334 | D223: 成都/资阳/眉山 | E223: 成都/资阳/眉山 | F223: 周涛 | G223: 1.000 | H223: 顺丰标快 | I223: 寄转第三方 | J223: 11.00 | K223: 0.00 | L223: 11.00 | M223: 江源 | N223: 运费 | O223: =VLOOKUP(C223,Sheet2!A:C,2,FALSE) -> 补宝-物流服务 | P223: =VLOOKUP(C223,Sheet2!G:H,2,FALSE) -> 134****6101 | Q223: 成都江源易通信息技术有限公司
A224: 222 | B224: 12-15 | C224: SF3260499115096 | D224: 成都/资阳/眉山 | E224: 成都/资阳/眉山 | F224: 代俊峰 | G224: 1.000 | H224: 顺丰标快 | I224: 寄转第三方 | J224: 11.00 | K224: 0.00 | L224: 11.00 | M224: 代俊峰 | N224: 运费 | O224: =VLOOKUP(C224,Sheet2!A:C,2,FALSE) -> 补宝-物流服务 | P224: =VLOOKUP(C224,Sheet2!G:H,2,FALSE) -> 134****6101 | Q224: 成都江源易通信息技术有限公司
A225: 223 | B225: 12-15 | C225: SF3260499115906 | D225: 成都/资阳/眉山 | E225: 成都/资阳/眉山 | F225: 代俊峰 | G225: 1.000 | H225: 顺丰标快 | I225: 寄转第三方 | J225: 11.00 | K225: 0.00 | L225: 11.00 | M225: 代俊峰 | N225: 运费 | O225: =VLOOKUP(C225,Sheet2!A:C,2,FALSE) -> 补宝-物流服务 | P225: =VLOOKUP(C225,Sheet2!G:H,2,FALSE) -> 134****6101 | Q225: 成都江源易通信息技术有限公司
A226: 224 | B226: 12-15 | C226: SF3260956999481 | D226: 北京 | E226: 北京 | F226: 何立林 | G226: 0.000 | H226: 顺丰标快 | I226: 寄付 | J226: 3.00 | K226: 0.00 | L226: 3.00 | M226: 何立林 | N226: 收件微派 | O226: =VLOOKUP(C226,Sheet2!A:C,2,FALSE) -> 立充充电宝取机柜-物流服务 | P226: =VLOOKUP(C226,Sheet2!G:H,2,FALSE) -> 136****7868 | Q226: 山东省点线面网络科技有限公司
A227: 225 | B227: 12-16 | C227: SF3261282600597 | D227: 成都/资阳/眉山 | E227: 成都/资阳/眉山 | F227: 刘洪 | G227: 1.000 | H227: 顺丰标快 | I227: 寄转第三方 | J227: 11.00 | K227: 0.00 | L227: 11.00 | M227: 江源 | N227: 运费 | O227: =VLOOKUP(C227,Sheet2!A:C,2,FALSE) -> 补宝-物流服务 | P227: =VLOOKUP(C227,Sheet2!G:H,2,FALSE) -> 134****6101 | Q227: 成都江源易通信息技术有限公司
... A364: 362 | B364: 12-24 | C364: SF5105056506251 | D364: 成都/资阳/眉山 | E364: 雅安 | F364: 李世云 | G364: 0.000 | H364: 顺丰标快 | I364: 寄付 | J364: 6.00 | K364: 0.00 | L364: 6.00 | M364: 江源 | N364: 派件微派 | O364: =VLOOKUP(C364,Sheet2!A:C,2,FALSE) -> 补宝-物流服务 | P364: =VLOOKUP(C364,Sheet2!G:H,2,FALSE) -> 134****6101 | Q364: 成都江源易通信息技术有限公司
A365: 363 | B365: 12-24 | C365: SF5105265169872 | D365: 沈阳/铁岭/抚顺 | E365: 大连 | F365: 唐先生 | G365: 2.500 | H365: 顺丰标快 | I365: 寄转第三方 | J365: 16.00 | K365: 0.00 | L365: 16.00 | M365: 周玉红 | N365: 运费 | O365: 立充充电宝取机柜-仅服务 | P365: =VLOOKUP(C365,Sheet2!G:H,2,FALSE) -> 165****7666 | Q365: 深圳市锐丰伟业科技有限公司
A366: 364 | B366: 12-24 | C366: SF5105265169872 | D366: 沈阳/铁岭/抚顺 | E366: 大连 | F366: 唐先生 | G366: 0.000 | H366: 顺丰标快 | I366: 寄转第三方 | J366: 5.50 | K366: 0.00 | L366: 5.50 | M366: 周玉红 | N366: 包装服务 | O366: 立充充电宝取机柜-仅服务 | P366: =VLOOKUP(C366,Sheet2!G:H,2,FALSE) -> 165****7666 | Q366: 深圳市锐丰伟业科技有限公司
A367: 365 | B367: 12-24 | C367: SF5105265388697 | D367: 沈阳/铁岭/抚顺 | E367: 大连 | F367: 唐先生 | G367: 1.000 | H367: 顺丰标快 | I367: 寄转第三方 | J367: 13.00 | K367: 0.00 | L367: 13.00 | M367: 周玉红 | N367: 运费 | O367: =VLOOKUP(C367,Sheet2!A:C,2,FALSE) -> 取宝-仅物流 | P367: =VLOOKUP(C367,Sheet2!G:H,2,FALSE) -> 165****7666 | Q367: 深圳市锐丰伟业科技有限公司
A368: 366 | B368: 12-24 | C368: SF5105265388697 | D368: 沈阳/铁岭/抚顺 | E368: 大连 | F368: 唐先生 | G368: 0.000 | H368: 顺丰标快 | I368: 寄转第三方 | J368: 1.00 | K368: 0.00 | L368: 1.00 | M368: 周玉红 | N368: 包装服务 | O368: =VLOOKUP(C368,Sheet2!A:C,2,FALSE) -> 取宝-仅物流 | P368: =VLOOKUP(C368,Sheet2!G:H,2,FALSE) -> 165****7666 | Q368: 深圳市锐丰伟业科技有限公司
A369: 367 | B369: 12-25 | C369: SF3266463124493 | D369: 东莞 | E369: 东莞 | F369: 邹小华 | G369: 0.000 | H369: 顺丰标快 | I369: 寄付 | J369: 6.00 | K369: 0.00 | L369: 6.00 | M369: 邹小华 | N369: 收件微派 | O369: =VLOOKUP(C369,Sheet2!A:C,2,FALSE) -> 取宝-物流服务 | P369: =VLOOKUP(C369,Sheet2!G:H,2,FALSE) -> 186****6788 | Q369: 东莞市中汇信息技术有限公司
A370: 368 | B370: 12-25 | C370: SF3266463124793 | D370: 东莞 | E370: 东莞 | F370: 邹小华 | G370: 0.000 | H370: 顺丰标快 | I370: 寄付 | J370: 6.00 | K370: 0.00 | L370: 6.00 | M370: 邹小华 | N370: 收件微派 | O370: =VLOOKUP(C370,Sheet2!A:C,2,FALSE) -> 取宝-物流服务 | P370: =VLOOKUP(C370,Sheet2!G:H,2,FALSE) -> 186****6788 | Q370: 东莞市中汇信息技术有限公司
A371: 369 | B371: 12-25 | C371: SF3266463665558 | D371: 东莞 | E371: 东莞 | F371: 邹小华 | G371: 0.000 | H371: 顺丰标快 | I371: 寄付 | J371: 3.00 | K371: 0.00 | L371: 3.00 | M371: 邹小华 | N371: 收件微派 | O371: =VLOOKUP(C371,Sheet2!A:C,2,FALSE) -> 立充充电宝取机柜-物流服务 | P371: =VLOOKUP(C371,Sheet2!G:H,2,FALSE) -> 186****6788 | Q371: 东莞市中汇信息技术有限公司
A372: 370 | B372: 12-26 | C372: SF3268270973716 | D372: 保定/雄安新区 | E372: 沈阳/铁岭/抚顺 | F372: 贾微 | G372: 1.000 | H372: 顺丰标快 | I372: 寄转第三方 | J372: 16.00 | K372: 0.00 | L372: 16.00 | M372: 孙浩特色牛杂面板面 | N372: 运费 | O372: =VLOOKUP(C372,Sheet2!A:C,2,FALSE) -> 立充充电宝取机柜-物流服务 | P372: =VLOOKUP(C372,Sheet2!G:H,2,FALSE) -> 131****2614 | Q372: 辽宁深蓝数据服务有限公司
A373: 371 | B373: 12-26 | C373: SF3268270973716 | D373: 保定/雄安新区 | E373: 沈阳/铁岭/抚顺 | F373: 贾微 | G373: 0.000 | H373: 顺丰标快 | I373: 寄转第三方 | J373: 2.00 | K373: 0.00 | L373: 2.00 | M373: 孙浩特色牛杂面板面 | N373: 包装服务 | O373: =VLOOKUP(C373,Sheet2!A:C,2,FALSE) -> 立充充电宝取机柜-物流服务 | P373: =VLOOKUP(C373,Sheet2!G:H,2,FALSE) -> 131****2614 | Q373: 辽宁深蓝数据服务有限公司
A374: 372 | B374: 12-26 | C374: SF3268275983233 | D374: 保定/雄安新区 | E374: 沈阳/铁岭/抚顺 | F374: 贾微 | G374: 4.600 | H374: 顺丰标快 | I374: 寄转第三方 | J374: 38.00 | K374: 0.00 | L374: 38.00 | M374: 孙浩特色牛杂面板面 | N374: 运费 | O374: =VLOOKUP(C374,Sheet2!A:C,2,FALSE) -> 立充充电宝取机柜-物流服务 | P374: =VLOOKUP(C374,Sheet2!G:H,2,FALSE) -> 131****2614 | Q374: 辽宁深蓝数据服务有限公司
A375: 373 | B375: 12-26 | C375: SF3268275983233 | D375: 保定/雄安新区 | E375: 沈阳/铁岭/抚顺 | F375: 贾微 | G375: 0.000 | H375: 顺丰标快 | I375: 寄转第三方 | J375: 6.00 | K375: 0.00 | L375: 6.00 | M375: 孙浩特色牛杂面板面 | N375: 包装服务 | O375: =VLOOKUP(C375,Sheet2!A:C,2,FALSE) -> 立充充电宝取机柜-物流服务 | P375: =VLOOKUP(C375,Sheet2!G:H,2,FALSE) -> 131****2614 | Q375: 辽宁深蓝数据服务有限公司
A376: 374 | B376: 12-26 | C376: SF3268275983358 | D376: 保定/雄安新区 | E376: 沈阳/铁岭/抚顺 | F376: 贾微 | G376: 1.000 | H376: 顺丰标快 | I376: 寄转第三方 | J376: 16.00 | K376: 0.00 | L376: 16.00 | M376: 孙浩特色牛杂面板面 | N376: 运费 | O376: =VLOOKUP(C376,Sheet2!A:C,2,FALSE) -> 立充充电宝取机柜-物流服务 | P376: =VLOOKUP(C376,Sheet2!G:H,2,FALSE) -> 131****2614 | Q376: 辽宁深蓝数据服务有限公司
A377: 375 | B377: 12-26 | C377: SF3268275983358 | D377: 保定/雄安新区 | E377: 沈阳/铁岭/抚顺 | F377: 贾微 | G377: 0.000 | H377: 顺丰标快 | I377: 寄转第三方 | J377: 2.00 | K377: 0.00 | L377: 2.00 | M377: 孙浩特色牛杂面板面 | N377: 包装服务 | O377: =VLOOKUP(C377,Sheet2!A:C,2,FALSE) -> 立充充电宝取机柜-物流服务 | P377: =VLOOKUP(C377,Sheet2!G:H,2,FALSE) -> 131****2614 | Q377: 辽宁深蓝数据服务有限公司
A378: 376 | B378: 12-26 | C378: SF3268277986250 | D378: 深圳 | E378: 东莞 | F378: 吴珊珊 | G378: 1.000 | H378: 顺丰标快 | I378: 寄转第三方 | J378: 13.00 | K378: 0.00 | L378: 13.00 | M378: 饶云普 | N378: 运费 | O378: 立充充电宝取机柜-仅服务 | P378: =VLOOKUP(C378,Sheet2!G:H,2,FALSE) -> 130****4667 | Q378: 广东久益智付科技有限公司
A379: 377 | B379: 12-26 | C379: SF3268277986250 | D379: 深圳 | E379: 东莞 | F379: 吴珊珊 | G379: 0.000 | H379: 顺丰标快 | I379: 寄转第三方 | J379: 1.00 | K379: 0.00 | L379: 1.00 | M379: 饶云普 | N379: 包装服务 | O379: 立充充电宝取机柜-仅服务 | P379: =VLOOKUP(C379,Sheet2!G:H,2,FALSE) -> 130****4667 | Q379: 广东久益智付科技有限公司
A380: 378 | B380: 12-26 | C380: SF3268938193753 | D380: 东莞 | E380: 东莞 | F380: 邹小华 | G380: 1.000 | H380: 顺丰标快 | I380: 寄转第三方 | J380: 11.00 | K380: 0.00 | L380: 11.00 | M380: 邹小华 | N380: 运费 | O380: =VLOOKUP(C380,Sheet2!A:C,2,FALSE) -> 取宝-物流服务 | P380: =VLOOKUP(C380,Sheet2!G:H,2,FALSE) -> 186****6788 | Q380: 东莞市中汇信息技术有限公司
A381: 379 | B381: 12-26 | C381: SF3268938193753 | D381: 东莞 | E381: 东莞 | F381: 邹小华 | G381: 0.000 | H381: 顺丰标快 | I381: 寄转第三方 | J381: 1.00 | K381: 0.00 | L381: 1.00 | M381: 邹小华 | N381: 包装服务 | O381: =VLOOKUP(C381,Sheet2!A:C,2,FALSE) -> 取宝-物流服务 | P381: =VLOOKUP(C381,Sheet2!G:H,2,FALSE) -> 186****6788 | Q381: 东莞市中汇信息技术有限公司
A382: 380 | B382: 12-26 | C382: SF5105887343533 | D382: 广州 | E382: 东莞 | F382: 邹小华 | G382: 3.000 | H382: 顺丰标快 | I382: 寄转第三方 | J382: 17.00 | K382: 0.00 | L382: 17.00 | M382: 邹小华 | N382: 运费 | O382: =VLOOKUP(C382,Sheet2!A:C,2,FALSE) -> 立充充电宝取机柜-物流服务 | P382: =VLOOKUP(C382,Sheet2!G:H,2,FALSE) -> 186****6788 | Q382: 东莞市中汇信息技术有限公司
A383: 381 | B383: 12-26 | C383: SF5105887343533 | D383: 广州 | E383: 东莞 | F383: 邹小华 | G383: 0.000 | H383: 顺丰标快 | I383: 寄转第三方 | J383: 5.00 | K383: 0.00 | L383: 5.00 | M383: 邹小华 | N383: 包装服务 | O383: =VLOOKUP(C383,Sheet2!A:C,2,FALSE) -> 立充充电宝取机柜-物流服务 | P383: =VLOOKUP(C383,Sheet2!G:H,2,FALSE) -> 186****6788 | Q383: 东莞市中汇信息技术有限公司
A384: 382 | B384: 12-26 | C384: SF5105887607240 | D384: 广州 | E384: 东莞 | F384: 邹小华 | G384: 1.000 | H384: 顺丰标快 | I384: 寄转第三方 | J384: 13.00 | K384: 0.00 | L384: 13.00 | M384: 邹小华 | N384: 运费 | O384: =VLOOKUP(C384,Sheet2!A:C,2,FALSE) -> 取宝-物流服务 | P384: =VLOOKUP(C384,Sheet2!G:H,2,FALSE) -> 186****6788 | Q384: 东莞市中汇信息技术有限公司
A385: 383 | B385: 12-26 | C385: SF5105887607240 | D385: 广州 | E385: 东莞 | F385: 邹小华 | G385: 0.000 | H385: 顺丰标快 | I385: 寄转第三方 | J385: 1.00 | K385: 0.00 | L385: 1.00 | M385: 邹小华 | N385: 包装服务 | O385: =VLOOKUP(C385,Sheet2!A:C,2,FALSE) -> 取宝-物流服务 | P385: =VLOOKUP(C385,Sheet2!G:H,2,FALSE) -> 186****6788 | Q385: 东莞市中汇信息技术有限公司
A386: 384 | B386: 12-26 | C386: SF5105887607286 | D386: 广州 | E386: 东莞 | F386: 邹小华 | G386: 1.000 | H386: 顺丰标快 | I386: 寄转第三方 | J386: 13.00 | K386: 0.00 | L386: 13.00 | M386: 邹小华 | N386: 运费 | O386: =VLOOKUP(C386,Sheet2!A:C,2,FALSE) -> 取宝-物流服务 | P386: =VLOOKUP(C386,Sheet2!G:H,2,FALSE) -> 186****6788 | Q386: 东莞市中汇信息技术有限公司
A387: 385 | B387: 12-26 | C387: SF5105887607286 | D387: 广州 | E387: 东莞 | F387: 邹小华 | G387: 0.000 | H387: 顺丰标快 | I387: 寄转第三方 | J387: 1.00 | K387: 0.00 | L387: 1.00 | M387: 邹小华 | N387: 包装服务 | O387: =VLOOKUP(C387,Sheet2!A:C,2,FALSE) -> 取宝-物流服务 | P387: =VLOOKUP(C387,Sheet2!G:H,2,FALSE) -> 186****6788 | Q387: 东莞市中汇信息技术有限公司
A388: 386 | B388: 12-26 | C388: SF5106531594533 | D388: 东莞 | E388: 东莞 | F388: 邹小华 | G388: 3.100 | H388: 顺丰标快 | I388: 寄转第三方 | J388: 13.00 | K388: 0.00 | L388: 13.00 | M388: 邹小华 | N388: 运费 | O388: =VLOOKUP(C388,Sheet2!A:C,2,FALSE) -> 立充充电宝取机柜-物流服务 | P388: =VLOOKUP(C388,Sheet2!G:H,2,FALSE) -> 186****6788 | Q388: 东莞市中汇信息技术有限公司
A389: 387 | B389: 12-26 | C389: SF5106531594533 | D389: 东莞 | E389: 东莞 | F389: 邹小华 | G389: 0.000 | H389: 顺丰标快 | I389: 寄转第三方 | J389: 5.00 | K389: 0.00 | L389: 5.00 | M389: 邹小华 | N389: 包装服务 | O389: =VLOOKUP(C389,Sheet2!A:C,2,FALSE) -> 立充充电宝取机柜-物流服务 | P389: =VLOOKUP(C389,Sheet2!G:H,2,FALSE) -> 186****6788 | Q389: 东莞市中汇信息技术有限公司
A390: 388 | B390: 12-26 | C390: SF5106533894875 | D390: 东莞 | E390: 东莞 | F390: 邹小华 | G390: 1.000 | H390: 顺丰标快 | I390: 寄转第三方 | J390: 11.00 | K390: 0.00 | L390: 11.00 | M390: 邹小华 | N390: 运费 | O390: =VLOOKUP(C390,Sheet2!A:C,2,FALSE) -> 取宝-物流服务 | P390: =VLOOKUP(C390,Sheet2!G:H,2,FALSE) -> 186****6788 | Q390: 东莞市中汇信息技术有限公司
A391: 389 | B391: 12-26 | C391: SF5106533894875 | D391: 东莞 | E391: 东莞 | F391: 邹小华 | G391: 0.000 | H391: 顺丰标快 | I391: 寄转第三方 | J391: 1.00 | K391: 0.00 | L391: 1.00 | M391: 邹小华 | N391: 包装服务 | O391: =VLOOKUP(C391,Sheet2!A:C,2,FALSE) -> 取宝-物流服务 | P391: =VLOOKUP(C391,Sheet2!G:H,2,FALSE) -> 186****6788 | Q391: 东莞市中汇信息技术有限公司
A392: 390 | B392: 12-26 | C392: SF5106557446946 | D392: 深圳 | E392: 东莞 | F392: 吴珊珊 | G392: 3.000 | H392: 顺丰标快 | I392: 寄转第三方 | J392: 17.00 | K392: 0.00 | L392: 17.00 | M392: 饶云普 | N392: 运费 | O392: 立充充电宝取机柜-仅服务 | P392: =VLOOKUP(C392,Sheet2!G:H,2,FALSE) -> 130****4667 | Q392: 广东久益智付科技有限公司
A393: 391 | B393: 12-26 | C393: SF5106557446946 | D393: 深圳 | E393: 东莞 | F393: 吴珊珊 | G393: 0.000 | H393: 顺丰标快 | I393: 寄转第三方 | J393: 5.00 | K393: 0.00 | L393: 5.00 | M393: 饶云普 | N393: 包装服务 | O393: 立充充电宝取机柜-仅服务 | P393: =VLOOKUP(C393,Sheet2!G:H,2,FALSE) -> 130****4667 | Q393: 广东久益智付科技有限公司
A394: 392 | B394: 12-26 | C394: SF5106557446982 | D394: 深圳 | E394: 东莞 | F394: 吴珊珊 | G394: 1.000 | H394: 顺丰标快 | I394: 寄转第三方 | J394: 13.00 | K394: 0.00 | L394: 13.00 | M394: 饶云普 | N394: 运费 | O394: 立充充电宝取机柜-仅服务 | P394: =VLOOKUP(C394,Sheet2!G:H,2,FALSE) -> 130****4667 | Q394: 广东久益智付科技有限公司
A395: 393 | B395: 12-26 | C395: SF5106557446982 | D395: 深圳 | E395: 东莞 | F395: 吴珊珊 | G395: 0.000 | H395: 顺丰标快 | I395: 寄转第三方 | J395: 1.00 | K395: 0.00 | L395: 1.00 | M395: 饶云普 | N395: 包装服务 | O395: 立充充电宝取机柜-仅服务 | P395: =VLOOKUP(C395,Sheet2!G:H,2,FALSE) -> 130****4667 | Q395: 广东久益智付科技有限公司
A396: 394 | B396: 12-27 | C396: SF3268270973716 | D396: 保定/雄安新区 | E396: 沈阳/铁岭/抚顺 | F396: 贾微 | G396: 0.000 | H396: 顺丰标快 | I396: 寄付 | J396: 3.00 | K396: 0.00 | L396: 3.00 | M396: 孙浩特色牛杂面板面 | N396: 收件微派 | O396: =VLOOKUP(C396,Sheet2!A:C,2,FALSE) -> 立充充电宝取机柜-物流服务 | P396: =VLOOKUP(C396,Sheet2!G:H,2,FALSE) -> 131****2614 | Q396: 辽宁深蓝数据服务有限公司
A397: 395 | B397: 12-27 | C397: SF3268275983233 | D397: 保定/雄安新区 | E397: 沈阳/铁岭/抚顺 | F397: 贾微 | G397: 0.000 | H397: 顺丰标快 | I397: 寄付 | J397: 3.00 | K397: 0.00 | L397: 3.00 | M397: 孙浩特色牛杂面板面 | N397: 收件微派 | O397: =VLOOKUP(C397,Sheet2!A:C,2,FALSE) -> 立充充电宝取机柜-物流服务 | P397: =VLOOKUP(C397,Sheet2!G:H,2,FALSE) -> 131****2614 | Q397: 辽宁深蓝数据服务有限公司
A398: 396 | B398: 12-27 | C398: SF3268275983358 | D398: 保定/雄安新区 | E398: 沈阳/铁岭/抚顺 | F398: 贾微 | G398: 0.000 | H398: 顺丰标快 | I398: 寄付 | J398: 3.00 | K398: 0.00 | L398: 3.00 | M398: 孙浩特色牛杂面板面 | N398: 收件微派 | O398: =VLOOKUP(C398,Sheet2!A:C,2,FALSE) -> 立充充电宝取机柜-物流服务 | P398: =VLOOKUP(C398,Sheet2!G:H,2,FALSE) -> 131****2614 | Q398: 辽宁深蓝数据服务有限公司
A399: 397 | B399: 12-27 | C399: SF3268938193753 | D399: 东莞 | E399: 东莞 | F399: 邹小华 | G399: 0.000 | H399: 顺丰标快 | I399: 寄付 | J399: 6.00 | K399: 0.00 | L399: 6.00 | M399: 邹小华 | N399: 收件微派 | O399: =VLOOKUP(C399,Sheet2!A:C,2,FALSE) -> 取宝-物流服务 | P399: =VLOOKUP(C399,Sheet2!G:H,2,FALSE) -> 186****6788 | Q399: 东莞市中汇信息技术有限公司
A400: 398 | B400: 12-27 | C400: SF5105887343533 | D400: 广州 | E400: 东莞 | F400: 邹小华 | G400: 0.000 | H400: 顺丰标快 | I400: 寄付 | J400: 3.00 | K400: 0.00 | L400: 3.00 | M400: 邹小华 | N400: 收件微派 | O400: =VLOOKUP(C400,Sheet2!A:C,2,FALSE) -> 立充充电宝取机柜-物流服务 | P400: =VLOOKUP(C400,Sheet2!G:H,2,FALSE) -> 186****6788 | Q400: 东莞市中汇信息技术有限公司
A401: 399 | B401: 12-27 | C401: SF5105887607240 | D401: 广州 | E401: 东莞 | F401: 邹小华 | G401: 0.000 | H401: 顺丰标快 | I401: 寄付 | J401: 6.00 | K401: 0.00 | L401: 6.00 | M401: 邹小华 | N401: 收件微派 | O401: =VLOOKUP(C401,Sheet2!A:C,2,FALSE) -> 取宝-物流服务 | P401: =VLOOKUP(C401,Sheet2!G:H,2,FALSE) -> 186****6788 | Q401: 东莞市中汇信息技术有限公司
A402: 400 | B402: 12-27 | C402: SF5105887607286 | D402: 广州 | E402: 东莞 | F402: 邹小华 | G402: 0.000 | H402: 顺丰标快 | I402: 寄付 | J402: 6.00 | K402: 0.00 | L402: 6.00 | M402: 邹小华 | N402: 收件微派 | O402: =VLOOKUP(C402,Sheet2!A:C,2,FALSE) -> 取宝-物流服务 | P402: =VLOOKUP(C402,Sheet2!G:H,2,FALSE) -> 186****6788 | Q402: 东莞市中汇信息技术有限公司
A403: 401 | B403: 12-27 | C403: SF5106531594533 | D403: 东莞 | E403: 东莞 | F403: 邹小华 | G403: 0.000 | H403: 顺丰标快 | I403: 寄付 | J403: 3.00 | K403: 0.00 | L403: 3.00 | M403: 邹小华 | N403: 收件微派 | O403: =VLOOKUP(C403,Sheet2!A:C,2,FALSE) -> 立充充电宝取机柜-物流服务 | P403: =VLOOKUP(C403,Sheet2!G:H,2,FALSE) -> 186****6788 | Q403: 东莞市中汇信息技术有限公司
A404: 402 | B404: 12-27 | C404: SF5106533894875 | D404: 东莞 | E404: 东莞 | F404: 邹小华 | G404: 0.000 | H404: 顺丰标快 | I404: 寄付 | J404: 6.00 | K404: 0.00 | L404: 6.00 | M404: 邹小华 | N404: 收件微派 | O404: =VLOOKUP(C404,Sheet2!A:C,2,FALSE) -> 取宝-物流服务 | P404: =VLOOKUP(C404,Sheet2!G:H,2,FALSE) -> 186****6788 | Q404: 东莞市中汇信息技术有限公司
A405: 403 | B405: 12-29 | C405: SF3268640105742 | D405: 东莞 | E405: 东莞 | F405: 邹小华 | G405: 1.000 | H405: 顺丰标快 | I405: 寄转第三方 | J405: 11.00 | K405: 0.00 | L405: 11.00 | M405: 邹小华 | N405: 运费 | O405: =VLOOKUP(C405,Sheet2!A:C,2,FALSE) -> 立充充电宝取机柜-物流服务 | P405: =VLOOKUP(C405,Sheet2!G:H,2,FALSE) -> 186****6788 | Q405: 东莞市中汇信息技术有限公司
A406: 404 | B406: 12-29 | C406: SF3268640416024 | D406: 东莞 | E406: 东莞 | F406: 邹小华 | G406: 3.000 | H406: 顺丰标快 | I406: 寄转第三方 | J406: 13.00 | K406: 0.00 | L406: 13.00 | M406: 邹小华 | N406: 运费 | O406: =VLOOKUP(C406,Sheet2!A:C,2,FALSE) -> 立充充电宝取机柜-物流服务 | P406: =VLOOKUP(C406,Sheet2!G:H,2,FALSE) -> 186****6788 | Q406: 东莞市中汇信息技术有限公司
A407: 405 | B407: 12-29 | C407: SF3268640416024 | D407: 东莞 | E407: 东莞 | F407: 邹小华 | G407: 0.000 | H407: 顺丰标快 | I407: 寄转第三方 | J407: 7.00 | K407: 0.00 | L407: 7.00 | M407: 邹小华 | N407: 包装服务 | O407: =VLOOKUP(C407,Sheet2!A:C,2,FALSE) -> 立充充电宝取机柜-物流服务 | P407: =VLOOKUP(C407,Sheet2!G:H,2,FALSE) -> 186****6788 | Q407: 东莞市中汇信息技术有限公司
... A485: 483 | B485: 12-30 | C485: SF5127722066632 | D485: 东莞 | E485: 东莞 | F485: 邹小华 | G485: 0.000 | H485: 顺丰标快 | I485: 寄转第三方 | J485: 2.00 | K485: 0.00 | L485: 2.00 | M485: 邹小华 | N485: 包装服务 | O485: =VLOOKUP(C485,Sheet2!A:C,2,FALSE) -> 取宝-物流服务 | P485: =VLOOKUP(C485,Sheet2!G:H,2,FALSE) -> 186****6788 | Q485: 东莞市中汇信息技术有限公司
A486: 484 | B486: 12-30 | C486: SF5127722204781 | D486: 东莞 | E486: 东莞 | F486: 邹小华 | G486: 11.000 | H486: 顺丰标快 | I486: 寄转第三方 | J486: 21.00 | K486: 0.00 | L486: 21.00 | M486: 邹小华 | N486: 运费 | O486: 立充充电宝取机柜-物流服务 | P486: 186****6788 | Q486: 东莞市中汇信息技术有限公司
A487: 485 | B487: 12-30 | C487: SF5127722204781 | D487: 东莞 | E487: 东莞 | F487: 邹小华 | G487: 0.000 | H487: 顺丰标快 | I487: 寄转第三方 | J487: 4.00 | K487: 0.00 | L487: 4.00 | M487: 邹小华 | N487: 包装服务 | O487: 立充充电宝取机柜-物流服务 | P487: 186****6788 | Q487: 东莞市中汇信息技术有限公司
A488: 486 | B488: 12-30 | C488: SF5127722665550 | D488: 东莞 | E488: 东莞 | F488: 邹小华 | G488: 1.000 | H488: 顺丰标快 | I488: 寄转第三方 | J488: 11.00 | K488: 0.00 | L488: 11.00 | M488: 邹小华 | N488: 运费 | O488: =VLOOKUP(C488,Sheet2!A:C,2,FALSE) -> 取宝-物流服务 | P488: =VLOOKUP(C488,Sheet2!G:H,2,FALSE) -> 186****6788 | Q488: 东莞市中汇信息技术有限公司
A489: 487 | B489: 12-31 | C489: SF3268649501419 | D489: 惠州 | E489: 东莞 | F489: 邹小华 | G489: 0.000 | H489: 顺丰标快 | I489: 寄付 | J489: 6.00 | K489: 0.00 | L489: 6.00 | M489: 邹小华 | N489: 收件微派 | O489: =VLOOKUP(C489,Sheet2!A:C,2,FALSE) -> 取宝-物流服务 | P489: =VLOOKUP(C489,Sheet2!G:H,2,FALSE) -> 186****6788 | Q489: 东莞市中汇信息技术有限公司
A490: 488 | B490: 12-31 | C490: SF3268649653710 | D490: 惠州 | E490: 东莞 | F490: 邹小华 | G490: 0.000 | H490: 顺丰标快 | I490: 寄付 | J490: 3.00 | K490: 0.00 | L490: 3.00 | M490: 邹小华 | N490: 收件微派 | O490: =VLOOKUP(C490,Sheet2!A:C,2,FALSE) -> 立充充电宝取机柜-物流服务 | P490: =VLOOKUP(C490,Sheet2!G:H,2,FALSE) -> 186****6788 | Q490: 东莞市中汇信息技术有限公司
A491: 489 | B491: 12-31 | C491: SF3268714509952 | D491: 东莞 | E491: 东莞 | F491: 邹小华 | G491: 1.000 | H491: 顺丰标快 | I491: 寄转第三方 | J491: 11.00 | K491: 0.00 | L491: 11.00 | M491: 邹小华 | N491: 运费 | O491: =VLOOKUP(C491,Sheet2!A:C,2,FALSE) -> 取宝-物流服务 | P491: =VLOOKUP(C491,Sheet2!G:H,2,FALSE) -> 186****6788 | Q491: 东莞市中汇信息技术有限公司
A492: 490 | B492: 12-31 | C492: SF3268714509952 | D492: 东莞 | E492: 东莞 | F492: 邹小华 | G492: 0.000 | H492: 顺丰标快 | I492: 寄转第三方 | J492: 1.00 | K492: 0.00 | L492: 1.00 | M492: 邹小华 | N492: 包装服务 | O492: =VLOOKUP(C492,Sheet2!A:C,2,FALSE) -> 取宝-物流服务 | P492: =VLOOKUP(C492,Sheet2!G:H,2,FALSE) -> 186****6788 | Q492: 东莞市中汇信息技术有限公司
A493: 491 | B493: 12-31 | C493: SF3268714724220 | D493: 东莞 | E493: 东莞 | F493: 邹小华 | G493: 3.100 | H493: 顺丰标快 | I493: 寄转第三方 | J493: 13.00 | K493: 0.00 | L493: 13.00 | M493: 邹小华 | N493: 运费 | O493: =VLOOKUP(C493,Sheet2!A:C,2,FALSE) -> 立充充电宝取机柜-物流服务 | P493: =VLOOKUP(C493,Sheet2!G:H,2,FALSE) -> 186****6788 | Q493: 东莞市中汇信息技术有限公司
A494: 492 | B494: 12-31 | C494: SF3268714724220 | D494: 东莞 | E494: 东莞 | F494: 邹小华 | G494: 0.000 | H494: 顺丰标快 | I494: 寄转第三方 | J494: 5.00 | K494: 0.00 | L494: 5.00 | M494: 邹小华 | N494: 包装服务 | O494: =VLOOKUP(C494,Sheet2!A:C,2,FALSE) -> 立充充电宝取机柜-物流服务 | P494: =VLOOKUP(C494,Sheet2!G:H,2,FALSE) -> 186****6788 | Q494: 东莞市中汇信息技术有限公司
A495: 493 | B495: 12-31 | C495: SF3268857238618 | D495: 泸州 | E495: 成都/资阳/眉山 | F495: 阿贞 | G495: 0.000 | H495: 顺丰标快 | I495: 寄付 | J495: 3.00 | K495: 0.00 | L495: 3.00 | M495: 钱诗义 | N495: 收件微派 | O495: =VLOOKUP(C495,Sheet2!A:C,2,FALSE) -> 立充充电宝取机柜-物流服务 | P495: =VLOOKUP(C495,Sheet2!G:H,2,FALSE) -> 134****6101 | Q495: 成都江源易通信息技术有限公司
A496: 494 | B496: 12-31 | C496: SF5106970083922 | D496: 东莞 | E496: 东莞 | F496: 邹小华 | G496: 0.000 | H496: 顺丰标快 | I496: 寄付 | J496: 3.00 | K496: 0.00 | L496: 3.00 | M496: 邹小华 | N496: 收件微派 | O496: =VLOOKUP(C496,Sheet2!A:C,2,FALSE) -> 立充充电宝取机柜-物流服务 | P496: =VLOOKUP(C496,Sheet2!G:H,2,FALSE) -> 186****6788 | Q496: 东莞市中汇信息技术有限公司
A497: 495 | B497: 12-31 | C497: SF5127754205822 | D497: 东莞 | E497: 东莞 | F497: 邹小华 | G497: 1.000 | H497: 顺丰标快 | I497: 寄转第三方 | J497: 11.00 | K497: 0.00 | L497: 11.00 | M497: 邹小华 | N497: 运费 | O497: =VLOOKUP(C497,Sheet2!A:C,2,FALSE) -> 取宝-物流服务 | P497: =VLOOKUP(C497,Sheet2!G:H,2,FALSE) -> 186****6788 | Q497: 东莞市中汇信息技术有限公司
...

Sheet 月结报告

Sheet 12月订单明细
A1: 运单号 | B1: 任务类型 | C1: 系统订单号 | D1: 照片是否导出 | E1: 批次号 | F1: 服务状态 | G1: 商户订单号 | H1: 上门小哥手机号 | I1: 物流状态 | J1: 是否打印 | K1: 预计上门时间 | L1: 收件人 | M1: 收件手机 | N1: 收件电话 | O1: 收件公司 | P1: 收件详细地址 | Q1: 寄件人 | R1: 寄件电话 | S1: 寄方备注 | T1: 寄件公司 | U1: 寄件详细地址 | V1: 托寄物内容 | W1: 托寄物数量 | X1: 件数 | Y1: 包裹重量(kg) | Z1: 运费付款方式 | AA1: 物流产品 | AB1: 自取 | AC1: 定额保价金额(元) | AD1: 基础保价金额(元) | AE1: 密钥认证 | AF1: 下单时间 | AG1: 下单账号 | AH1: 接单人姓名 | AI1: 任务完成时间 | AJ1: 接单人手机 | AK1: 签收完成时间 | AL1: 月结卡号 | AM1: 下call上门收件 | AN1: 标记 | AO1: 异常原因
A2: SF3268579296831 | B2: 补宝-物流服务 | C2: WP25123087228645 | D2: 未导出 | E2: BAT251230092439 | F2: 待接单 | I2: 未收件 | J2: 未打印 | L2: 唐*满 | M2: 155****0885‎‎‎‬‬‬ | N2: *******0885‎‎‎‬‬‬ | O2: 大连浩源********* | P2: 辽宁省大 连市金州区***********‎‎‎‬‬‬ | Q2: 孙*达 | R2: *******6213‎‎‎‬‬‬ | T2: 达叔烤骨头 | U2: 大连市普兰店区**** ************‎‎‎‬‬‬ | V2: 充电宝 | W2: 1 | X2: 1 | Y2: 1 | Z2: 第三方付 | AA2: 顺丰特快 | AE2: 否 | AF2: 2025-12-30 13:46:23 | AG2: 155****0885 | AL2: 7551083218 | AM2: 是
A3: SF3268579291750 | B3: 补宝-物流服务 | C3: WP25123087226877 | D3: 未导出 | E3: BAT251230092259 | F3: 待接单 | I3: 未收件 | J3: 未打印 | L3: 唐*满 | M3: 155****0885‎‎‎‬‬‬ | N3: *******0885‎‎‎‬‬‬ | O3: 大连浩源********* | P3: 辽宁省大 连市金州区***********‎‎‎‬‬‬ | Q3: 孙*达 | R3: *******6213‎‎‎‬‬‬ | U3: 大连市普兰店区**** ************‎‎‎‬‬‬ | V3: 充电柜 | W3: 1 | X3: 1 | Y3: 5 | Z3: 第三方付 | AA3: 顺丰特快 | AE3: 否 | AF3: 2025-12-30 13:46:23 | AG3: 155****0885 | AL3: 7551083218 | AM3: 是
A4: SF5127709690867 | B4: 补宝-物流服务 | C4: WP25123087225294 | D4: 未导出 | E4: BAT251230092044 | F4: 待接单 | I4: 未收件 | J4: 未打印 | L4: 唐*满 | M4: 155****0885‎‎‎‬‬‬ | N4: *******0885‎‎‎‬‬‬ | O4: 大连浩源********* | P4: 辽宁省大 连市金州区***********‎‎‎‬‬‬ | Q4: 孙*达 | R4: *******6213‎‎‎‬‬‬ | T4: 达叔烤骨头 | U4: 大连市普兰店区**** ************‎‎‎‬‬‬ | V4: 充电宝 | W4: 2 | X4: 1 | Y4: 1 | Z4: 第三方付 | AA4: 顺丰特快 | AE4: 否 | AF4: 2025-12-30 13:46:23 | AG4: 155****0885 | AL4: 7551083218 | AM4: 是
A5: SF5106905852824 | B5: 补宝-物流服务 | C5: WP25123087222064 | D5: 未导出 | E5: BAT251230091695 | F5: 待接单 | I5: 未收件 | J5: 未打印 | L5: 唐*满 | M5: 155****0885‎‎‎‬‬‬ | O5: 大连浩源********* | P5: 辽宁省大 连市金州区***********‎‎‎‬‬‬ | Q5: 孙*达 | R5: *******6213‎‎‎‬‬‬ | T5: 达叔烤骨头 | U5: 大连市普兰店区**** ************‎‎‎‬‬‬ | V5: 充电宝 | W5: 2 | X5: 1 | Y5: 1 | Z5: 第三方付 | AA5: 顺丰特快 | AC5: 500 | AE5: 否 | AF5: 2025-12-30 13:46:23 | AG5: 155****0885 | AL5: 7551083218 | AM5: 是
A6: SF5105056503415 | B6: 补宝-物流服务 | C6: WP25122253862488 | D6: 未导出 | E6: BAT251222071369 | F6: 已完成 | I6: 派送成功 | J6: 未打印 | K6: 2025-12-23 12:00 | L6: 李*云 | M6: 181****7580‎‎‎‬‬‬ | P6: 四川省雅安市雨城区***** ****‎‎‎‬‬‬ | Q6: 江* | R6: *******6925‎‎‎‬‬‬ | U6: 四川省成都市 武侯区*****************‎‎‎‬‬‬ | V6: 充电宝 | W6: 2 | X6: 1 | Z6: 寄付月结 | AA6: 顺丰标快 | AE6: 否 | AF6: 2025-12-22 14:08:09 | AG6: 134****6101 | AH6: 穆赵超 | AI6: 2025-12-23 09:24:01 | AJ6: 150****2907‎‎‎‬‬‬ | AK6: 2025-12-23 09:24:06 | AL6: 7551083218 | AM6: 否
A7: SF5105056506251 | B7: 补宝-物流服务 | C7: WP25122253859962 | D7: 未导出 | E7: BAT251222071098 | F7: 已完成 | I7: 派送成功 | J7: 未打印 | K7: 2025-12-23 12:00 | L7: 李*云 | M7: 181****7580‎‎‎‬‬‬ | P7: 四川省雅安市雨城区***** ****‎‎‎‬‬‬ | Q7: 江* | R7: *******6925‎‎‎‬‬‬ | U7: 四川省成都市 武侯区*****************‎‎‎‬‬‬ | V7: 充电宝 | W7: 2 | X7: 1 | Z7: 寄付月结 | AA7: 顺丰标快 | AE7: 否 | AF7: 2025-12-22 14:08:09 | AG7: 134****6101 | AH7: 穆赵超 | AI7: 2025-12-23 09:24:30 | AJ7: 150****2907‎‎‎‬‬‬ | AK7: 2025-12-23 09:24:37 | AL7: 7551083218 | AM7: 否
A8: SF3266863453181 | B8: 补宝-物流服务 | C8: WP25122253857124 | D8: 未导出 | E8: BAT251222070775 | F8: 已完成 | I8: 派送成功 | J8: 未打印 | K8: 2025-12-23 12:00 | L8: 李*云 | M8: 181****7580‎‎‎‬‬‬ | P8: 四川省雅安市雨城区***** ****‎‎‎‬‬‬ | Q8: 江* | R8: *******6925‎‎‎‬‬‬ | S8: 24100081244 | U8: 四川省成都市 武侯区*****************‎‎‎‬‬‬ | V8: 充电宝 | W8: 1 | X8: 1 | Z8: 寄付月结 | AA8: 顺丰标快 | AE8: 否 | AF8: 2025-12-22 14:08:09 | AG8: 134****6101 | AH8: 穆赵超 | AI8: 2025-12-23 09:23:08 | AJ8: 150****2907‎‎‎‬‬‬ | AK8: 2025-12-23 09:23:15 | AL8: 7551083218 | AM8: 否
A9: SF3261464758524 | B9: 补宝-物流服务 | C9: WP25121840418840 | D9: 未导出 | E9: BAT251218185468 | F9: 已完成 | I9: 派送成功 | J9: 未打印 | L9: 邹*华 | M9: 186****6788‎‎‎‬‬‬ | N9: *******6788‎‎‎‬‬‬ | O9: 清溪美宜********** | P9: 广东省 东莞市清溪镇********************‎‎‎‬‬‬ | Q9: 邹*华 | R9: *******6788‎‎‎‬‬‬ | S9: 进店补立充充电宝的宝1个 | U9: 广东省东莞市东城街道东纵路东城段208号 东城万达中心写**********‎‎‎‬‬‬ | V9: 充电宝 | W9: 1 | X9: 1 | Z9: 寄付月结 | AA9: 顺丰标快 | AE9: 否 | AF9: 2025-12-18 16:37:18 | AG9: 186****6788 | AH9: 黄定平 | AI9: 2025-12-19 09:27:31 | AJ9: 132****1601‎‎‎‬‬‬ | AK9: 2025-12-19 09:28:32 | AL9: 7551083218 | AM9: 是
A10: SF3261464758781 | B10: 补宝-物流服务 | C10: WP25121840414211 | D10: 未导出 | E10: BAT251218184998 | F10: 已完成 | I10: 派送成功 | J10: 未打印 | L10: 邹*华 | M10: 186****6788‎‎‎‬‬‬ | N10: *******6788‎‎‎‬‬‬ | O10: 清溪美宜********** | P10: 广东省 东莞市清溪镇********************‎‎‎‬‬‬ | Q10: 邹*华 | R10: *******6788‎‎‎‬‬‬ | S10: 进店补立充充电宝的宝2个 | U10: 广东省东莞市东城街道东纵路东城段208号 东城万达中心写**********‎‎‎‬‬‬ | V10: 充电宝 | W10: 2 | X10: 1 | Z10: 寄付月结 | AA10: 顺丰标快 | AE10: 否 | AF10: 2025-12-18 16:37:18 | AG10: 186****6788 | AH10: 张直国 | AI10: 2025-12-19 09:15:13 | AJ10: 131****3365‎‎‎‬‬‬ | AK10: 2025-12-19 09:15:31 | AL10: 7551083218 | AM10: 是
A11: SF3261417303446 | B11: 补宝-物流服务 | C11: WP25121840198092 | D11: 未导出 | E11: BAT251218163193 | F11: 已完成 | I11: 派送成功 | J11: 未打印 | K11: 2025-12-19 12:00 | L11: 老* | M11: 152****5518‎‎‎‬‬‬ | P11: 都江堰市 观景路483**********‎‎‎‬‬‬ | Q11: 江* | R11: *******5357‎‎‎‬‬‬ | U11: 四川省成都市 武侯区*****************‎‎‎‬‬‬ | V11: 充电宝 | W11: 2 | X11: 1 | Z11: 寄付月结 | AA11: 顺丰标快 | AE11: 否 | AF11: 2025-12-18 16:06:35 | AG11: 134****6101 | AH11: 孟俊涛 | AI11: 2025-12-20 19:42:07 | AJ11: 177****7352‎‎‎‬‬‬ | AK11: 2025-12-20 19:42:17 | AL11: 7551083218 | AM11: 否
A12: SF3261417303058 | B12: 补宝-物流服务 | C12: WP25121840196464 | D12: 未导出 | E12: BAT251218163017 | F12: 已完成 | I12: 派送成功 | J12: 未打印 | K12: 2025-12-19 12:00 | L12: 老* | M12: 152****5518‎‎‎‬‬‬ | P12: 都江堰市 观景路483**********‎‎‎‬‬‬ | Q12: 江* | R12: *******5357‎‎‎‬‬‬ | U12: 四川省成都市 武侯区*****************‎‎‎‬‬‬ | V12: 充电宝 | W12: 2 | X12: 1 | Z12: 寄付月结 | AA12: 顺丰标快 | AE12: 否 | AF12: 2025-12-18 16:06:35 | AG12: 134****6101 | AH12: 孟俊涛 | AI12: 2025-12-20 19:43:08 | AJ12: 177****7352‎‎‎‬‬‬ | AK12: 2025-12-20 19:43:13 | AL12: 7551083218 | AM12: 否
A13: SF3261282600597 | B13: 补宝-物流服务 | C13: WP25121629308215 | D13: 未导出 | E13: BAT251216021950 | F13: 已完成 | I13: 派送成功 | J13: 未打印 | K13: 2025-12-17 12:00 | L13: 刘* | M13: 135****7686‎‎‎‬‬‬ | N13: *******7686‎‎‎‬‬‬ | P13: 四川省成都市武侯区************ **‎‎‎‬‬‬ | Q13: 江* | R13: *******5357‎‎‎‬‬‬ | S13: 补宝机身号：23090013991 | U13: 四川省成都市 武侯区*****************‎‎‎‬‬‬ | V13: 充电宝 | W13: 1 | X13: 1 | Z13: 寄付月结 | AA13: 顺丰即日 | AE13: 否 | AF13: 2025-12-16 09:21:02 | AG13: 134****6101 | AH13: 马兴龙 | AI13: 2025-12-16 16:40:35 | AJ13: 191****7127‎‎‎‬‬‬ | AK13: 2025-12-16 16:40:41 | AL13: 7551083218 | AM13: 是
A14: SF3260491849334 | B14: 补宝-物流服务 | C14: WP25121525331090 | D14: 未导出 | E14: BAT251215106641 | F14: 已完成 | I14: 派送成功 | J14: 未打印 | K14: 2025-12-16 12:00 | L14: 周* | M14: 158****0900‎‎‎‬‬‬ | P14: 四川省成都市金牛区*********** **‎‎‎‬‬‬ | Q14: 江* | R14: *******5357‎‎‎‬‬‬ | S14: 补宝机身号： 24040036300 | U14: 四川省成都市 武侯区*****************‎‎‎‬‬‬ | V14: 充电宝 | W14: 1 | X14: 1 | Z14: 寄付月结 | AA14: 顺丰标快 | AE14: 否 | AF14: 2025-12-15 14:18:49 | AG14: 134****6101 | AH14: 杨飞 | AI14: 2025-12-16 09:48:57 | AJ14: 173****8035‎‎‎‬‬‬ | AK14: 2025-12-16 09:49:21 | AL14: 7551083218 | AM14: 是
A15: SF3260491849237 | B15: 补宝-物流服务 | C15: WP25121525329098 | D15: 未导出 | E15: BAT251215106408 | F15: 已完成 | I15: 派送成功 | J15: 未打印 | K15: 2025-12-16 12:00 | L15: 周* | M15: 158****0900‎‎‎‬‬‬ | P15: 四川省成都市金牛区*********** **‎‎‎‬‬‬ | Q15: 江* | R15: *******5357‎‎‎‬‬‬ | S15: 补宝机身号： 24040036300 | U15: 四川省成都市 武侯区*****************‎‎‎‬‬‬ | V15: 充电宝 | W15: 2 | X15: 1 | Z15: 寄付月结 | AA15: 顺丰标快 | AE15: 否 | AF15: 2025-12-15 14:18:49 | AG15: 134****6101 | AH15: 杨飞 | AI15: 2025-12-16 09:47:55 | AJ15: 173****8035‎‎‎‬‬‬ | AK15: 2025-12-16 09:48:01 | AL15: 7551083218 | AM15: 是
A16: SF3260420814593 | B16: 补宝-物流服务 | C16: WP25121525237467 | D16: 未导出 | E16: BAT251215096732 | F16: 待接单 | I16: 未收件 | J16: 未打印 | L16: 乔* | N16: *******5919‎‎‎‬‬‬ | O16: 天津三有****** | P16: 河北省廊坊市固安县***** **********‎‎‎‬‬‬ | Q16: 闫 | R16: *******8837‎‎‎‬‬‬ | U16: 北京市大兴区**************** **************‎‎‎‬‬‬ | V16: 立充机柜 | W16: 1 | X16: 1 | Z16: 寄付月结 | AA16: 顺丰标快 | AE16: 否 | AF16: 2025-12-15 13:55:27 | AG16: 136****7868 | AL16: 7551083218 | AM16: 是
A17: SF3260499115096 | B17: 补宝-物流服务 | C17: WP25121524879952 | D17: 未导出 | E17: BAT251215058005 | F17: 已完成 | I17: 派送成功 | J17: 未打印 | K17: 2025-12-16 12:00 | L17: 代*峰 | M17: 186****8030‎‎‎‬‬‬ | N17: *******8030‎‎‎‬‬‬ | P17: 四川省成都市成华区********************** ************‎‎‎‬‬‬ | Q17: 代*峰 | R17: *******8030‎‎‎‬‬‬ | S17: 补宝机柜：24100081048 | U17: 四川省成都市 郫都区*******‎‎‎‬‬‬ | V17: 充电宝 | W17: 1 | X17: 1 | Z17: 寄付月结 | AA17: 顺丰标快 | AE17: 否 | AF17: 2025-12-15 14:13:51 | AG17: 134****6101 | AH17: 刘银豪 | AI17: 2025-12-15 20:37:35 | AJ17: 177****9764‎‎‎‬‬‬ | AK17: 2025-12-15 20:37:46 | AL17: 7551083218 | AM17: 是
A18: SF3260499115906 | B18: 补宝-物流服务 | C18: WP25121524873236 | D18: 未导出 | E18: BAT251215057306 | F18: 已完成 | I18: 派送成功 | J18: 未打印 | K18: 2025-12-16 12:00 | L18: 代*峰 | M18: 186****8030‎‎‎‬‬‬ | N18: *******8030‎‎‎‬‬‬ | P18: 成华区********** *************************‎‎‎‬‬‬ | Q18: 代*峰 | R18: *******8030‎‎‎‬‬‬ | S18: 补宝机柜号：24100081048 | U18: 四川省成都市 郫都区*******‎‎‎‬‬‬ | V18: 充电宝 | W18: 2 | X18: 1 | Z18: 寄付月结 | AA18: 顺丰标快 | AE18: 否 | AF18: 2025-12-15 14:13:51 | AG18: 134****6101 | AH18: 刘银豪 | AI18: 2025-12-15 20:39:01 | AJ18: 177****9764‎‎‎‬‬‬ | AK18: 2025-12-15 20:39:09 | AL18: 7551083218 | AM18: 是
A19: SF3278405753506 | B19: 补宝-物流服务 | C19: WP25121108634270 | D19: 未导出 | E19: BAT251211042008 | F19: 已完成 | I19: 派送成功 | J19: 未打印 | K19: 2025-12-12 12:00 | L19: 邹*华 | M19: 186****6788‎‎‎‬‬‬ | N19: *******6788‎‎‎‬‬‬ | O19: 高埗稻田***** | P19: 广东省东莞市高埗镇*********** *****************‎‎‎‬‬‬ | Q19: 邹*华 | R19: *******6788‎‎‎‬‬‬ | S19: 进店补立充充电宝的宝1个 | U19: 广东省东莞市东城街道东纵路东城段208号 东城万达中心写**********‎‎‎‬‬‬ | V19: 充电宝 | W19: 1 | X19: 1 | Z19: 寄付月结 | AA19: 顺丰标快 | AE19: 否 | AF19: 2025-12-11 10:27:22 | AG19: 186****6788 | AH19: 李亮 | AI19: 2025-12-11 17:34:56 | AJ19: 186****3894‎‎‎‬‬‬ | AK19: 2025-12-11 17:35:29 | AL19: 7551083218 | AM19: 是
A20: SF3278434363447 | B20: 补宝-物流服务 | C20: WP25121108476885 | D20: 未导出 | E20: BAT251211024420 | F20: 已完成 | I20: 派送成功 | J20: 未打印 | K20: 2025-12-12 12:00 | L20: 邹*华 | M20: 186****6788‎‎‎‬‬‬ | N20: *******6788‎‎‎‬‬‬ | O20: 寮步****** | P20: 广东省东莞市寮步 镇*********‎‎‎‬‬‬ | Q20: 邹*华 | R20: *******6788‎‎‎‬‬‬ | S20: 进店补立充充电宝的宝2个 | U20: 广东省东莞市东城街道东纵路东城段208号 东城万达中心写**********‎‎‎‬‬‬ | V20: 充电宝 | W20: 2 | X20: 1 | Z20: 寄付月结 | AA20: 顺丰标快 | AE20: 否 | AF20: 2025-12-11 09:28:59 | AG20: 186****6788 | AH20: 庄龙生 | AI20: 2025-12-11 17:06:43 | AJ20: 132****2205‎‎‎‬‬‬ | AK20: 2025-12-11 17:06:55 | AL20: 7551083218 | AM20: 是
A21: SF3278434363483 | B21: 补宝-物流服务 | C21: WP25121108475411 | D21: 未导出 | E21: BAT251211024253 | F21: 已完成 | I21: 派送成功 | J21: 未打印 | K21: 2025-12-12 12:00 | L21: 邹*华 | M21: 186****6788‎‎‎‬‬‬ | N21: *******6788‎‎‎‬‬‬ | O21: 高埗稻田***** | P21: 广东省东莞市高埗镇*********** *****************‎‎‎‬‬‬ | Q21: 邹*华 | R21: *******6788‎‎‎‬‬‬ | S21: 进店补立充充电宝的宝3个 | U21: 广东省东莞市东城街道东纵路东城段208号 东城万达中心写**********‎‎‎‬‬‬ | V21: 充电宝 | W21: 3 | X21: 1 | Z21: 寄付月结 | AA21: 顺丰标快 | AE21: 否 | AF21: 2025-12-11 09:28:59 | AG21: 186****6788 | AH21: 李亮 | AI21: 2025-12-11 17:37:01 | AJ21: 186****3894‎‎‎‬‬‬ | AK21: 2025-12-11 17:37:39 | AL21: 7551083218 | AM21: 是
A22: SF3269834853653 | B22: 补宝-物流服务 | C22: WP25121108472079 | D22: 未导出 | E22: BAT251211024149 | F22: 已完成 | I22: 派送成功 | J22: 未打印 | K22: 2025-12-12 12:00 | L22: 邹*华 | M22: 186****6788‎‎‎‬‬‬ | N22: *******6788‎‎‎‬‬‬ | O22: 企石凯迪******* | P22: 广东省东莞市企石 **********‎‎‎‬‬‬ | Q22: 邹*华 | R22: *******6788‎‎‎‬‬‬ | S22: 进店补立充充电宝的宝2个 | U22: 广东省东莞市东城街道东纵路东城段208号 东城万达中心写**********‎‎‎‬‬‬ | V22: 充电宝 | W22: 2 | X22: 1 | Z22: 寄付月结 | AA22: 顺丰标快 | AE22: 否 | AF22: 2025-12-11 09:28:59 | AG22: 186****6788 | AH22: 李立华 | AI22: 2025-12-11 17:53:00 | AJ22: 136****4147‎‎‎‬‬‬ | AK22: 2025-12-11 17:53:22 | AL22: 7551083218 | AM22: 是
A23: SF3269042397254 | B23: 补宝-物流服务 | C23: WP25120902973697 | D23: 未导出 | E23: BAT251209504158 | F23: 已完成 | I23: 派送成功 | J23: 未打印 | L23: 罗* | M23: 181****6669‎‎‎‬‬‬ | N23: *******6669‎‎‎‬‬‬ | P23: 广东省深圳市宝安区* ************************‎‎‎‬‬‬ | Q23: 吴*继 | R23: *******6168‎‎‎‬‬‬ | T23: 广东久益智付科技有限公司 | U23: 广东省东莞市南城 **********‎‎‎‬‬‬ | V23: 立充充电宝 | W23: 1 | X23: 1 | Z23: 寄付月结 | AA23: 顺丰标快 | AE23: 否 | AF23: 2025-12-09 22:16:31 | AG23: 130****4667 | AH23: 丘春生 | AI23: 2025-12-11 09:56:57 | AJ23: 139****6926‎‎‎‬‬‬ | AK23: 2025-12-11 09:57:06 | AL23: 7551083218 | AM23: 是
A24: SF3269933113650 | B24: 补宝-物流服务 | C24: WP25120895414076 | D24: 未导出 | E24: BAT251208277541 | F24: 已完成 | I24: 派送成功 | J24: 未打印 | K24: 2025-12-09 12:00 | L24: 邹*华 | M24: 186****6788‎‎‎‬‬‬ | N24: *******6788‎‎‎‬‬‬ | O24: 洪梅湘味***** | P24: 广东省东莞市洪梅镇***************** **‎‎‎‬‬‬ | Q24: 邹*华 | R24: *******6788‎‎‎‬‬‬ | S24: 进店补立充充电宝的宝1个 | U24: 广东省东莞市东城街道东纵路东城段208号 东城万达中心写**********‎‎‎‬‬‬ | V24: 充电宝 | W24: 1 | X24: 1 | Z24: 寄付月结 | AA24: 顺丰标快 | AE24: 否 | AF24: 2025-12-08 17:26:58 | AG24: 186****6788 | AH24: 苏洁 | AI24: 2025-12-09 10:27:06 | AJ24: 158****3232‎‎‎‬‬‬ | AK24: 2025-12-09 10:27:10 | AL24: 7551083218 | AM24: 是
A25: SF3278126546304 | B25: 补宝-物流服务 | C25: WP25120895409404 | D25: 未导出 | E25: BAT251208277033 | F25: 已完成 | I25: 派送成功 | J25: 未打印 | L25: 邹*华 | M25: 186****6788‎‎‎‬‬‬ | N25: *******6788‎‎‎‬‬‬ | O25: 洪梅湘味***** | P25: 广东省东莞市洪梅镇***************** **‎‎‎‬‬‬ | Q25: 邹*华 | R25: *******6788‎‎‎‬‬‬ | S25: 进店补立充充电宝的宝2个 | U25: 广东省东莞市东城街道东纵路东城段208号 东城万达中心写**********‎‎‎‬‬‬ | V25: 充电宝 | W25: 2 | X25: 1 | Z25: 寄付月结 | AA25: 顺丰标快 | AE25: 否 | AF25: 2025-12-08 17:26:58 | AG25: 186****6788 | AH25: 苏洁 | AI25: 2025-12-09 10:26:25 | AJ25: 158****3232‎‎‎‬‬‬ | AK25: 2025-12-09 10:26:30 | AL25: 7551083218 | AM25: 是
A26: SF3269248082701 | B26: 补宝-物流服务 | C26: WP25120895195768 | D26: 未导出 | E26: BAT251208255813 | F26: 已完成 | I26: 派送成功 | J26: 未打印 | K26: 2025-12-09 12:00 | L26: 邹*华 | M26: 186****6788‎‎‎‬‬‬ | N26: *******6788‎‎‎‬‬‬ | O26: 石碣****** | P26: 广东省东莞市石 碣镇**********************‎‎‎‬‬‬ | Q26: 邹*华 | R26: *******6788‎‎‎‬‬‬ | S26: 进店取立充充电宝2个 | U26: 广东省东莞市东城街道东纵路东城段208号 东城万达中心写**********‎‎‎‬‬‬ | V26: 充电宝 | W26: 2 | X26: 1 | Z26: 寄付月结 | AA26: 顺丰标快 | AE26: 否 | AF26: 2025-12-08 17:06:18 | AG26: 186****6788 | AH26: 冉江林 | AI26: 2025-12-09 10:51:16 | AJ26: 189****8452‎‎‎‬‬‬ | AK26: 2025-12-09 10:51:29 | AL26: 7551083218 | AM26: 是
A27: SF3269246608556 | B27: 补宝-物流服务 | C27: WP25120895158153 | D27: 未导出 | E27: BAT251208251915 | F27: 已完成 | I27: 派送成功 | J27: 未打印 | K27: 2025-12-09 12:00 | L27: 邹*华 | M27: 186****6788‎‎‎‬‬‬ | N27: *******6788‎‎‎‬‬‬ | O27: 常平**** | P27: 广东省东莞市常平 镇*********‎‎‎‬‬‬ | Q27: 邹*华 | R27: *******6788‎‎‎‬‬‬ | S27: 进店补立充充电宝的宝2个 | U27: 广东省东莞市东城街道东纵路东城段208号 东城万达中心写**********‎‎‎‬‬‬ | V27: 充电宝 | W27: 2 | X27: 1 | Z27: 寄付月结 | AA27: 顺丰标快 | AE27: 否 | AF27: 2025-12-08 17:02:57 | AG27: 186****6788 | AH27: 周乐义 | AI27: 2025-12-09 09:56:55 | AJ27: 136****8851‎‎‎‬‬‬ | AK27: 2025-12-09 09:57:18 | AL27: 7551083218 | AM27: 是
A28: SF3278179778744 | B28: 补宝-物流服务 | C28: WP25120895129612 | D28: 未导出 | E28: BAT251208248948 | F28: 已完成 | I28: 派送成功 | J28: 未打印 | K28: 2025-12-09 12:00 | L28: 邹*华 | M28: 186****6788‎‎‎‬‬‬ | N28: *******6788‎‎‎‬‬‬ | O28: 大岭山五******* | P28: 广东省东莞市大岭山镇 ************************‎‎‎‬‬‬ | Q28: 邹*华 | R28: *******6788‎‎‎‬‬‬ | S28: 进店补立充充电宝的宝2个 | U28: 广东省东莞市东城街道东纵路东城段208号 东城万达中心写**********‎‎‎‬‬‬ | V28: 充电宝 | W28: 2 | X28: 1 | Z28: 寄付月结 | AA28: 顺丰标快 | AE28: 否 | AF28: 2025-12-08 16:59:57 | AG28: 186****6788 | AH28: 周洋 | AI28: 2025-12-09 14:49:30 | AJ28: 186****5265‎‎‎‬‬‬ | AK28: 2025-12-09 14:49:40 | AL28: 7551083218 | AM28: 是
A29: SF3269241885700 | B29: 补宝-物流服务 | C29: WP25120895120790 | D29: 未导出 | E29: BAT251208248056 | F29: 已完成 | I29: 派送成功 | J29: 未打印 | K29: 2025-12-09 12:00 | L29: 邹*华 | M29: 186****6788‎‎‎‬‬‬ | N29: *******6788‎‎‎‬‬‬ | O29: 寮步四个*************** | P29: 广东省东莞 市寮步镇************‎‎‎‬‬‬ | Q29: 邹*华 | R29: *******6788‎‎‎‬‬‬ | S29: 进店取立充的充电宝的宝2个 | U29: 广东省东莞市东城街道东纵路东城段208号 东城万达中心写**********‎‎‎‬‬‬ | V29: 充电宝 | W29: 1 | X29: 1 | Z29: 寄付月结 | AA29: 顺丰标快 | AE29: 否 | AF29: 2025-12-08 16:59:57 | AG29: 186****6788 | AH29: 孙剑 | AI29: 2025-12-09 10:42:47 | AJ29: 157****3657‎‎‎‬‬‬ | AK29: 2025-12-09 10:43:03 | AL29: 7551083218 | AM29: 是
A30: SF3269240753364 | B30: 补宝-物流服务 | C30: WP25120895103995 | D30: 未导出 | E30: BAT251208246383 | F30: 已完成 | I30: 派送成功 | J30: 未打印 | K30: 2025-12-09 12:00 | L30: 邹*华 | M30: 186****6788‎‎‎‬‬‬ | N30: *******6788‎‎‎‬‬‬ | O30: 企石好想******** | P30: 广东省东莞 市企石镇************‎‎‎‬‬‬ | Q30: 邹*华 | R30: *******6788‎‎‎‬‬‬ | S30: 进店补立充充电宝的宝2个 | U30: 广东省东莞市东城街道东纵路东城段208号 东城万达中心写**********‎‎‎‬‬‬ | V30: 充电宝 | W30: 2 | X30: 1 | Z30: 寄付月结 | AA30: 顺丰标快 | AE30: 否 | AF30: 2025-12-08 16:56:42 | AG30: 186****6788 | AH30: 胡佳琪 | AI30: 2025-12-09 08:54:53 | AJ30: 151****3972‎‎‎‬‬‬ | AK30: 2025-12-09 08:55:13 | AL30: 7551083218 | AM30: 是
A31: SF3269276252803 | B31: 补宝-物流服务 | C31: WP25120894815169 | D31: 未导出 | E31: BAT251208216282 | F31: 已取消 | I31: 未收件 | J31: 未打印 | L31: 邹*华 | M31: 186****6788‎‎‎‬‬‬ | N31: *******6788‎‎‎‬‬‬ | O31: 洪梅湘味***** | P31: 广东省东莞市洪梅镇***************** **‎‎‎‬‬‬ | Q31: 邹*华 | R31: *******6788‎‎‎‬‬‬ | S31: 进店补立充充电宝的宝2个 | U31: 广东省东莞市东城街道东纵路东城段208号 东城万达中心写**********‎‎‎‬‬‬ | V31: 充电宝 | W31: 2 | X31: 1 | Z31: 寄付月结 | AA31: 顺丰标快 | AE31: 否 | AF31: 2025-12-08 16:21:05 | AG31: 186****6788 | AL31: 7551083218 | AM31: 是
A32: SF3274990520130 | B32: 补宝-物流服务 | C32: WP25120373167360 | D32: 未导出 | E32: BAT251203136179 | F32: 已完成 | I32: 派送成功 | J32: 未打印 | K32: 2025-12-04 12:00 | L32: 邹*华 | M32: 186****6788‎‎‎‬‬‬ | N32: *******6788‎‎‎‬‬‬ | O32: 石湾美宜***************** | P32: 广东省惠州市博罗县*** **************‎‎‎‬‬‬ | Q32: 邹*华 | R32: *******6788‎‎‎‬‬‬ | S32: 进店补立充充电宝的宝2个 | U32: 广东省东莞市东城街道东纵路东城段208号 东城万达中心写**********‎‎‎‬‬‬ | V32: 充电宝 | W32: 2 | X32: 1 | Z32: 寄付月结 | AA32: 顺丰标快 | AE32: 否 | AF32: 2025-12-03 14:34:58 | AG32: 186****6788 | AH32: 苏永富 | AI32: 2025-12-04 11:09:54 | AJ32: 135****4319‎‎‎‬‬‬ | AK32: 2025-12-04 11:10:07 | AL32: 7551083218 | AM32: 是
A33: SF3268714509952 | B33: 取宝-物流服务 | C33: WP25123190773889 | D33: 未导出 | E33: BAT251231026646 | F33: 已完成 | H33: 15013577157 | I33: 派送成功 | J33: 未打印 | K33: 2026-01-01 12:00 | L33: 邹*华 | M33: 186****6788‎‎‎‬‬‬ | N33: *******6788‎‎‎‬‬‬ | P33: 广东省东莞市东城街道东纵路东城段208号 东城万达中心写**********‎‎‎‬‬‬ | Q33: 邹*华 | R33: *******6788‎‎‎‬‬‬ | S33: 进店取立充充电宝的宝3个 | T33: 小云乡·云南菜(长安店) | U33: 广东省东莞 市长安镇************‎‎‎‬‬‬ | V33: 充电宝 | W33: 3 | X33: 1 | Z33: 寄付月结 | AA33: 顺丰标快 | AE33: 否 | AF33: 2025-12-31 10:08:00 | AG33: 186****6788 | AH33: 蔡李任 | AI33: 2025-12-31 12:14:55 | AJ33: 150****7157‎‎‎‬‬‬ | AK33: 2026-01-01 09:00:03 | AL33: 7551083218 | AM33: 是
A34: SF5127754205822 | B34: 取宝-物流服务 | C34: WP25123190772209 | D34: 未导出 | E34: BAT251231026472 | F34: 已完成 | H34: 15013577157 | I34: 派送成功 | J34: 未打印 | K34: 2026-01-01 12:00 | L34: 邹*华 | M34: 186****6788‎‎‎‬‬‬ | N34: *******6788‎‎‎‬‬‬ | P34: 广东省东莞市东城街道东纵路东城段208号 东城万达中心写**********‎‎‎‬‬‬ | Q34: 邹*华 | R34: *******6788‎‎‎‬‬‬ | S34: 进店取立充充电宝的宝2个 | T34: 小云乡·云南菜(长安店) | U34: 广东省东莞 市长安镇************‎‎‎‬‬‬ | V34: 充电宝 | W34: 2 | X34: 1 | Z34: 寄付月结 | AA34: 顺丰标快 | AE34: 否 | AF34: 2025-12-31 10:08:00 | AG34: 186****6788 | AH34: 蔡李任 | AI34: 2025-12-31 12:12:11 | AJ34: 150****7157‎‎‎‬‬‬ | AK34: 2026-01-01 09:00:03 | AL34: 7551083218 | AM34: 是
A35: SF5127722665550 | B35: 取宝-物流服务 | C35: WP25123088309157 | D35: 未导出 | E35: BAT251230202947 | F35: 已完成 | H35: 13178616287 | I35: 派送成功 | J35: 未打印 | K35: 2025-12-31 12:00 | L35: 邹*华 | M35: 186****6788‎‎‎‬‬‬ | N35: *******6788‎‎‎‬‬‬ | P35: 广东省东莞市东城街道东纵路东城段208号 东城万达中心写**********‎‎‎‬‬‬ | Q35: 邹*华 | R35: *******6788‎‎‎‬‬‬ | S35: 进店取立充充电宝的宝2个 | T35: 清溪宝家酒店二楼商务棋牌 | U35: 广东省东莞市清溪镇***************** *‎‎‎‬‬‬ | V35: 充电宝 | W35: 2 | X35: 1 | Z35: 寄付月结 | AA35: 顺丰特快 | AE35: 否 | AF35: 2025-12-30 17:25:46 | AG35: 186****6788 | AH35: 潘承寸 | AI35: 2025-12-30 21:36:26 | AJ35: 131****6287‎‎‎‬‬‬ | AK35: 2025-12-31 08:43:04 | AL35: 7551083218 | AM35: 是
A36: SF5106970421620 | B36: 取宝-物流服务 | C36: WP25123088304955 | D36: 未导出 | E36: BAT251230202501 | F36: 已完成 | H36: 13178616287 | I36: 派送成功 | J36: 未打印 | K36: 2025-12-31 12:00 | L36: 邹*华 | M36: 186****6788‎‎‎‬‬‬ | N36: *******6788‎‎‎‬‬‬ | P36: 广东省东莞市东城街道东纵路东城段208号 东城万达中心写**********‎‎‎‬‬‬ | Q36: 邹*华 | R36: *******6788‎‎‎‬‬‬ | S36: 进店取立充充电宝的宝2个 | T36: 清溪宝家酒店二楼商务棋牌 | U36: 广东省东莞市清溪镇***************** *‎‎‎‬‬‬ | V36: 充电宝 | W36: 2 | X36: 1 | Z36: 寄付月结 | AA36: 顺丰特快 | AE36: 否 | AF36: 2025-12-30 17:25:46 | AG36: 186****6788 | AH36: 潘承寸 | AI36: 2025-12-30 21:35:24 | AJ36: 131****6287‎‎‎‬‬‬ | AK36: 2025-12-31 08:43:04 | AL36: 7551083218 | AM36: 是 | AO36: 异常时间：2025-12-30 18:50:57； 异常类型：客户拒绝取证； 异常描述：客户收不到验证码； 审核意见：；
A37: SF5127722066632 | B37: 取宝-物流服务 | C37: WP25123088280271 | D37: 未导出 | E37: BAT251230199984 | F37: 异常结束 | H37: 17377165959 | I37: 派送成功 | J37: 未打印 | K37: 2025-12-31 12:00 | L37: 邹*华 | M37: 186****6788‎‎‎‬‬‬ | N37: *******6788‎‎‎‬‬‬ | P37: 广东省东莞市东城街道东纵路东城段208号 东城万达中心写**********‎‎‎‬‬‬ | Q37: 邹*华 | R37: *******6788‎‎‎‬‬‬ | S37: 进店取立充充电宝的宝2个 | T37: 塘厦惠影千都沐足 | U37: 广东省东莞市塘厦 镇*********‎‎‎‬‬‬ | V37: 充电宝 | W37: 1 | X37: 1 | Z37: 寄付月结 | AA37: 顺丰特快 | AE37: 否 | AF37: 2025-12-30 17:22:06 | AG37: 186****6788 | AH37: 李钊 | AI37: 2025-12-30 18:50:57 | AJ37: 173****5959‎‎‎‬‬‬ | AK37: 2025-12-31 11:08:26 | AL37: 7551083218 | AM37: 是 | AO37: 异常时间：2025-12-30 18:52:46； 异常类型：客户拒绝取证； 异常描述：客户收不到验证码； 审核意见：；
A38: SF5106970144442 | B38: 取宝-物流服务 | C38: WP25123088275704 | D38: 未导出 | E38: BAT251230199531 | F38: 异常结束 | H38: 17377165959 | I38: 派送成功 | J38: 未打印 | K38: 2025-12-31 12:00 | L38: 邹*华 | M38: 186****6788‎‎‎‬‬‬ | N38: *******6788‎‎‎‬‬‬ | P38: 广东省东莞市东城街道东纵路东城段208号 东城万达中心写**********‎‎‎‬‬‬ | Q38: 邹*华 | R38: *******6788‎‎‎‬‬‬ | S38: 进店取立充充电宝的宝2个 | T38: 塘厦惠影千都沐足 | U38: 广东省东莞市塘厦 镇*********‎‎‎‬‬‬ | V38: 充电宝 | W38: 2 | X38: 1 | Z38: 寄付月结 | AA38: 顺丰特快 | AE38: 否 | AF38: 2025-12-30 17:22:06 | AG38: 186****6788 | AH38: 李钊 | AI38: 2025-12-30 18:52:46 | AJ38: 173****5959‎‎‎‬‬‬ | AK38: 2025-12-31 11:08:26 | AL38: 7551083218 | AM38: 是
A39: SF5127702222006 | B39: 取宝-物流服务 | C39: WP25123087300735 | D39: 未导出 | E39: BAT251230099882 | F39: 已取消 | H39: 18681027015 | I39: 已取消 | J39: 未打印 | L39: 邹*华 | M39: 186****6788‎‎‎‬‬‬ | N39: *******6788‎‎‎‬‬‬ | P39: 广东省东莞市东城街道东纵路东城段208号 东城万达中心写**********‎‎‎‬‬‬ | Q39: 邹*华 | R39: *******6788‎‎‎‬‬‬ | S39: 进店取立充充电宝的宝2个 | T39: 清溪宝家酒店二楼商务棋牌 | U39: 广东省东莞市清溪镇***************** *‎‎‎‬‬‬ | V39: 充电宝 | W39: 2 | X39: 1 | Z39: 寄付月结 | AA39: 顺丰特快 | AE39: 否 | AF39: 2025-12-30 14:11:03 | AG39: 186****6788 | AH39: 唐伟华 | AJ39: 186****7015‎‎‎‬‬‬ | AL39: 7551083218 | AM39: 是
A40: SF5106901940142 | B40: 取宝-物流服务 | C40: WP25123087299207 | D40: 未导出 | E40: BAT251230099714 | F40: 已取消 | H40: 18681027015 | I40: 已取消 | J40: 未打印 | L40: 邹*华 | M40: 186****6788‎‎‎‬‬‬ | N40: *******6788‎‎‎‬‬‬ | P40: 广东省东莞市东城街道东纵路东城段208号 东城万达中心写**********‎‎‎‬‬‬ | Q40: 邹*华 | R40: *******6788‎‎‎‬‬‬ | S40: 进店取立充充电宝的宝2个 | T40: 清溪宝家酒店二楼商务棋牌 | U40: 广东省东莞市清溪镇***************** *‎‎‎‬‬‬ | V40: 充电宝 | W40: 2 | X40: 1 | Z40: 寄付月结 | AA40: 顺丰特快 | AE40: 否 | AF40: 2025-12-30 14:11:03 | AG40: 186****6788 | AL40: 7551083218 | AM40: 是
A41: SF3268641154808 | B41: 取宝-物流服务 | C41: WP25122982149008 | D41: 未导出 | E41: BAT251229036168 | F41: 已完成 | H41: 13268553514 | I41: 派送成功 | J41: 未打印 | K41: 2025-12-30 12:00 | L41: 邹*华 | M41: 186****6788‎‎‎‬‬‬ | N41: *******6788‎‎‎‬‬‬ | P41: 广东省东莞市东城街道东纵路东城段208号 东城万达中心写**********‎‎‎‬‬‬ | Q41: 邹*华 | R41: *******6788‎‎‎‬‬‬ | S41: 进店取立充充电宝的宝2个 | T41: 中堂傲游网吧(槎滘大道店) | U41: 广东省东莞市中堂镇************* *‎‎‎‬‬‬ | V41: 充电宝 | W41: 2 | X41: 1 | Z41: 寄付月结 | AA41: 顺丰标快 | AE41: 否 | AF41: 2025-12-29 10:44:18 | AG41: 186****6788 | AH41: 刘家劲 | AI41: 2025-12-29 10:52:45 | AJ41: 132****3514‎‎‎‬‬‬ | AK41: 2025-12-30 08:39:46 | AL41: 7551083218 | AM41: 是
A42: SF5106055772095 | B42: 取宝-物流服务 | C42: WP25122982148001 | D42: 未导出 | E42: BAT251229036059 | F42: 已完成 | H42: 13268553514 | I42: 派送成功 | J42: 未打印 | K42: 2025-12-30 12:00 | L42: 邹*华 | M42: 186****6788‎‎‎‬‬‬ | N42: *******6788‎‎‎‬‬‬ | P42: 广东省东莞市东城街道东纵路东城段208号 东城万达中心写**********‎‎‎‬‬‬ | Q42: 邹*华 | R42: *******6788‎‎‎‬‬‬ | S42: 进店取立充充电宝的宝3个 | T42: 中堂傲游网吧(槎滘大道店) | U42: 广东省东莞市中堂镇************* *‎‎‎‬‬‬ | V42: 充电宝 | W42: 3 | X42: 1 | Z42: 寄付月结 | AA42: 顺丰标快 | AE42: 否 | AF42: 2025-12-29 10:44:18 | AG42: 186****6788 | AH42: 刘家劲 | AI42: 2025-12-29 10:53:47 | AJ42: 132****3514‎‎‎‬‬‬ | AK42: 2025-12-30 08:39:46 | AL42: 7551083218 | AM42: 是
A43: SF5106055772013 | B43: 取宝-物流服务 | C43: WP25122982146144 | D43: 未导出 | E43: BAT251229035848 | F43: 已完成 | H43: 18681134492 | I43: 派送成功 | J43: 未打印 | K43: 2025-12-30 12:00 | L43: 邹*华 | M43: 186****6788‎‎‎‬‬‬ | N43: *******6788‎‎‎‬‬‬ | P43: 广东省东莞市东城街道东纵路东城段208号 东城万达中心写**********‎‎‎‬‬‬ | Q43: 邹*华 | R43: *******6788‎‎‎‬‬‬ | S43: 进店取立充充电宝的宝3个 | T43: 沪上阿姨 | U43: 广东省东莞市桥头镇********* ****‎‎‎‬‬‬ | V43: 充电宝 | W43: 3 | X43: 1 | Z43: 寄付月结 | AA43: 顺丰标快 | AE43: 否 | AF43: 2025-12-29 10:44:18 | AG43: 186****6788 | AH43: 陈金明 | AI43: 2025-12-29 12:19:29 | AJ43: 186****4492‎‎‎‬‬‬ | AK43: 2025-12-29 17:03:48 | AL43: 7551083218 | AM43: 是
A44: SF5106188210316 | B44: 取宝-物流服务 | C44: WP25122982134110 | D44: 未导出 | E44: BAT251229034551 | F44: 已完成 | H44: 13650273235 | I44: 派送成功 | J44: 未打印 | K44: 2025-12-30 12:00 | L44: 邹*华 | M44: 186****6788‎‎‎‬‬‬ | N44: *******6788‎‎‎‬‬‬ | P44: 广东省东莞市东城街道东纵路东城段208号 东城万达中心写**********‎‎‎‬‬‬ | Q44: 邹*华 | R44: *******6788‎‎‎‬‬‬ | S44: 进店取立充充电宝的宝2个 | T44: 企石乐乐商务公馆(企石店) | U44: 广东省东莞市企石镇* ************************‎‎‎‬‬‬ | V44: 充电宝 | W44: 2 | X44: 1 | Z44: 寄付月结 | AA44: 顺丰标快 | AE44: 否 | AF44: 2025-12-29 10:38:34 | AG44: 186****6788 | AH44: 吴红文 | AI44: 2025-12-29 11:29:12 | AJ44: 136****3235‎‎‎‬‬‬ | AK44: 2025-12-29 17:03:48 | AL44: 7551083218 | AM44: 是
A45: SF3268640954282 | B45: 取宝-物流服务 | C45: WP25122982131844 | D45: 未导出 | E45: BAT251229034312 | F45: 已完成 | H45: 13650273235 | I45: 派送成功 | J45: 未打印 | K45: 2025-12-30 12:00 | L45: 邹*华 | M45: 186****6788‎‎‎‬‬‬ | N45: *******6788‎‎‎‬‬‬ | P45: 广东省东莞市东城街道东纵路东城段208号 东城万达中心写**********‎‎‎‬‬‬ | Q45: 邹*华 | R45: *******6788‎‎‎‬‬‬ | S45: 进店取立充充电宝的宝2个 | T45: 企石乐乐商务公馆(企石店) | U45: 广东省东莞市企石镇* ************************‎‎‎‬‬‬ | V45: 充电宝 | W45: 2 | X45: 1 | Z45: 寄付月结 | AA45: 顺丰标快 | AE45: 否 | AF45: 2025-12-29 10:38:34 | AG45: 186****6788 | AH45: 吴红文 | AI45: 2025-12-29 11:32:00 | AJ45: 136****3235‎‎‎‬‬‬ | AK45: 2025-12-29 17:03:48 | AL45: 7551083218 | AM45: 是
A46: SF3268649501419 | B46: 取宝-物流服务 | C46: WP25122982126993 | D46: 未导出 | E46: BAT251229033798 | F46: 已完成 | H46: 15016008764 | I46: 派送成功 | J46: 未打印 | K46: 2025-12-30 12:00 | L46: 邹*华 | M46: 186****6788‎‎‎‬‬‬ | N46: *******6788‎‎‎‬‬‬ | P46: 广东省东莞市东城街道东纵路东城段208号 东城万达中心写**********‎‎‎‬‬‬ | Q46: 邹*华 | R46: *******6788‎‎‎‬‬‬ | S46: 进店取立充充电宝的宝3个 | T46: 石湾美宜佳便利店(蓝湾半岛店粤20946) | U46: 广东省惠州市博罗县*** **************‎‎‎‬‬‬ | V46: 充电宝 | W46: 3 | X46: 1 | Z46: 寄付月结 | AA46: 顺丰标快 | AE46: 否 | AF46: 2025-12-29 10:35:55 | AG46: 186****6788 | AH46: 姚锦林 | AI46: 2025-12-29 18:40:23 | AJ46: 150****8764‎‎‎‬‬‬ | AK46: 2025-12-30 08:39:46 | AL46: 7551083218 | AM46: 是
A47: SF5106184196451 | B47: 取宝-物流服务 | C47: WP25122982112187 | D47: 未导出 | E47: BAT251229032184 | F47: 已完成 | H47: 18664174207 | I47: 派送成功 | J47: 未打印 | K47: 2025-12-30 12:00 | L47: 邹*华 | M47: 186****6788‎‎‎‬‬‬ | N47: *******6788‎‎‎‬‬‬ | P47: 广东省东莞市东城街道东纵路东城段208号 东城万达中心写**********‎‎‎‬‬‬ | Q47: 邹*华 | R47: *******6788‎‎‎‬‬‬ | S47: 进店取立充充电宝的宝2个 | T47: 囍得雀·CoFiTi 24h智能棋牌室 | U47: 广东省东莞市麻涌镇************* ************************‎‎‎‬‬‬ | V47: 充电宝 | W47: 2 | X47: 1 | Z47: 寄付月结 | AA47: 顺丰标快 | AE47: 否 | AF47: 2025-12-29 10:30:16 | AG47: 186****6788 | AH47: 赵志辉 | AI47: 2025-12-29 16:07:14 | AJ47: 186****4207‎‎‎‬‬‬ | AK47: 2025-12-30 08:39:46 | AL47: 7551083218 | AM47: 是
A48: SF5106184196433 | B48: 取宝-物流服务 | C48: WP25122982110985 | D48: 未导出 | E48: BAT251229032048 | F48: 已完成 | H48: 18664174207 | I48: 派送成功 | J48: 未打印 | K48: 2025-12-30 12:00 | L48: 邹*华 | M48: 186****6788‎‎‎‬‬‬ | N48: *******6788‎‎‎‬‬‬ | P48: 广东省东莞市东城街道东纵路东城段208号 东城万达中心写**********‎‎‎‬‬‬ | Q48: 邹*华 | R48: *******6788‎‎‎‬‬‬ | S48: 进店取立充充电宝的宝2个 | T48: 麻涌喜得雀． CoFiTi 24h智能棋牌室 | U48: 广东省东莞市麻涌镇************* ************************‎‎‎‬‬‬ | V48: 充电宝 | W48: 2 | X48: 1 | Z48: 寄付月结 | AA48: 顺丰标快 | AE48: 否 | AF48: 2025-12-29 10:30:16 | AG48: 186****6788 | AH48: 赵志辉 | AI48: 2025-12-29 16:08:10 | AJ48: 186****4207‎‎‎‬‬‬ | AK48: 2025-12-30 08:39:46 | AL48: 7551083218 | AM48: 是
A49: SF5106533894875 | B49: 取宝-物流服务 | C49: WP25122672851944 | D49: 未导出 | E49: BAT251226106430 | F49: 已完成 | H49: 13580986295 | I49: 派送成功 | J49: 未打印 | K49: 2025-12-27 12:00 | L49: 邹*华 | M49: 186****6788‎‎‎‬‬‬ | N49: *******6788‎‎‎‬‬‬ | P49: 广东省东莞市东城街道东纵路东城段208号 东城万达中心写**********‎‎‎‬‬‬ | Q49: 邹*华 | R49: *******6788‎‎‎‬‬‬ | S49: 门口取立充充电宝的宝2个 | T49: 凤岗泰国菜 | U49: 广东省 东莞市凤岗镇********************‎‎‎‬‬‬ | V49: 充电宝 | W49: 2 | X49: 1 | Z49: 寄付月结 | AA49: 顺丰特快 | AE49: 否 | AF49: 2025-12-26 13:47:40 | AG49: 186****6788 | AH49: 王孚群 | AI49: 2025-12-26 14:29:51 | AJ49: 135****6295‎‎‎‬‬‬ | AK49: 2025-12-27 08:32:07 | AL49: 7551083218 | AM49: 是
A50: SF3268938193753 | B50: 取宝-物流服务 | C50: WP25122672851222 | D50: 未导出 | E50: BAT251226106348 | F50: 已完成 | H50: 13580986295 | I50: 派送成功 | J50: 未打印 | K50: 2025-12-27 12:00 | L50: 邹*华 | M50: 186****6788‎‎‎‬‬‬ | N50: *******6788‎‎‎‬‬‬ | P50: 广东省东莞市东城街道东纵路东城段208号 东城万达中心写**********‎‎‎‬‬‬ | Q50: 邹*华 | R50: *******6788‎‎‎‬‬‬ | S50: 门口取立充充电宝的宝3个 | T50: 凤岗泰国菜 | U50: 广东省 东莞市凤岗镇********************‎‎‎‬‬‬ | V50: 充电宝 | W50: 3 | X50: 1 | Z50: 寄付月结 | AA50: 顺丰特快 | AE50: 否 | AF50: 2025-12-26 13:47:40 | AG50: 186****6788 | AH50: 王孚群 | AI50: 2025-12-26 14:31:47 | AJ50: 135****6295‎‎‎‬‬‬ | AK50: 2025-12-27 08:32:07 | AL50: 7551083218 | AM50: 是
A51: SF5105887607240 | B51: 取宝-物流服务 | C51: WP25122672330152 | D51: 未导出 | E51: BAT251226044989 | F51: 已完成 | H51: 13928928825 | I51: 派送成功 | J51: 未打印 | K51: 2025-12-27 12:00 | L51: 邹*华 | M51: 186****6788‎‎‎‬‬‬ | N51: *******6788‎‎‎‬‬‬ | P51: 广东省东莞市东城街道东纵路东城段208号 东城万达中心写**********‎‎‎‬‬‬ | Q51: 邹*华 | R51: *******6788‎‎‎‬‬‬ | S51: 进店取立充充电宝的宝2个 | T51: 新塘湖南湘当好 | U51: 广东省广州增程新塘镇** *******‎‎‎‬‬‬ | V51: 充电宝 | W51: 2 | X51: 1 | Z51: 寄付月结 | AA51: 顺丰特快 | AE51: 否 | AF51: 2025-12-26 10:46:36 | AG51: 186****6788 | AH51: 李德成 | AI51: 2025-12-26 10:58:18 | AJ51: 139****8825‎‎‎‬‬‬ | AK51: 2025-12-27 08:32:07 | AL51: 7551083218 | AM51: 是
A52: SF5105887607286 | B52: 取宝-物流服务 | C52: WP25122672328153 | D52: 未导出 | E52: BAT251226044771 | F52: 已完成 | H52: 13928928825 | I52: 派送成功 | J52: 未打印 | K52: 2025-12-27 12:00 | L52: 邹*华 | M52: 186****6788‎‎‎‬‬‬ | N52: *******6788‎‎‎‬‬‬ | P52: 广东省东莞市东城街道东纵路东城段208号 东城万达中心写**********‎‎‎‬‬‬ | Q52: 邹*华 | R52: *******6788‎‎‎‬‬‬ | S52: 进店取立充充电宝的宝2个 | T52: 新塘湖南湘当好 | U52: 广东省广州增程新塘镇** *******‎‎‎‬‬‬ | V52: 充电宝 | W52: 2 | X52: 1 | Z52: 寄付月结 | AA52: 顺丰特快 | AE52: 否 | AF52: 2025-12-26 10:46:36 | AG52: 186****6788 | AH52: 李德成 | AI52: 2025-12-26 11:01:26 | AJ52: 139****8825‎‎‎‬‬‬ | AK52: 2025-12-27 08:32:07 | AL52: 7551083218 | AM52: 是
A53: SF3268348952001 | B53: 取宝-物流服务 | C53: WP25122569291133 | D53: 未导出 | E53: BAT251225190999 | F53: 已取消 | H53: 13383848783 | I53: 已取消 | J53: 未打印 | L53: 吴*欣 | M53: 137****3997‎‎‎‬‬‬ | P53: 深圳 市南山区************‎‎‎‬‬‬ | Q53: 王* | R53: *******7266‎‎‎‬‬‬ | U53: 河南省***** *****‎‎‎‬‬‬ | V53: 充电宝 | W53: 5 | X53: 1 | Z53: 寄付月结 | AA53: 顺丰标快 | AE53: 否 | AF53: 2025-12-25 17:00:24 | AG53: 134****9085 | AL53: 7551083218 | AM53: 是
A54: SF3266463124793 | B54: 取宝-物流服务 | C54: WP25122463816787 | D54: 未导出 | E54: BAT251224103159 | F54: 已完成 | H54: 18681108584 | I54: 派送成功 | J54: 未打印 | K54: 2025-12-25 12:00 | L54: 邹*华 | M54: 186****6788‎‎‎‬‬‬ | N54: *******6788‎‎‎‬‬‬ | P54: 广东省东莞市东城街道东纵路东城段208号 东城万达中心写**********‎‎‎‬‬‬ | Q54: 邹*华 | R54: *******6788‎‎‎‬‬‬ | S54: 进店取立充充电宝的宝2个 | T54: 茶山罗浮山聚园土窑鸡 | U54: 广东省东莞市茶山镇* ************************‎‎‎‬‬‬ | V54: 充电宝 | W54: 2 | X54: 1 | Z54: 寄付月结 | AA54: 顺丰标快 | AE54: 否 | AF54: 2025-12-24 13:49:18 | AG54: 186****6788 | AH54: 戴文 | AI54: 2025-12-24 14:25:10 | AJ54: 186****8584‎‎‎‬‬‬ | AK54: 2025-12-25 08:41:54 | AL54: 7551083218 | AM54: 是
A55: SF3266463124493 | B55: 取宝-物流服务 | C55: WP25122463815724 | D55: 未导出 | E55: BAT251224103046 | F55: 已完成 | H55: 18681108584 | I55: 派送成功 | J55: 未打印 | K55: 2025-12-25 12:00 | L55: 邹*华 | M55: 186****6788‎‎‎‬‬‬ | N55: *******6788‎‎‎‬‬‬ | P55: 广东省东莞市东城街道东纵路东城段208号 东城万达中心写**********‎‎‎‬‬‬ | Q55: 邹*华 | R55: *******6788‎‎‎‬‬‬ | S55: 进店取立充充电宝的宝2个 | T55: 茶山罗浮山聚园土窑鸡 | U55: 广东省东莞市茶山镇* ************************‎‎‎‬‬‬ | V55: 充电宝 | W55: 2 | X55: 1 | Z55: 寄付月结 | AA55: 顺丰标快 | AE55: 否 | AF55: 2025-12-24 13:49:18 | AG55: 186****6788 | AH55: 戴文 | AI55: 2025-12-24 14:28:10 | AJ55: 186****8584‎‎‎‬‬‬ | AK55: 2025-12-25 08:41:54 | AL55: 7551083218 | AM55: 是
A56: SF3266726759704 | B56: 取宝-物流服务 | C56: WP25122359261257 | D56: 未导出 | E56: BAT251223122625 | F56: 已完成 | H56: 13688807096 | I56: 派送成功 | J56: 未打印 | K56: 2025-12-24 12:00 | L56: 吴*欣 | M56: 137****3997‎‎‎‬‬‬ | N56: *******3997‎‎‎‬‬‬ | O56: 嘉** | P56: 广东省深圳市南山 区*********************‎‎‎‬‬‬ | Q56: 魅***************) | R56: *******3997‎‎‎‬‬‬ | S56: 机柜SN：24110086513 电宝SN：D1219000831 | U56: 广东省深圳市龙华区 **********************************‎‎‎‬‬‬ | V56: 充电宝 | W56: 1 | X56: 1 | Z56: 寄付月结 | AA56: 顺丰标快 | AE56: 否 | AF56: 2025-12-23 14:46:56 | AG56: 137****3997 | AH56: 肖博 | AI56: 2025-12-23 16:29:35 | AJ56: 136****7096‎‎‎‬‬‬ | AK56: 2025-12-25 11:33:27 | AL56: 7551083218 | AM56: 是
A57: SF3266855056465 | B57: 取宝-物流服务 | C57: WP25122254986109 | D57: 未导出 | E57: BAT251222190586 | F57: 处理中 | H57: 17328290159 | I57: 未收件 | J57: 未打印 | L57: 邹*华 | M57: 186****6788‎‎‎‬‬‬ | N57: *******6788‎‎‎‬‬‬ | P57: 广东省东莞市东城街道东纵路东城段208号 东城万达中心写**********‎‎‎‬‬‬ | Q57: 邹*华 | R57: *******6788‎‎‎‬‬‬ | S57: 进店取立充充电宝的宝2个 | T57: 石湾四川幺妹烤鱼(清湾路店) | U57: 广东省惠州市博罗县***************** **********‎‎‎‬‬‬ | V57: 充电宝 | W57: 2 | X57: 1 | Z57: 寄付月结 | AA57: 顺丰标快 | AE57: 否 | AF57: 2025-12-22 16:33:00 | AG57: 186****6788 | AH57: 吴有成 | AJ57: 173****0159‎‎‎‬‬‬ | AL57: 7551083218 | AM57: 是
A58: SF3266855268219 | B58: 取宝-物流服务 | C58: WP25122254975574 | D58: 未导出 | E58: BAT251222189536 | F58: 已取消 | H58: 15707520063 | I58: 已取消 | J58: 未打印 | L58: 邹*华 | M58: 186****6788‎‎‎‬‬‬ | N58: *******6788‎‎‎‬‬‬ | P58: 广东省东莞市东城街道东纵路东城段208号 东城万达中心写**********‎‎‎‬‬‬ | Q58: 邹*华 | R58: *******6788‎‎‎‬‬‬ | S58: 进店取立充充电宝的宝2个 | T58: 石湾四川幺妹烤鱼(清湾路店) | U58: 广东省惠州市博罗县*** **************************‎‎‎‬‬‬ | V58: 充电宝 | W58: 2 | X58: 1 | Z58: 寄付月结 | AA58: 顺丰标快 | AE58: 否 | AF58: 2025-12-22 16:31:40 | AG58: 186****6788 | AL58: 7551083218 | AM58: 是
A59: SF5105010030170 | B59: 取宝-物流服务 | C59: WP25122254972173 | D59: 未导出 | E59: BAT251222189191 | F59: 已完成 | H59: 17328290159 | I59: 派送成功 | J59: 未打印 | K59: 2025-12-23 12:00 | L59: 邹*华 | M59: 186****6788‎‎‎‬‬‬ | N59: *******6788‎‎‎‬‬‬ | P59: 广东省东莞市东城街道东纵路东城段208号 东城万达中心写**********‎‎‎‬‬‬ | Q59: 邹*华 | R59: *******6788‎‎‎‬‬‬ | S59: 进店取立充充电宝的宝2个 | T59: 石湾四川幺妹烤鱼(清湾路店) | U59: 广东省惠州市博罗县*** **************************‎‎‎‬‬‬ | V59: 充电宝 | W59: 2 | X59: 1 | Z59: 寄付月结 | AA59: 顺丰标快 | AE59: 否 | AF59: 2025-12-22 16:31:40 | AG59: 186****6788 | AH59: 吴有成 | AI59: 2025-12-22 17:16:53 | AJ59: 173****0159‎‎‎‬‬‬ | AK59: 2025-12-23 08:31:39 | AL59: 7551083218 | AM59: 是
A60: SF5105173211669 | B60: 取宝-物流服务 | C60: WP25122253613424 | D60: 未导出 | E60: BAT251222044996 | F60: 已完成 | H60: 13929434923 | I60: 派送成功 | J60: 未打印 | K60: 2025-12-23 12:00 | L60: 邹*华 | M60: 186****6788‎‎‎‬‬‬ | N60: *******6788‎‎‎‬‬‬ | P60: 广东省东莞市东城街道东纵路东城段208号 东城万达中心写**********‎‎‎‬‬‬ | Q60: 邹*华 | R60: *******6788‎‎‎‬‬‬ | S60: 进店取立充充电宝的宝2个 | T60: 企石小球莞24h自助台球(深巷店 | U60: 东莞市企石镇* *****************************‎‎‎‬‬‬ | V60: 充电宝 | W60: 2 | X60: 1 | Z60: 寄付月结 | AA60: 顺丰标快 | AE60: 否 | AF60: 2025-12-22 10:51:26 | AG60: 186****6788 | AH60: 陈英岳 | AI60: 2025-12-22 11:21:02 | AJ60: 139****4923‎‎‎‬‬‬ | AK60: 2025-12-22 16:42:22 | AL60: 7551083218 | AM60: 是
A61: SF5105173211350 | B61: 取宝-物流服务 | C61: WP25122253610636 | D61: 未导出 | E61: BAT251222044696 | F61: 已完成 | H61: 13929434923 | I61: 派送成功 | J61: 未打印 | K61: 2025-12-23 12:00 | L61: 邹*华 | M61: 186****6788‎‎‎‬‬‬ | N61: *******6788‎‎‎‬‬‬ | P61: 广东省东莞市东城街道东纵路东城段208号 东城万达中心写**********‎‎‎‬‬‬ | Q61: 邹*华 | R61: *******6788‎‎‎‬‬‬ | S61: 进店取立充充电宝的宝2个 | T61: 企石小球莞24h自助台球(深巷店 | U61: 东莞市企石镇* *****************************‎‎‎‬‬‬ | V61: 充电宝 | W61: 2 | X61: 1 | Z61: 寄付月结 | AA61: 顺丰标快 | AE61: 否 | AF61: 2025-12-22 10:51:26 | AG61: 186****6788 | AH61: 陈英岳 | AI61: 2025-12-22 11:22:50 | AJ61: 139****4923‎‎‎‬‬‬ | AK61: 2025-12-22 16:42:22 | AL61: 7551083218 | AM61: 是
A62: SF5105657330911 | B62: 取宝-物流服务 | C62: WP25122048990769 | D62: 未导出 | E62: BAT251220087082 | F62: 已完成 | H62: 13225120974 | I62: 派送成功 | J62: 未打印 | K62: 2025-12-21 12:00 | L62: 邹*华 | M62: 186****6788‎‎‎‬‬‬ | N62: *******6788‎‎‎‬‬‬ | P62: 广东省东莞市东城街道东纵路东城段208号 东城万达中心写**********‎‎‎‬‬‬ | Q62: 邹*华 | R62: *******6788‎‎‎‬‬‬ | S62: 进店取立充充电宝的宝2个 | T62: 谢岗兄弟烧烤 | U62: 广东省东莞市谢岗 镇******‎‎‎‬‬‬ | V62: 充电宝 | W62: 2 | X62: 1 | Z62: 寄付月结 | AA62: 顺丰特快 | AE62: 否 | AF62: 2025-12-20 13:48:14 | AG62: 186****6788 | AH62: 于观国 | AI62: 2025-12-20 14:26:27 | AJ62: 132****0974‎‎‎‬‬‬ | AK62: 2025-12-22 08:25:24 | AL62: 7551083218 | AM62: 是
A63: SF5105657330074 | B63: 取宝-物流服务 | C63: WP25122048989846 | D63: 未导出 | E63: BAT251220086977 | F63: 已完成 | H63: 13225120974 | I63: 派送成功 | J63: 未打印 | K63: 2025-12-21 12:00 | L63: 邹*华 | M63: 186****6788‎‎‎‬‬‬ | N63: *******6788‎‎‎‬‬‬ | P63: 广东省东莞市东城街道东纵路东城段208号 东城万达中心写**********‎‎‎‬‬‬ | Q63: 邹*华 | R63: *******6788‎‎‎‬‬‬ | S63: 进店取立充充电宝的宝2个 | T63: 谢岗兄弟烧烤 | U63: 广东省东莞市谢岗 镇******‎‎‎‬‬‬ | V63: 充电宝 | W63: 2 | X63: 1 | Z63: 寄付月结 | AA63: 顺丰特快 | AE63: 否 | AF63: 2025-12-20 13:48:14 | AG63: 186****6788 | AH63: 于观国 | AI63: 2025-12-20 14:25:11 | AJ63: 132****0974‎‎‎‬‬‬ | AK63: 2025-12-22 08:25:24 | AL63: 7551083218 | AM63: 是
A64: SF3266238182607 | B64: 取宝-物流服务 | C64: WP25121943581823 | D64: 未导出 | E64: BAT251219026276 | F64: 已完成 | H64: 18420076627 | I64: 派送成功 | J64: 未打印 | K64: 2025-12-20 12:00 | L64: 邹*华 | M64: 186****6788‎‎‎‬‬‬ | N64: *******6788‎‎‎‬‬‬ | P64: 广东省东莞市东城街道东纵路东城段208号 东城万达中心写**********‎‎‎‬‬‬ | Q64: 邹*华 | R64: *******6788‎‎‎‬‬‬ | S64: 进店取立充充电宝的宝2个 | T64: 石湾田园鹅庄 | U64: 广东省惠州市博罗 县*********************‎‎‎‬‬‬ | V64: 充电宝 | W64: 2 | X64: 1 | Z64: 寄付月结 | AA64: 顺丰标快 | AE64: 否 | AF64: 2025-12-19 09:34:29 | AG64: 186****6788 | AH64: 杨雄卫 | AI64: 2025-12-19 15:58:20 | AJ64: 184****6627‎‎‎‬‬‬ | AK64: 2025-12-20 09:07:21 | AL64: 7551083218 | AM64: 是
A65: SF3266238182625 | B65: 取宝-物流服务 | C65: WP25121943580637 | D65: 未导出 | E65: BAT251219026135 | F65: 已完成 | H65: 18420076627 | I65: 派送成功 | J65: 未打印 | K65: 2025-12-20 12:00 | L65: 邹*华 | M65: 186****6788‎‎‎‬‬‬ | N65: *******6788‎‎‎‬‬‬ | P65: 广东省东莞市东城街道东纵路东城段208号 东城万达中心写**********‎‎‎‬‬‬ | Q65: 邹*华 | R65: *******6788‎‎‎‬‬‬ | S65: 进店取立充充电宝的宝2个 | T65: 石湾田园鹅庄 | U65: 广东省惠州市博罗 县*********************‎‎‎‬‬‬ | V65: 充电宝 | W65: 2 | X65: 1 | Z65: 寄付月结 | AA65: 顺丰标快 | AE65: 否 | AF65: 2025-12-19 09:34:29 | AG65: 186****6788 | AH65: 杨雄卫 | AI65: 2025-12-19 15:59:08 | AJ65: 184****6627‎‎‎‬‬‬ | AK65: 2025-12-20 09:07:21 | AL65: 7551083218 | AM65: 是
A66: SF3261485909095 | B66: 取宝-物流服务 | C66: WP25121840582186 | D66: 未导出 | E66: BAT251218201942 | F66: 已完成 | H66: 13169541816 | I66: 派送成功 | J66: 未打印 | K66: 2025-12-19 12:00 | L66: 邹*华 | M66: 186****6788‎‎‎‬‬‬ | N66: *******6788‎‎‎‬‬‬ | P66: 广东省东莞市东城街道东纵路东城段208号 东城万达中心写**********‎‎‎‬‬‬ | Q66: 邹*华 | R66: *******6788‎‎‎‬‬‬ | S66: 进店取立充充电宝的宝2个 | T66: 洪梅星动酒吧 | U66: 广东省东莞市洪梅 镇*********************‎‎‎‬‬‬ | V66: 充电宝 | W66: 2 | X66: 1 | Z66: 寄付月结 | AA66: 顺丰特快 | AE66: 否 | AF66: 2025-12-18 16:57:37 | AG66: 186****6788 | AH66: 江许放 | AI66: 2025-12-18 18:15:22 | AJ66: 131****1816‎‎‎‬‬‬ | AK66: 2025-12-19 08:38:09 | AL66: 7551083218 | AM66: 是
A67: SF3261485909923 | B67: 取宝-物流服务 | C67: WP25121840577913 | D67: 未导出 | E67: BAT251218201494 | F67: 已完成 | H67: 13169541816 | I67: 派送成功 | J67: 未打印 | K67: 2025-12-19 12:00 | L67: 邹*华 | M67: 186****6788‎‎‎‬‬‬ | N67: *******6788‎‎‎‬‬‬ | P67: 广东省东莞市东城街道东纵路东城段208号 东城万达中心写**********‎‎‎‬‬‬ | Q67: 邹*华 | R67: *******6788‎‎‎‬‬‬ | S67: 进店取立充充电宝的宝2个 | T67: 洪梅星动酒吧 | U67: 广东省东莞市洪梅 镇*********************‎‎‎‬‬‬ | V67: 充电宝 | W67: 2 | X67: 1 | Z67: 寄付月结 | AA67: 顺丰特快 | AE67: 否 | AF67: 2025-12-18 16:57:37 | AG67: 186****6788 | AH67: 江许放 | AI67: 2025-12-18 18:14:44 | AJ67: 131****1816‎‎‎‬‬‬ | AK67: 2025-12-19 08:38:09 | AL67: 7551083218 | AM67: 是
A68: SF3261793330250 | B68: 取宝-物流服务 | C68: WP25121838974799 | D68: 未导出 | E68: BAT251218031525 | F68: 待接单 | H68: 13798847017 | I68: 未收件 | J68: 未打印 | L68: 邹*华 | M68: 186****6788‎‎‎‬‬‬ | N68: *******6788‎‎‎‬‬‬ | P68: 广东省东莞市东城街道东纵路东城段208号 东城万达中心写**********‎‎‎‬‬‬ | Q68: 邹*华 | R68: *******6788‎‎‎‬‬‬ | S68: 进店取立充充电宝的宝2个 | U68: 广东省东莞市凤清路80号凤临阁商铺3栋325 凤岗******** **‎‎‎‬‬‬ | V68: 充电宝 | W68: 2 | X68: 1 | Z68: 寄付月结 | AA68: 顺丰标快 | AE68: 否 | AF68: 2025-12-18 10:15:34 | AG68: 186****6788 | AL68: 7551083218 | AM68: 是
A69: SF3261793330975 | B69: 取宝-物流服务 | C69: WP25121838973172 | D69: 未导出 | E69: BAT251218031318 | F69: 处理中 | H69: 13798847017 | I69: 未收件 | J69: 未打印 | L69: 邹*华 | M69: 186****6788‎‎‎‬‬‬ | N69: *******6788‎‎‎‬‬‬ | P69: 广东省东莞市东城街道东纵路东城段208号 东城万达中心写**********‎‎‎‬‬‬ | Q69: 邹*华 | R69: *******6788‎‎‎‬‬‬ | S69: 进店取立充充电宝的宝2个 | U69: 广东省东莞市凤清路80号凤临阁商铺3栋325 凤岗******** **‎‎‎‬‬‬ | V69: 充电宝 | W69: 2 | X69: 1 | Z69: 寄付月结 | AA69: 顺丰标快 | AE69: 否 | AF69: 2025-12-18 10:15:34 | AG69: 186****6788 | AH69: 聂仁春 | AJ69: 136****5002‎‎‎‬‬‬ | AL69: 7551083218 | AM69: 是
A70: SF3261643577268 | B70: 取宝-物流服务 | C70: WP25121734967981 | D70: 未导出 | E70: BAT251217124799 | F70: 已完成 | H70: 18420076627 | I70: 派送成功 | J70: 未打印 | K70: 2025-12-18 12:00 | L70: 邹*华 | M70: 186****6788‎‎‎‬‬‬ | N70: *******6788‎‎‎‬‬‬ | P70: 广东省东莞市东城街道东纵路东城段208号 东城万达中心写**********‎‎‎‬‬‬ | Q70: 邹*华 | R70: *******6788‎‎‎‬‬‬ | S70: 进店取立充充电宝的宝2个 | T70: 石湾田园·舍 | U70: 广东省 惠州市博罗县********************‎‎‎‬‬‬ | V70: 充电宝 | W70: 2 | X70: 1 | Z70: 寄付月结 | AA70: 顺丰标快 | AE70: 否 | AF70: 2025-12-17 14:11:35 | AG70: 186****6788 | AH70: 杨雄卫 | AI70: 2025-12-17 15:19:56 | AJ70: 184****6627‎‎‎‬‬‬ | AK70: 2025-12-18 08:31:05 | AL70: 7551083218 | AM70: 是
A71: SF3261643546502 | B71: 取宝-物流服务 | C71: WP25121734966613 | D71: 未导出 | E71: BAT251217124658 | F71: 已完成 | H71: 18420076627 | I71: 派送成功 | J71: 未打印 | K71: 2025-12-18 12:00 | L71: 邹*华 | M71: 186****6788‎‎‎‬‬‬ | N71: *******6788‎‎‎‬‬‬ | P71: 广东省东莞市东城街道东纵路东城段208号 东城万达中心写**********‎‎‎‬‬‬ | Q71: 邹*华 | R71: *******6788‎‎‎‬‬‬ | S71: 进店取立充充电宝的宝2个 | T71: 石湾田园·舍 | U71: 广东省 惠州市博罗县********************‎‎‎‬‬‬ | V71: 充电宝 | W71: 2 | X71: 1 | Z71: 寄付月结 | AA71: 顺丰标快 | AE71: 否 | AF71: 2025-12-17 14:11:36 | AG71: 186****6788 | AH71: 杨雄卫 | AI71: 2025-12-17 15:21:00 | AJ71: 184****6627‎‎‎‬‬‬ | AK71: 2025-12-18 08:31:05 | AL71: 7551083218 | AM71: 是
A72: SF3260991839038 | B72: 取宝-物流服务 | C72: WP25121319314858 | D72: 未导出 | E72: BAT251213078155 | F72: 已完成 | H72: 18137035839 | I72: 派送成功 | J72: 未打印 | K72: 2025-12-14 12:00 | L72: 高 | M72: 159****1002‎‎‎‬‬‬ | P72: 河南省商丘市永城市聚客隆时尚生活广 **********‎‎‎‬‬‬ | Q72: 高 | R72: *******1002‎‎‎‬‬‬ | U72: 河南省商丘市永城市中原路与商 业路交汇处**********‎‎‎‬‬‬ | V72: 充电宝 | W72: 2 | X72: 1 | Z72: 寄付月结 | AA72: 顺丰标快 | AE72: 否 | AF72: 2025-12-13 12:29:21 | AG72: 137****1781 | AH72: 王甲 | AI72: 2025-12-13 13:09:36 | AJ72: 181****5839‎‎‎‬‬‬ | AK72: 2025-12-13 17:48:58 | AL72: 7551083218 | AM72: 是
A73: SF3260990255392 | B73: 取宝-物流服务 | C73: WP25121319307957 | D73: 未导出 | E73: BAT251213077338 | F73: 已完成 | H73: 18537381800 | I73: 派送成功 | J73: 未打印 | K73: 2025-12-14 12:00 | L73: 高 | M73: 159****1002‎‎‎‬‬‬ | P73: 河南省兰考县******** ******************‎‎‎‬‬‬ | Q73: 高 | R73: *******1002‎‎‎‬‬‬ | U73: 河南省兰考县** *************‎‎‎‬‬‬ | V73: 充电宝 | W73: 2 | X73: 1 | Z73: 寄付月结 | AA73: 顺丰标快 | AE73: 否 | AF73: 2025-12-13 12:24:18 | AG73: 137****1781 | AH73: 张欢欢 | AI73: 2025-12-13 14:15:19 | AJ73: 185****1800‎‎‎‬‬‬ | AK73: 2025-12-14 10:08:49 | AL73: 7551083218 | AM73: 是
A74: SF3260926780376 | B74: 取宝-物流服务 | C74: WP25121319250292 | D74: 未导出 | E74: BAT251213070804 | F74: 已完成 | H74: 18137035839 | I74: 派送成功 | J74: 未打印 | K74: 2025-12-14 12:00 | L74: 高 | M74: 159****1002‎‎‎‬‬‬ | P74: 河南省商丘市永城市聚客隆时尚生活广 **********‎‎‎‬‬‬ | Q74: 高 | R74: *******1002‎‎‎‬‬‬ | U74: 河南省商丘市永城市中原路与商 业路交汇处**********‎‎‎‬‬‬ | V74: 充电宝 | W74: 4 | X74: 1 | Z74: 寄付月结 | AA74: 顺丰标快 | AE74: 否 | AF74: 2025-12-13 11:59:17 | AG74: 137****1781 | AH74: 王甲 | AI74: 2025-12-13 13:08:44 | AJ74: 181****5839‎‎‎‬‬‬ | AK74: 2025-12-13 17:48:58 | AL74: 7551083218 | AM74: 是
A75: SF3260922986699 | B75: 取宝-物流服务 | C75: WP25121319211492 | D75: 未导出 | E75: BAT251213066612 | F75: 已取消 | H75: 18537381800 | I75: 已取消 | J75: 未打印 | L75: 高 | M75: 159****1002‎‎‎‬‬‬ | P75: 河南省兰考县******** ******************‎‎‎‬‬‬ | Q75: 高 | R75: *******1002‎‎‎‬‬‬ | U75: 河南省兰考县** *************‎‎‎‬‬‬ | V75: 充电宝 | W75: 2 | X75: 1 | Z75: 寄付月结 | AA75: 顺丰标快 | AE75: 否 | AF75: 2025-12-13 11:45:19 | AG75: 137****1781 | AH75: 张欢欢 | AJ75: 185****1800‎‎‎‬‬‬ | AL75: 7551083218 | AM75: 是
A76: SF3260923645215 | B76: 取宝-物流服务 | C76: WP25121319205711 | D76: 未导出 | E76: BAT251213065988 | F76: 已完成 | H76: 13321873014 | I76: 派送成功 | J76: 未打印 | K76: 2025-12-14 12:00 | L76: 高 | M76: 159****1002‎‎‎‬‬‬ | P76: 河南省兰考县******** ******************‎‎‎‬‬‬ | Q76: 高 | R76: *******1002‎‎‎‬‬‬ | U76: 河南省兰考县************************ *******‎‎‎‬‬‬ | V76: 充电宝 | W76: 2 | X76: 1 | Z76: 寄付月结 | AA76: 顺丰标快 | AE76: 否 | AF76: 2025-12-13 11:43:23 | AG76: 137****1781 | AH76: 李亚鸣 | AI76: 2025-12-13 12:19:16 | AJ76: 133****3014‎‎‎‬‬‬ | AK76: 2025-12-14 10:08:49 | AL76: 7551083218 | AM76: 是
A77: SF3260247668265 | B77: 取宝-物流服务 | C77: WP25121319091559 | D77: 未导出 | E77: BAT251213053946 | F77: 已完成 | H77: 19138167163 | I77: 派送成功 | J77: 未打印 | K77: 2025-12-14 12:00 | L77: 高 | M77: 159****1002‎‎‎‬‬‬ | P77: 河南省宁陵县******** ***************‎‎‎‬‬‬ | Q77: 高 | R77: *******1002‎‎‎‬‬‬ | U77: 河南省宁陵县城关镇珠江路中央国际C区*********** ******‎‎‎‬‬‬ | V77: 充电宝 | W77: 2 | X77: 1 | Z77: 寄付月结 | AA77: 顺丰标快 | AE77: 否 | AF77: 2025-12-13 11:11:14 | AG77: 137****1781 | AH77: 李俊达 | AI77: 2025-12-13 12:11:35 | AJ77: 191****7163‎‎‎‬‬‬ | AK77: 2025-12-14 09:16:55 | AL77: 7551083218 | AM77: 是
A78: SF3260247668034 | B78: 取宝-物流服务 | C78: WP25121319063128 | D78: 未导出 | E78: BAT251213050820 | F78: 已完成 | H78: 13703704654 | I78: 派送成功 | J78: 未打印 | K78: 2025-12-14 12:00 | L78: 高*士 | M78: 159****1002‎‎‎‬‬‬ | P78: 河南省宁陵县******** ***************‎‎‎‬‬‬ | Q78: 高 | R78: *******1002‎‎‎‬‬‬ | S78: 机器SN24080059312 | U78: 河南 省宁陵县***************************‎‎‎‬‬‬ | V78: 充电宝 | W78: 2 | X78: 1 | Z78: 寄付月结 | AA78: 顺丰标快 | AE78: 否 | AF78: 2025-12-13 11:11:14 | AG78: 137****1781 | AH78: 李坤伦 | AI78: 2025-12-13 12:32:03 | AJ78: 137****4654‎‎‎‬‬‬ | AK78: 2025-12-14 09:16:55 | AL78: 7551083218 | AM78: 是
A79: SF3269408246618 | B79: 取宝-物流服务 | C79: WP25121214633019 | D79: 未导出 | E79: BAT251212150093 | F79: 已完成 | H79: 15817383404 | I79: 派送成功 | J79: 未打印 | K79: 2025-12-13 15:00 | L79: 何*忠 | M79: 158****6590‎‎‎‬‬‬ | P79: 江西省南昌市西湖区* **********‎‎‎‬‬‬ | Q79: 吴*红 | R79: *******6596‎‎‎‬‬‬ | U79: 深圳市南山区****** ****‎‎‎‬‬‬ | V79: 充电宝 | W79: 2 | X79: 1 | Z79: 寄付月结 | AA79: 顺丰标快 | AE79: 否 | AF79: 2025-12-12 15:07:37 | AG79: 134****9085 | AH79: 崔凯明 | AI79: 2025-12-12 15:12:19 | AJ79: 158****3404‎‎‎‬‬‬ | AK79: 2025-12-13 15:46:39 | AL79: 7551083218 | AM79: 是
A80: SF3278835817464 | B80: 取宝-物流服务 | C80: WP25121110669016 | D80: 未导出 | E80: BAT251211255254 | F80: 已完成 | H80: 15338371225 | I80: 派送成功 | J80: 未打印 | K80: 2025-12-12 12:00 | L80: 邹*华 | M80: 186****6788‎‎‎‬‬‬ | N80: *******6788‎‎‎‬‬‬ | P80: 广东省东莞市东城街道东纵路东城段208号 东城万达中心写**********‎‎‎‬‬‬ | Q80: 邹*华 | R80: *******6788‎‎‎‬‬‬ | S80: 进店取立充充电宝的宝1个 | T80: 高埗稻田休闲垂钓鱼 | U80: 广东省东莞市高埗镇*********** *****************‎‎‎‬‬‬ | V80: 充电宝 | W80: 1 | X80: 1 | Z80: 寄付月结 | AA80: 顺丰标快 | AE80: 否 | AF80: 2025-12-11 17:35:38 | AG80: 186****6788 | AH80: 万建东 | AI80: 2025-12-11 18:08:24 | AJ80: 153****1225‎‎‎‬‬‬ | AK80: 2025-12-12 08:59:28 | AL80: 7551083218 | AM80: 是
A81: SF3278721881453 | B81: 取宝-物流服务 | C81: WP25121003636092 | D81: 未导出 | E81: BAT251210043900 | F81: 已完成 | H81: 13268703125 | I81: 派送成功 | J81: 未打印 | K81: 2025-12-11 12:00 | L81: 邹*华 | M81: 186****6788‎‎‎‬‬‬ | N81: *******6788‎‎‎‬‬‬ | P81: 广东省东莞市东城街道东纵路东城段208号 东城万达中心写**********‎‎‎‬‬‬ | Q81: 邹*华 | R81: *******6788‎‎‎‬‬‬ | S81: 进店取立充充电宝的宝2个 | T81: 高埗文婷川菜馆 | U81: 广东省东莞市东莞 市高埗镇******************‎‎‎‬‬‬ | V81: 充电宝 | W81: 2 | X81: 1 | Z81: 寄付月结 | AA81: 顺丰标快 | AE81: 否 | AF81: 2025-12-10 10:37:18 | AG81: 186****6788 | AH81: 吴凤章 | AI81: 2025-12-10 12:47:17 | AJ81: 132****3125‎‎‎‬‬‬ | AK81: 2025-12-11 08:24:03 | AL81: 7551083218 | AM81: 是
A82: SF3278721883531 | B82: 取宝-物流服务 | C82: WP25121003634558 | D82: 未导出 | E82: BAT251210043735 | F82: 已完成 | H82: 13268703125 | I82: 派送成功 | J82: 未打印 | K82: 2025-12-11 12:00 | L82: 邹*华 | M82: 186****6788‎‎‎‬‬‬ | N82: *******6788‎‎‎‬‬‬ | P82: 广东省东莞市东城街道东纵路东城段208号 东城万达中心写**********‎‎‎‬‬‬ | Q82: 邹*华 | R82: *******6788‎‎‎‬‬‬ | S82: 进店取立充充电宝的宝3个 | T82: 高埗文婷川菜馆 | U82: 广东省东莞市东莞 市高埗镇******************‎‎‎‬‬‬ | V82: 充电宝 | W82: 3 | X82: 1 | Z82: 寄付月结 | AA82: 顺丰标快 | AE82: 否 | AF82: 2025-12-10 10:37:18 | AG82: 186****6788 | AH82: 吴凤章 | AI82: 2025-12-10 12:43:57 | AJ82: 132****3125‎‎‎‬‬‬ | AK82: 2025-12-11 08:24:03 | AL82: 7551083218 | AM82: 是
A83: SF3278938703425 | B83: 取宝-物流服务 | C83: WP25120999180916 | D83: 未导出 | E83: BAT251209118572 | F83: 处理中 | H83: 18681091730 | I83: 未收件 | J83: 未打印 | L83: 邹*华 | M83: 186****6788‎‎‎‬‬‬ | N83: *******6788‎‎‎‬‬‬ | P83: 广东省东莞市东城街道东纵路东城段208号 东城万达中心写**********‎‎‎‬‬‬ | Q83: 邹*华 | R83: *******6788‎‎‎‬‬‬ | S83: 取门口的立充充电宝的宝2个 | T83: 塘厦美宜佳便利店（花园街1号店） | U83: 广东省东莞市塘厦镇***************************** *‎‎‎‬‬‬ | V83: 充电宝 | W83: 2 | X83: 1 | Z83: 寄付月结 | AA83: 顺丰标快 | AE83: 否 | AF83: 2025-12-09 14:03:22 | AG83: 186****6788 | AH83: 卢松松 | AJ83: 186****1730‎‎‎‬‬‬ | AL83: 7551083218 | AM83: 是
A84: SF3269246462710 | B84: 取宝-物流服务 | C84: WP25120895179698 | D84: 未导出 | E84: BAT251208254138 | F84: 已完成 | H84: 15899913232 | I84: 派送成功 | J84: 未打印 | K84: 2025-12-09 12:00 | L84: 邹*华 | M84: 186****6788‎‎‎‬‬‬ | N84: *******6788‎‎‎‬‬‬ | P84: 广东省东莞市东城街道东纵路东城段208号 东城万达中心写**********‎‎‎‬‬‬ | Q84: 邹*华 | R84: *******6788‎‎‎‬‬‬ | S84: 进店取立充充电宝的宝1个 | T84: 洪梅湘味石锅鱼烤鱼 | U84: 广东省东莞市洪梅镇***************** **‎‎‎‬‬‬ | V84: 充电宝 | W84: 1 | X84: 1 | Z84: 寄付月结 | AA84: 顺丰标快 | AE84: 否 | AF84: 2025-12-08 17:04:37 | AG84: 186****6788 | AH84: 苏洁 | AI84: 2025-12-08 17:21:42 | AJ84: 158****3232‎‎‎‬‬‬ | AK84: 2025-12-09 08:11:39 | AL84: 7551083218 | AM84: 是
A85: SF3278194935152 | B85: 取宝-物流服务 | C85: WP25120894825677 | D85: 未导出 | E85: BAT251208217452 | F85: 处理中 | H85: 15899913232 | I85: 未收件 | J85: 未打印 | L85: 邹*华 | M85: 186****6788‎‎‎‬‬‬ | N85: *******6788‎‎‎‬‬‬ | P85: 广东省东莞市东城街道东纵路东城段208号 东城万达中心写**********‎‎‎‬‬‬ | Q85: 邹*华 | R85: *******6788‎‎‎‬‬‬ | S85: 进店取立充充电宝的坏宝1个电话弹宝 | T85: 洪梅湘味石锅鱼烤鱼 | U85: 广东省东莞市洪梅镇***************** **‎‎‎‬‬‬ | V85: 充电宝 | W85: 1 | X85: 1 | Z85: 寄付月结 | AA85: 顺丰标快 | AE85: 否 | AF85: 2025-12-08 16:22:27 | AG85: 186****6788 | AH85: 苏洁 | AJ85: 158****3232‎‎‎‬‬‬ | AL85: 7551083218 | AM85: 是
A86: SF3262727180607 | B86: 取宝-物流服务 | C86: WP25120687957947 | D86: 未导出 | E86: BAT251206092980 | F86: 已完成 | H86: 19154960769 | I86: 派送成功 | J86: 未打印 | K86: 2025-12-07 12:00 | L86: 邹*华 | M86: 186****6788‎‎‎‬‬‬ | N86: *******6788‎‎‎‬‬‬ | P86: 广东省东莞市东城街道东纵路东城段208号 东城万达中心写**********‎‎‎‬‬‬ | Q86: 邹*华 | R86: *******6788‎‎‎‬‬‬ | S86: 门口取立充充电宝的宝2个 | T86: 凤岗柒号棋牌室 | U86: 广东省东莞市凤岗镇***************** **‎‎‎‬‬‬ | V86: 充电宝 | W86: 2 | X86: 1 | Z86: 寄付月结 | AA86: 顺丰特快 | AE86: 否 | AF86: 2025-12-06 12:39:43 | AG86: 186****6788 | AH86: 莫永豪 | AI86: 2025-12-06 13:06:53 | AJ86: 191****0769‎‎‎‬‬‬ | AK86: 2025-12-07 08:20:41 | AL86: 7551083218 | AM86: 是
A87: SF3262727180661 | B87: 取宝-物流服务 | C87: WP25120687956515 | D87: 未导出 | E87: BAT251206092814 | F87: 已完成 | H87: 19154960769 | I87: 派送成功 | J87: 未打印 | K87: 2025-12-07 12:00 | L87: 邹*华 | M87: 186****6788‎‎‎‬‬‬ | N87: *******6788‎‎‎‬‬‬ | P87: 广东省东莞市东城街道东纵路东城段208号 东城万达中心写**********‎‎‎‬‬‬ | Q87: 邹*华 | R87: *******6788‎‎‎‬‬‬ | S87: 门口取立充充电宝的宝2个 | T87: 凤岗柒号棋牌室 | U87: 广东省东莞市凤岗镇***************** **‎‎‎‬‬‬ | V87: 充电宝 | W87: 2 | X87: 1 | Z87: 寄付月结 | AA87: 顺丰特快 | AE87: 否 | AF87: 2025-12-06 12:39:43 | AG87: 186****6788 | AH87: 莫永豪 | AI87: 2025-12-06 13:08:07 | AJ87: 191****0769‎‎‎‬‬‬ | AK87: 2025-12-07 08:20:41 | AL87: 7551083218 | AM87: 是
A88: SF3274447743808 | B88: 取宝-物流服务 | C88: WP25120583519277 | D88: 未导出 | E88: BAT251205179884 | F88: 已取消 | H88: 13580632199 | I88: 已取消 | J88: 未打印 | L88: 吴*红 | M88: 137****6596‎‎‎‬‬‬ | P88: 深圳 市南山区************‎‎‎‬‬‬ | Q88: 邹*华 | R88: *******6788‎‎‎‬‬‬ | U88: 广东省东莞市东城街道东纵路东城段208号东城万达中心写字楼34层3401室（ 东莞市中**********‎‎‎‬‬‬ | V88: 充电宝 | W88: 5 | X88: 1 | Z88: 寄付月结 | AA88: 顺丰标快 | AE88: 否 | AF88: 2025-12-05 15:33:14 | AG88: 134****9085 | AL88: 7551083218 | AM88: 是
A89: SF3274418514967 | B89: 取宝-物流服务 | C89: WP25120582780075 | D89: 未导出 | E89: BAT251205095106 | F89: 已完成 | H89: 13228160389 | I89: 派送成功 | J89: 未打印 | K89: 2025-12-06 12:00 | L89: 代*峰 | M89: 186****8030‎‎‎‬‬‬ | N89: *******8030‎‎‎‬‬‬ | P89: 四川省成都市 郫都区*******‎‎‎‬‬‬ | Q89: 江* | R89: *******5357‎‎‎‬‬‬ | U89: 四川省成都市 武侯区*****************‎‎‎‬‬‬ | V89: 充电宝 | W89: 2 | X89: 1 | Z89: 寄付月结 | AA89: 顺丰标快 | AE89: 否 | AF89: 2025-12-05 11:53:32 | AG89: 134****6101 | AH89: 缪伟 | AI89: 2025-12-05 15:44:34 | AJ89: 132****0389‎‎‎‬‬‬ | AK89: 2025-12-06 09:24:12 | AL89: 7551083218 | AM89: 是
A90: SF3262863515431 | B90: 取宝-物流服务 | C90: WP25120582778975 | D90: 未导出 | E90: BAT251205094974 | F90: 已完成 | H90: 13228160389 | I90: 派送成功 | J90: 未打印 | K90: 2025-12-06 12:00 | L90: 代*峰 | M90: 186****8030‎‎‎‬‬‬ | N90: *******8030‎‎‎‬‬‬ | P90: 四川省成都市 郫都区*******‎‎‎‬‬‬ | Q90: 江* | R90: *******5357‎‎‎‬‬‬ | U90: 四川省成都市 武侯区*****************‎‎‎‬‬‬ | V90: 充电宝 | W90: 2 | X90: 1 | Z90: 寄付月结 | AA90: 顺丰标快 | AE90: 否 | AF90: 2025-12-05 11:53:33 | AG90: 134****6101 | AH90: 缪伟 | AI90: 2025-12-05 15:43:36 | AJ90: 132****0389‎‎‎‬‬‬ | AK90: 2025-12-06 09:24:12 | AL90: 7551083218 | AM90: 是
A91: SF3274418514921 | B91: 取宝-物流服务 | C91: WP25120582777873 | D91: 未导出 | E91: BAT251205094838 | F91: 已完成 | H91: 13228160389 | I91: 派送成功 | J91: 未打印 | K91: 2025-12-06 12:00 | L91: 代*峰 | M91: 186****8030‎‎‎‬‬‬ | N91: *******8030‎‎‎‬‬‬ | P91: 四川省成都市 郫都区*******‎‎‎‬‬‬ | Q91: 江* | R91: *******5357‎‎‎‬‬‬ | U91: 四川省成都市 武侯区*****************‎‎‎‬‬‬ | V91: 充电宝 | W91: 2 | X91: 1 | Z91: 寄付月结 | AA91: 顺丰标快 | AE91: 否 | AF91: 2025-12-05 11:53:32 | AG91: 134****6101 | AH91: 缪伟 | AI91: 2025-12-05 15:42:53 | AJ91: 132****0389‎‎‎‬‬‬ | AK91: 2025-12-06 09:24:12 | AL91: 7551083218 | AM91: 是
A92: SF3274239917142 | B92: 取宝-物流服务 | C92: WP25120478696008 | D92: 未导出 | E92: BAT251204213523 | F92: 已完成 | H92: 17690840985 | I92: 派送成功 | J92: 未打印 | K92: 2025-12-06 22:00 | L92: 阿* | M92: 166****7945‎‎‎‬‬‬ | N92: *******7945‎‎‎‬‬‬ | P92: 四川省成 都市武侯区**********************‎‎‎‬‬‬ | Q92: 阿* | R92: *******7945‎‎‎‬‬‬ | S92: 立充机柜或充电宝：24090064424 | U92: 新疆乌鲁木齐水磨沟 区***************‎‎‎‬‬‬ | V92: 充电宝 | W92: 1 | X92: 1 | Z92: 寄付月结 | AA92: 顺丰标快 | AE92: 否 | AF92: 2025-12-04 16:13:48 | AG92: 134****6101 | AH92: 张礼彬 | AI92: 2025-12-05 17:00:24 | AJ92: 176****0985‎‎‎‬‬‬ | AK92: 2025-12-08 16:02:56 | AL92: 7551083218 | AM92: 是
A93: SF3274239917151 | B93: 取宝-物流服务 | C93: WP25120478693749 | D93: 未导出 | E93: BAT251204213267 | F93: 已完成 | H93: 17690840985 | I93: 派送成功 | J93: 未打印 | K93: 2025-12-06 22:00 | L93: 阿* | M93: 166****7945‎‎‎‬‬‬ | N93: *******7945‎‎‎‬‬‬ | P93: 四川省成 都市武侯区**********************‎‎‎‬‬‬ | Q93: 阿* | R93: *******7945‎‎‎‬‬‬ | S93: 立充机柜或充电宝：24090064424 | U93: 新疆乌鲁木齐水磨沟 区***************‎‎‎‬‬‬ | V93: 充电宝 | W93: 2 | X93: 1 | Z93: 寄付月结 | AA93: 顺丰标快 | AE93: 否 | AF93: 2025-12-04 16:13:48 | AG93: 134****6101 | AH93: 张礼彬 | AI93: 2025-12-05 17:03:52 | AJ93: 176****0985‎‎‎‬‬‬ | AK93: 2025-12-08 16:02:56 | AL93: 7551083218 | AM93: 是
A94: SF3274239917973 | B94: 取宝-物流服务 | C94: WP25120478691649 | D94: 未导出 | E94: BAT251204213032 | F94: 已完成 | H94: 17690840985 | I94: 派送成功 | J94: 未打印 | K94: 2025-12-06 22:00 | L94: 阿* | M94: 166****7945‎‎‎‬‬‬ | N94: *******7945‎‎‎‬‬‬ | P94: 四川省成 都市武侯区**********************‎‎‎‬‬‬ | Q94: 阿* | R94: *******7945‎‎‎‬‬‬ | S94: 立充机柜或充电宝：24090064424 | U94: 新疆乌鲁木齐水磨沟 区***************‎‎‎‬‬‬ | V94: 充电宝 | W94: 2 | X94: 1 | Z94: 寄付月结 | AA94: 顺丰标快 | AE94: 否 | AF94: 2025-12-04 16:13:48 | AG94: 134****6101 | AH94: 张礼彬 | AI94: 2025-12-05 17:02:32 | AJ94: 176****0985‎‎‎‬‬‬ | AK94: 2025-12-08 09:20:39 | AL94: 7551083218 | AM94: 是
A95: SF3274773516670 | B95: 取宝-物流服务 | C95: WP25120477704914 | D95: 未导出 | E95: BAT251204097423 | F95: 待接单 | H95: 13763150821 | I95: 未收件 | J95: 未打印 | L95: 邹*华 | M95: 186****6788‎‎‎‬‬‬ | N95: *******6788‎‎‎‬‬‬ | P95: 广东省东莞市东城街道东纵路东城段208号 东城万达中心写**********‎‎‎‬‬‬ | Q95: 邹*华 | R95: *******6788‎‎‎‬‬‬ | S95: 进店取立充充电宝2个 | T95: 桥头电竞网咖 | U95: 广东省东莞 市桥头镇************‎‎‎‬‬‬ | V95: 充电宝 | W95: 2 | X95: 1 | Z95: 寄付月结 | AA95: 顺丰标快 | AE95: 否 | AF95: 2025-12-04 11:58:27 | AG95: 186****6788 | AL95: 7551083218 | AM95: 是
A96: SF3262639025736 | B96: 取宝-物流服务 | C96: WP25120477703019 | D96: 未导出 | E96: BAT251204097205 | F96: 处理中 | H96: 13763150821 | I96: 未收件 | J96: 未打印 | L96: 邹*华 | M96: 186****6788‎‎‎‬‬‬ | N96: *******6788‎‎‎‬‬‬ | P96: 广东省东莞市东城街道东纵路东城段208号 东城万达中心写**********‎‎‎‬‬‬ | Q96: 邹*华 | R96: *******6788‎‎‎‬‬‬ | S96: 进店取立充充电宝的宝2个 | T96: 桥头电竞网咖 | U96: 广东省东莞 市桥头镇************‎‎‎‬‬‬ | V96: 充电宝 | W96: 2 | X96: 1 | Z96: 寄付月结 | AA96: 顺丰标快 | AE96: 否 | AF96: 2025-12-04 11:58:27 | AG96: 186****6788 | AH96: 黄耀冬 | AJ96: 137****0821‎‎‎‬‬‬ | AL96: 7551083218 | AM96: 是
A97: SF3262146754991 | B97: 取宝-物流服务 | C97: WP25120477474924 | D97: 未导出 | E97: BAT251204071359 | F97: 已完成 | H97: 17699076995 | I97: 派送成功 | J97: 未打印 | K97: 2025-12-06 15:00 | L97: 阿* | M97: 166****7945‎‎‎‬‬‬ | N97: *******7945‎‎‎‬‬‬ | P97: 四川省成 都市武侯区**********************‎‎‎‬‬‬ | Q97: 阿* | R97: *******7945‎‎‎‬‬‬ | S97: 立充机柜或充电宝 | U97: 新疆乌鲁木齐新市区**************‎‎‎‬‬‬ | V97: 充电宝 | W97: 2 | X97: 1 | Z97: 寄付月结 | AA97: 顺丰标快 | AE97: 否 | AF97: 2025-12-04 11:06:00 | AG97: 134****6101 | AH97: 刘勇 | AI97: 2025-12-05 13:44:54 | AJ97: 176****6995‎‎‎‬‬‬ | AK97: 2025-12-08 16:02:56 | AL97: 7551083218 | AM97: 是
A98: SF3262146754955 | B98: 取宝-物流服务 | C98: WP25120477473721 | D98: 未导出 | E98: BAT251204071216 | F98: 已完成 | H98: 17699076995 | I98: 派送成功 | J98: 未打印 | K98: 2025-12-06 15:00 | L98: 阿* | M98: 166****7945‎‎‎‬‬‬ | N98: *******7945‎‎‎‬‬‬ | P98: 四川省成 都市武侯区**********************‎‎‎‬‬‬ | Q98: 阿* | R98: *******7945‎‎‎‬‬‬ | S98: 立充机柜或充电宝 | U98: 新疆乌鲁木齐新市区**************‎‎‎‬‬‬ | V98: 充电宝 | W98: 2 | X98: 1 | Z98: 寄付月结 | AA98: 顺丰标快 | AE98: 否 | AF98: 2025-12-04 11:06:00 | AG98: 134****6101 | AH98: 刘勇 | AI98: 2025-12-05 13:58:15 | AJ98: 176****6995‎‎‎‬‬‬ | AK98: 2025-12-08 18:02:28 | AL98: 7551083218 | AM98: 是
A99: SF3274708420302 | B99: 取宝-物流服务 | C99: WP25120477472462 | D99: 未导出 | E99: BAT251204071067 | F99: 已完成 | H99: 17699076995 | I99: 派送成功 | J99: 未打印 | K99: 2025-12-06 15:00 | L99: 阿* | M99: 166****7945‎‎‎‬‬‬ | N99: *******7945‎‎‎‬‬‬ | P99: 四川省成 都市武侯区**********************‎‎‎‬‬‬ | Q99: 阿* | R99: *******7945‎‎‎‬‬‬ | S99: 立充机柜或充电宝 | U99: 新疆乌鲁木齐新市区**************‎‎‎‬‬‬ | V99: 充电宝 | W99: 2 | X99: 1 | Z99: 寄付月结 | AA99: 顺丰标快 | AE99: 否 | AF99: 2025-12-04 11:06:00 | AG99: 134****6101 | AH99: 刘勇 | AI99: 2025-12-05 13:52:00 | AJ99: 176****6995‎‎‎‬‬‬ | AK99: 2025-12-08 18:02:28 | AL99: 7551083218 | AM99: 是
A100: SF3262146773901 | B100: 取宝-物流服务 | C100: WP25120477471707 | D100: 未导出 | E100: BAT251204070983 | F100: 已完成 | H100: 17699076995 | I100: 派送成功 | J100: 未打印 | K100: 2025-12-06 15:00 | L100: 阿* | M100: 166****7945‎‎‎‬‬‬ | N100: *******7945‎‎‎‬‬‬ | P100: 四川省成 都市武侯区**********************‎‎‎‬‬‬ | Q100: 阿* | R100: *******7945‎‎‎‬‬‬ | S100: 立充机柜或充电宝 | U100: 新疆乌鲁木齐新市区**************‎‎‎‬‬‬ | V100: 充电宝 | W100: 2 | X100: 1 | Z100: 寄付月结 | AA100: 顺丰标快 | AE100: 否 | AF100: 2025-12-04 11:06:00 | AG100: 134****6101 | AH100: 刘勇 | AI100: 2025-12-05 13:54:22 | AJ100: 176****6995‎‎‎‬‬‬ | AK100: 2025-12-08 18:02:28 | AL100: 7551083218 | AM100: 是
...

Sheet Sheet2
A1: 运单号 | B1: 任务类型 | C1: 收件手机 | G1: 运单号 | H1: 下单账号
A2: SF3268579296831 | B2: 补宝-物流服务 | C2: 155****0885‎‎‎‬‬‬ | G2: SF3268579296831 | H2: 155****0885
A3: SF3268579291750 | B3: 补宝-物流服务 | C3: 155****0885‎‎‎‬‬‬ | G3: SF3268579291750 | H3: 155****0885
A4: SF5127709690867 | B4: 补宝-物流服务 | C4: 155****0885‎‎‎‬‬‬ | G4: SF5127709690867 | H4: 155****0885
A5: SF5106905852824 | B5: 补宝-物流服务 | C5: 155****0885‎‎‎‬‬‬ | G5: SF5106905852824 | H5: 155****0885
A6: SF5105056503415 | B6: 补宝-物流服务 | C6: 181****7580‎‎‎‬‬‬ | G6: SF5105056503415 | H6: 134****6101
A7: SF5105056506251 | B7: 补宝-物流服务 | C7: 181****7580‎‎‎‬‬‬ | G7: SF5105056506251 | H7: 134****6101
A8: SF3266863453181 | B8: 补宝-物流服务 | C8: 181****7580‎‎‎‬‬‬ | G8: SF3266863453181 | H8: 134****6101
A9: SF3261464758524 | B9: 补宝-物流服务 | C9: 186****6788‎‎‎‬‬‬ | G9: SF3261464758524 | H9: 186****6788
A10: SF3261464758781 | B10: 补宝-物流服务 | C10: 186****6788‎‎‎‬‬‬ | G10: SF3261464758781 | H10: 186****6788
A11: SF3261417303446 | B11: 补宝-物流服务 | C11: 152****5518‎‎‎‬‬‬ | G11: SF3261417303446 | H11: 134****6101
A12: SF3261417303058 | B12: 补宝-物流服务 | C12: 152****5518‎‎‎‬‬‬ | G12: SF3261417303058 | H12: 134****6101
... A15: SF3260491849237 | B15: 补宝-物流服务 | C15: 158****0900‎‎‎‬‬‬ | G15: SF3260491849237 | H15: 134****6101
A16: SF3260420814593 | B16: 补宝-物流服务 | G16: SF3260420814593 | H16: 136****7868
A17: SF3260499115096 | B17: 补宝-物流服务 | C17: 186****8030‎‎‎‬‬‬ | G17: SF3260499115096 | H17: 134****6101
A18: SF3260499115906 | B18: 补宝-物流服务 | C18: 186****8030‎‎‎‬‬‬ | G18: SF3260499115906 | H18: 134****6101
A19: SF3278405753506 | B19: 补宝-物流服务 | C19: 186****6788‎‎‎‬‬‬ | G19: SF3278405753506 | H19: 186****6788
A20: SF3278434363447 | B20: 补宝-物流服务 | C20: 186****6788‎‎‎‬‬‬ | G20: SF3278434363447 | H20: 186****6788
A21: SF3278434363483 | B21: 补宝-物流服务 | C21: 186****6788‎‎‎‬‬‬ | G21: SF3278434363483 | H21: 186****6788
A22: SF3269834853653 | B22: 补宝-物流服务 | C22: 186****6788‎‎‎‬‬‬ | G22: SF3269834853653 | H22: 186****6788
A23: SF3269042397254 | B23: 补宝-物流服务 | C23: 181****6669‎‎‎‬‬‬ | G23: SF3269042397254 | H23: 130****4667
A24: SF3269933113650 | B24: 补宝-物流服务 | C24: 186****6788‎‎‎‬‬‬ | G24: SF3269933113650 | H24: 186****6788
A25: SF3278126546304 | B25: 补宝-物流服务 | C25: 186****6788‎‎‎‬‬‬ | G25: SF3278126546304 | H25: 186****6788
A26: SF3269248082701 | B26: 补宝-物流服务 | C26: 186****6788‎‎‎‬‬‬ | G26: SF3269248082701 | H26: 186****6788
A27: SF3269246608556 | B27: 补宝-物流服务 | C27: 186****6788‎‎‎‬‬‬ | G27: SF3269246608556 | H27: 186****6788
A28: SF3278179778744 | B28: 补宝-物流服务 | C28: 186****6788‎‎‎‬‬‬ | G28: SF3278179778744 | H28: 186****6788
... A173: SF5106905958549 | B173: 立充充电宝取机柜-仅物流 | C173: 155****0885‎‎‎‬‬‬ | G173: SF3266273769420 | H173: 131****2614
A174: SF3268277986250 | C174: 177****5688‎‎‎‬‬‬ | G174: SF3266238709946 | H174: 186****6788
A175: SF5106557446982 | C175: 177****5688‎‎‎‬‬‬ | G175: SF3261485880842 | H175: 186****6788
A176: SF5106557446946 | C176: 177****5688‎‎‎‬‬‬ | G176: SF3261485888202 | H176: 186****6788
A177: SF5105265169872 | C177: 155****0885‎‎‎‬‬‬ | G177: SF3261762960340 | H177: 131****2614
A178: SF3268714724220 | B178: 立充充电宝取机柜-物流服务 | C178: 186****6788‎‎‎‬‬‬ | G178: SF3261793913657 | H178: 186****6788
A179: SF5127722204781,SF2074509697134 | B179: 立充充电宝取机柜-物流服务 | C179: 186****6788‎‎‎‬‬‬ | G179: SF3268270973716 | H179: 131****2614
A180: SF5106979506489 | B180: 立充充电宝取机柜-物流服务 | C180: 186****6788‎‎‎‬‬‬ | G180: SF3261642298877 | H180: 186****6788
A181: SF5106970083922 | B181: 立充充电宝取机柜-物流服务 | C181: 186****6788‎‎‎‬‬‬ | G181: SF3260956999481 | H181: 136****7868
A182: SF3268545240764 | B182: 立充充电宝取机柜-物流服务 | C182: 155****0885‎‎‎‬‬‬ | G182: SF3269495090258 | H182: 134****9085
A183: SF5106997533365 | B183: 立充充电宝取机柜-物流服务 | C183: 155****0885‎‎‎‬‬‬ | G183: SF3269768176117 | H183: 131****2614
A184: SF5127766316133 | B184: 立充充电宝取机柜-物流服务 | C184: 155****0885‎‎‎‬‬‬ | G184: SF3269768176320 | H184: 131****2614
A185: SF3268571425528 | B185: 立充充电宝取机柜-物流服务 | C185: 186****6788‎‎‎‬‬‬ | G185: SF3269707179242 | H185: 131****2614
A186: SF5106901786306 | B186: 立充充电宝取机柜-物流服务 | C186: 186****6788‎‎‎‬‬‬ | G186: SF3278720614683 | H186: 186****6788
A187: SF5106096474396 | B187: 立充充电宝取机柜-物流服务 | C187: 166****7945‎‎‎‬‬‬ | G187: SF3278938439192 | H187: 186****6788
A188: SF3268857237271 | B188: 立充充电宝取机柜-物流服务 | C188: 166****7945‎‎‎‬‬‬ | G188: SF3278024325817 | H188: 136****7868
A189: SF5106096472069 | B189: 立充充电宝取机柜-物流服务 | C189: 166****7945‎‎‎‬‬‬ | G189: SF3262727683329 | H189: 186****6788
... A243: SF3262146923187 | B243: 立充充电宝取机柜-物流服务 | C243: 166****7945‎‎‎‬‬‬ | G243: SF3262004095497 | H243: 130****4667
A244: SF3262146923178 | B244: 立充充电宝取机柜-物流服务 | C244: 166****7945‎‎‎‬‬‬
A245: SF3274976461103 | B245: 立充充电宝取机柜-物流服务 | C245: 186****6788‎‎‎‬‬‬
A246: SF3262003984120 | B246: 立充充电宝取机柜-物流服务 | C246: 186****6788‎‎‎‬‬‬
A247: SF3262025177660 | B247: 立充充电宝取机柜-物流服务 | C247: 186****6788‎‎‎‬‬‬
A248: SF3262025177518 | B248: 立充充电宝取机柜-物流服务 | C248: 186****6788‎‎‎‬‬‬
A249: SF3262025177572 | B249: 立充充电宝取机柜-物流服务 | C249: 186****6788‎‎‎‬‬‬
A250: SF3295365022962 | B250: 立充充电宝取机柜-物流服务 | C250: 186****6788‎‎‎‬‬‬
A251: SF3262372954357 | B251: 立充充电宝取机柜-物流服务 | C251: 184****1003‎‎‎‬‬‬
A252: SF5106905958549 | B252: 立充充电宝取机柜-仅服务 | C252: 155****0885‎‎‎‬‬‬
A253: SF3268277986250 | B253: 立充充电宝取机柜-仅服务 | C253: 177****5688‎‎‎‬‬‬
A254: SF5106557446982 | B254: 立充充电宝取机柜-仅服务 | C254: 177****5688‎‎‎‬‬‬
A255: SF5106557446946 | B255: 立充充电宝取机柜-仅服务 | C255: 177****5688‎‎‎‬‬‬
... A288: SF3262004095497 | B288: 立充充电宝取机柜-仅服务 | C288: 177****5688‎‎‎‬‬‬

Sheet Sheet3
J1: 手机号 | K1: 账号所属公司 | L1: 公司性质
J2: 165****7666 | K2: 深圳市锐丰伟业科技有限公司 | L2: 服务商
J3: 186****8003 | K3: 河北亘石信息科技有限公司 | L3: 服务商
J4: 155****0885 | K4: 大连浩源满航空服务有限公司 | L4: 服务商
J5: 134****6101 | K5: 成都江源易通信息技术有限公司 | L5: 服务商
J6: 156****1234 | K6: 内蒙古悦盈科技有限公司 | L6: 服务商
J7: 137****1781 | K7: 东莞市聚伴科技有限公司 | L7: 服务商
J8: 181****5776 | K8: 福建无现新生信息科技有限公司 | L8: 服务商
J9: 136****7868 | K9: 山东省点线面网络科技有限公司 | L9: 服务商
J10: 131****2614 | K10: 辽宁深蓝数据服务有限公司 | L10: 服务商
J11: 158****6590 | K11: 江西森楠科技有限公司 | L11: 服务商
J12: 187****4440 | K12: 长治市聚英科技有限公司 | L12: 服务商
... J17: 134****9085 | K17: 深圳市嘉嘉电科技有限公司 | L17: 服务商

Sheet Sheet5
A1: 快递运单费用
A2: 序号 | B2: 日期 | C2: 运单号码 | D2: 寄件地区 | E2: 到件地区 | F2: 对方公司名称 | G2: 计费重量 | H2: 产品类型 | I2: 付款方式 | J2: 费用(元) | K2: 折扣/促销 | L2: 应付金额 | M2: 经手人 | N2: 服务 | O2: 任务类型 | P2: 下单账号 | Q2: 账号所属公司 | R2: 公司性质 | S2: 备注
A3: 1 | B3: 12-01 | C3: SF3262372117661 | D3: 雅安 | E3: 成都/资阳/眉山 | F3: 文刚 | G3: 1.000 | H3: 顺丰标快 | I3: 寄转第三方 | J3: 13.00 | K3: 0.00 | L3: 13.00 | M3: 文刚 | N3: 运费 | O3: 取宝-物流服务 | P3: 184****1003‎‎‎‬‬‬
A4: 2 | B4: 12-01 | C4: SF3262372117661 | D4: 雅安 | E4: 成都/资阳/眉山 | F4: 文刚 | G4: 0.000 | H4: 顺丰标快 | I4: 寄转第三方 | J4: 2.00 | K4: 0.00 | L4: 2.00 | M4: 文刚 | N4: 包装服务 | O4: 取宝-物流服务 | P4: 184****1003‎‎‎‬‬‬
A5: 3 | B5: 12-01 | C5: SF3262372954357 | D5: 雅安 | E5: 成都/资阳/眉山 | F5: 文刚 | G5: 4.500 | H5: 顺丰标快 | I5: 寄转第三方 | J5: 20.00 | K5: 0.00 | L5: 20.00 | M5: 文刚 | N5: 运费 | O5: 立充充电宝取机柜-物流服务 | P5: 184****1003‎‎‎‬‬‬
A6: 4 | B6: 12-01 | C6: SF3262372954357 | D6: 雅安 | E6: 成都/资阳/眉山 | F6: 文刚 | G6: 0.000 | H6: 顺丰标快 | I6: 寄转第三方 | J6: 7.00 | K6: 0.00 | L6: 7.00 | M6: 文刚 | N6: 包装服务 | O6: 立充充电宝取机柜-物流服务 | P6: 184****1003‎‎‎‬‬‬
A7: 5 | B7: 12-01 | C7: SF3262377404072 | D7: 东莞 | E7: 东莞 | F7: 邹小华 | G7: 1.000 | H7: 顺丰标快 | I7: 寄转第三方 | J7: 11.00 | K7: 0.00 | L7: 11.00 | M7: 邹小华 | N7: 运费 | O7: 取宝-物流服务 | P7: 186****6788‎‎‎‬‬‬ | Q7: 东莞市中汇信息技术有限公司
A8: 6 | B8: 12-01 | C8: SF3262377404072 | D8: 东莞 | E8: 东莞 | F8: 邹小华 | G8: 0.000 | H8: 顺丰标快 | I8: 寄转第三方 | J8: 2.00 | K8: 0.00 | L8: 2.00 | M8: 邹小华 | N8: 包装服务 | O8: 取宝-物流服务 | P8: 186****6788‎‎‎‬‬‬ | Q8: 东莞市中汇信息技术有限公司
A9: 7 | B9: 12-01 | C9: SF3262378607753 | D9: 东莞 | E9: 东莞 | F9: 邹小华 | G9: 1.000 | H9: 顺丰标快 | I9: 寄转第三方 | J9: 11.00 | K9: 0.00 | L9: 11.00 | M9: 邹小华 | N9: 运费 | O9: 取宝-物流服务 | P9: 186****6788‎‎‎‬‬‬ | Q9: 东莞市中汇信息技术有限公司
A10: 8 | B10: 12-01 | C10: SF3295326848005 | D10: 东莞 | E10: 东莞 | F10: 邹小华 | G10: 1.000 | H10: 顺丰标快 | I10: 寄转第三方 | J10: 11.00 | K10: 0.00 | L10: 11.00 | M10: 邹小华 | N10: 运费 | O10: 取宝-物流服务 | P10: 186****6788‎‎‎‬‬‬ | Q10: 东莞市中汇信息技术有限公司
A11: 9 | B11: 12-01 | C11: SF3295326848005 | D11: 东莞 | E11: 东莞 | F11: 邹小华 | G11: 0.000 | H11: 顺丰标快 | I11: 寄转第三方 | J11: 1.00 | K11: 0.00 | L11: 1.00 | M11: 邹小华 | N11: 包装服务 | O11: 取宝-物流服务 | P11: 186****6788‎‎‎‬‬‬ | Q11: 东莞市中汇信息技术有限公司
A12: 10 | B12: 12-01 | C12: SF3295364078732 | D12: 雅安 | E12: 成都/资阳/眉山 | F12: 文刚 | G12: 1.000 | H12: 顺丰标快 | I12: 寄转第三方 | J12: 13.00 | K12: 0.00 | L12: 13.00 | M12: 文刚 | N12: 运费 | O12: 取宝-物流服务 | P12: 184****1003‎‎‎‬‬‬
A13: 11 | B13: 12-01 | C13: SF3295364078732 | D13: 雅安 | E13: 成都/资阳/眉山 | F13: 文刚 | G13: 0.000 | H13: 顺丰标快 | I13: 寄转第三方 | J13: 2.00 | K13: 0.00 | L13: 2.00 | M13: 文刚 | N13: 包装服务 | O13: 取宝-物流服务 | P13: 184****1003‎‎‎‬‬‬
A14: 12 | B14: 12-01 | C14: SF3295364078769 | D14: 雅安 | E14: 成都/资阳/眉山 | F14: 文刚 | G14: 1.000 | H14: 顺丰标快 | I14: 寄转第三方 | J14: 13.00 | K14: 0.00 | L14: 13.00 | M14: 文刚 | N14: 运费 | O14: 取宝-物流服务 | P14: 184****1003‎‎‎‬‬‬
A15: 13 | B15: 12-01 | C15: SF3295364078769 | D15: 雅安 | E15: 成都/资阳/眉山 | F15: 文刚 | G15: 0.000 | H15: 顺丰标快 | I15: 寄转第三方 | J15: 2.00 | K15: 0.00 | L15: 2.00 | M15: 文刚 | N15: 包装服务 | O15: 取宝-物流服务 | P15: 184****1003‎‎‎‬‬‬
A16: 14 | B16: 12-01 | C16: SF3295365022962 | D16: 东莞 | E16: 东莞 | F16: 邹小华 | G16: 2.500 | H16: 顺丰标快 | I16: 寄转第三方 | J16: 13.00 | K16: 0.00 | L16: 13.00 | M16: 邹小华 | N16: 运费 | O16: 立充充电宝取机柜-物流服务 | P16: 186****6788‎‎‎‬‬‬ | Q16: 东莞市中汇信息技术有限公司
A17: 15 | B17: 12-01 | C17: SF3295365941133 | D17: 东莞 | E17: 东莞 | F17: 邹小华 | G17: 1.000 | H17: 顺丰标快 | I17: 寄转第三方 | J17: 11.00 | K17: 0.00 | L17: 11.00 | M17: 邹小华 | N17: 运费 | O17: 取宝-物流服务 | P17: 186****6788‎‎‎‬‬‬ | Q17: 东莞市中汇信息技术有限公司
A18: 16 | B18: 12-02 | C18: SF3262372117661 | D18: 雅安 | E18: 成都/资阳/眉山 | F18: 文刚 | G18: 0.000 | H18: 顺丰标快 | I18: 寄付 | J18: 6.00 | K18: 0.00 | L18: 6.00 | M18: 文刚 | N18: 收件微派 | O18: 取宝-物流服务 | P18: 184****1003‎‎‎‬‬‬
A19: 17 | B19: 12-02 | C19: SF3262377404072 | D19: 东莞 | E19: 东莞 | F19: 邹小华 | G19: 0.000 | H19: 顺丰标快 | I19: 寄付 | J19: 6.00 | K19: 0.00 | L19: 6.00 | M19: 邹小华 | N19: 收件微派 | O19: 取宝-物流服务 | P19: 186****6788‎‎‎‬‬‬ | Q19: 东莞市中汇信息技术有限公司
A20: 18 | B20: 12-02 | C20: SF3262378607753 | D20: 东莞 | E20: 东莞 | F20: 邹小华 | G20: 0.000 | H20: 顺丰标快 | I20: 寄付 | J20: 6.00 | K20: 0.00 | L20: 6.00 | M20: 邹小华 | N20: 收件微派 | O20: 取宝-物流服务 | P20: 186****6788‎‎‎‬‬‬ | Q20: 东莞市中汇信息技术有限公司
A21: 19 | B21: 12-02 | C21: SF3262992584639 | D21: 深圳 | E21: 东莞 | F21: 广东久益智付科技有限公司 | G21: 1.000 | H21: 顺丰标快 | I21: 寄转第三方 | J21: 13.00 | K21: 0.00 | L21: 13.00 | M21: 吴广继 | N21: 运费 | O21: 取宝-仅物流 | P21: 130****4667‎‎‎‬‬‬ | Q21: 广东久益智付科技有限公司
A22: 20 | B22: 12-02 | C22: SF3295326848005 | D22: 东莞 | E22: 东莞 | F22: 邹小华 | G22: 0.000 | H22: 顺丰标快 | I22: 寄付 | J22: 6.00 | K22: 0.00 | L22: 6.00 | M22: 邹小华 | N22: 收件微派 | O22: 取宝-物流服务 | P22: 186****6788‎‎‎‬‬‬ | Q22: 东莞市中汇信息技术有限公司
A23: 21 | B23: 12-02 | C23: SF3295364078732 | D23: 雅安 | E23: 成都/资阳/眉山 | F23: 文刚 | G23: 0.000 | H23: 顺丰标快 | I23: 寄付 | J23: 6.00 | K23: 0.00 | L23: 6.00 | M23: 文刚 | N23: 收件微派 | O23: 取宝-物流服务 | P23: 184****1003‎‎‎‬‬‬
A24: 22 | B24: 12-02 | C24: SF3295364078769 | D24: 雅安 | E24: 成都/资阳/眉山 | F24: 文刚 | G24: 0.000 | H24: 顺丰标快 | I24: 寄付 | J24: 6.00 | K24: 0.00 | L24: 6.00 | M24: 文刚 | N24: 收件微派 | O24: 取宝-物流服务 | P24: 184****1003‎‎‎‬‬‬
A25: 23 | B25: 12-02 | C25: SF3295365022962 | D25: 东莞 | E25: 东莞 | F25: 邹小华 | G25: 0.000 | H25: 顺丰标快 | I25: 寄付 | J25: 3.00 | K25: 0.00 | L25: 3.00 | M25: 邹小华 | N25: 收件微派 | O25: 立充充电宝取机柜-物流服务 | P25: 186****6788‎‎‎‬‬‬ | Q25: 东莞市中汇信息技术有限公司
A26: 24 | B26: 12-02 | C26: SF3295365941133 | D26: 东莞 | E26: 东莞 | F26: 邹小华 | G26: 0.000 | H26: 顺丰标快 | I26: 寄付 | J26: 6.00 | K26: 0.00 | L26: 6.00 | M26: 邹小华 | N26: 收件微派 | O26: 取宝-物流服务 | P26: 186****6788‎‎‎‬‬‬ | Q26: 东莞市中汇信息技术有限公司
A27: 25 | B27: 12-03 | C27: SF3262004095424 | D27: 深圳 | E27: 东莞 | F27: 吴珊珊 | G27: 1.000 | H27: 顺丰标快 | I27: 寄转第三方 | J27: 13.00 | K27: 0.00 | L27: 13.00 | M27: 饶云普 | N27: 运费 | O27: 立充充电宝取机柜-仅服务 | P27: 177****5688‎‎‎‬‬‬
A28: 26 | B28: 12-03 | C28: SF3262004095424 | D28: 深圳 | E28: 东莞 | F28: 吴珊珊 | G28: 0.000 | H28: 顺丰标快 | I28: 寄转第三方 | J28: 1.00 | K28: 0.00 | L28: 1.00 | M28: 饶云普 | N28: 包装服务 | O28: 立充充电宝取机柜-仅服务 | P28: 177****5688‎‎‎‬‬‬
A29: 27 | B29: 12-03 | C29: SF3262004095497 | D29: 深圳 | E29: 东莞 | F29: 吴珊珊 | G29: 2.300 | H29: 顺丰标快 | I29: 寄转第三方 | J29: 16.00 | K29: 0.00 | L29: 16.00 | M29: 饶云普 | N29: 运费 | O29: 立充充电宝取机柜-仅服务 | P29: 177****5688‎‎‎‬‬‬
A30: 28 | B30: 12-03 | C30: SF3262004095497 | D30: 深圳 | E30: 东莞 | F30: 吴珊珊 | G30: 0.000 | H30: 顺丰标快 | I30: 寄转第三方 | J30: 4.00 | K30: 0.00 | L30: 4.00 | M30: 饶云普 | N30: 包装服务 | O30: 立充充电宝取机柜-仅服务 | P30: 177****5688‎‎‎‬‬‬
A31: 29 | B31: 12-03 | C31: SF3262004095742 | D31: 深圳 | E31: 东莞 | F31: 吴珊珊 | G31: 1.000 | H31: 顺丰标快 | I31: 寄转第三方 | J31: 13.00 | K31: 0.00 | L31: 13.00 | M31: 饶云普 | N31: 运费 | O31: 立充充电宝取机柜-仅服务 | P31: 177****5688‎‎‎‬‬‬
A32: 30 | B32: 12-03 | C32: SF3262004095742 | D32: 深圳 | E32: 东莞 | F32: 吴珊珊 | G32: 0.000 | H32: 顺丰标快 | I32: 寄转第三方 | J32: 1.00 | K32: 0.00 | L32: 1.00 | M32: 饶云普 | N32: 包装服务 | O32: 立充充电宝取机柜-仅服务 | P32: 177****5688‎‎‎‬‬‬
A33: 31 | B33: 12-03 | C33: SF3262004097071 | D33: 深圳 | E33: 东莞 | F33: 吴珊珊 | G33: 1.000 | H33: 顺丰标快 | I33: 寄转第三方 | J33: 13.00 | K33: 0.00 | L33: 13.00 | M33: 饶云普 | N33: 运费 | O33: 立充充电宝取机柜-仅服务 | P33: 177****5688‎‎‎‬‬‬
A34: 32 | B34: 12-03 | C34: SF3262004097071 | D34: 深圳 | E34: 东莞 | F34: 吴珊珊 | G34: 0.000 | H34: 顺丰标快 | I34: 寄转第三方 | J34: 1.00 | K34: 0.00 | L34: 1.00 | M34: 饶云普 | N34: 包装服务 | O34: 立充充电宝取机柜-仅服务 | P34: 177****5688‎‎‎‬‬‬
A35: 33 | B35: 12-03 | C35: SF3262016306209 | D35: 东莞 | E35: 东莞 | F35: 邹小华 | G35: 1.000 | H35: 顺丰标快 | I35: 寄转第三方 | J35: 11.00 | K35: 0.00 | L35: 11.00 | M35: 邹小华 | N35: 运费 | O35: 取宝-物流服务 | P35: 186****6788‎‎‎‬‬‬ | Q35: 东莞市中汇信息技术有限公司
A36: 34 | B36: 12-03 | C36: SF3262016306209 | D36: 东莞 | E36: 东莞 | F36: 邹小华 | G36: 0.000 | H36: 顺丰标快 | I36: 寄转第三方 | J36: 1.00 | K36: 0.00 | L36: 1.00 | M36: 邹小华 | N36: 包装服务 | O36: 取宝-物流服务 | P36: 186****6788‎‎‎‬‬‬ | Q36: 东莞市中汇信息技术有限公司
A37: 35 | B37: 12-03 | C37: SF3262016306218 | D37: 东莞 | E37: 东莞 | F37: 邹小华 | G37: 1.000 | H37: 顺丰标快 | I37: 寄转第三方 | J37: 11.00 | K37: 0.00 | L37: 11.00 | M37: 邹小华 | N37: 运费 | O37: 取宝-物流服务 | P37: 186****6788‎‎‎‬‬‬ | Q37: 东莞市中汇信息技术有限公司
A38: 36 | B38: 12-03 | C38: SF3262016306218 | D38: 东莞 | E38: 东莞 | F38: 邹小华 | G38: 0.000 | H38: 顺丰标快 | I38: 寄转第三方 | J38: 1.00 | K38: 0.00 | L38: 1.00 | M38: 邹小华 | N38: 包装服务 | O38: 取宝-物流服务 | P38: 186****6788‎‎‎‬‬‬ | Q38: 东莞市中汇信息技术有限公司
A39: 37 | B39: 12-03 | C39: SF3262025177518 | D39: 东莞 | E39: 东莞 | F39: 邹小华 | G39: 2.400 | H39: 顺丰标快 | I39: 寄转第三方 | J39: 12.00 | K39: 0.00 | L39: 12.00 | M39: 邹小华 | N39: 运费 | O39: 立充充电宝取机柜-物流服务 | P39: 186****6788‎‎‎‬‬‬ | Q39: 东莞市中汇信息技术有限公司
A40: 38 | B40: 12-03 | C40: SF3262025177518 | D40: 东莞 | E40: 东莞 | F40: 邹小华 | G40: 0.000 | H40: 顺丰标快 | I40: 寄转第三方 | J40: 4.00 | K40: 0.00 | L40: 4.00 | M40: 邹小华 | N40: 包装服务 | O40: 立充充电宝取机柜-物流服务 | P40: 186****6788‎‎‎‬‬‬ | Q40: 东莞市中汇信息技术有限公司
A41: 39 | B41: 12-03 | C41: SF3262025177572 | D41: 东莞 | E41: 东莞 | F41: 邹小华 | G41: 5.400 | H41: 顺丰标快 | I41: 寄转第三方 | J41: 15.00 | K41: 0.00 | L41: 15.00 | M41: 邹小华 | N41: 运费 | O41: 立充充电宝取机柜-物流服务 | P41: 186****6788‎‎‎‬‬‬ | Q41: 东莞市中汇信息技术有限公司
A42: 40 | B42: 12-03 | C42: SF3262025177572 | D42: 东莞 | E42: 东莞 | F42: 邹小华 | G42: 0.000 | H42: 顺丰标快 | I42: 寄转第三方 | J42: 6.00 | K42: 0.00 | L42: 6.00 | M42: 邹小华 | N42: 包装服务 | O42: 立充充电宝取机柜-物流服务 | P42: 186****6788‎‎‎‬‬‬ | Q42: 东莞市中汇信息技术有限公司
A43: 41 | B43: 12-03 | C43: SF3262025177660 | D43: 东莞 | E43: 东莞 | F43: 邹小华 | G43: 14.000 | H43: 顺丰标快 | I43: 寄转第三方 | J43: 24.00 | K43: 0.00 | L43: 24.00 | M43: 邹小华 | N43: 运费 | O43: 立充充电宝取机柜-物流服务 | P43: 186****6788‎‎‎‬‬‬ | Q43: 东莞市中汇信息技术有限公司
A44: 42 | B44: 12-03 | C44: SF3262025177660 | D44: 东莞 | E44: 东莞 | F44: 邹小华 | G44: 0.000 | H44: 顺丰标快 | I44: 寄转第三方 | J44: 12.00 | K44: 0.00 | L44: 12.00 | M44: 邹小华 | N44: 包装服务 | O44: 立充充电宝取机柜-物流服务 | P44: 186****6788‎‎‎‬‬‬ | Q44: 东莞市中汇信息技术有限公司
A45: 43 | B45: 12-03 | C45: SF3262028718328 | D45: 东莞 | E45: 东莞 | F45: 邹小华 | G45: 1.000 | H45: 顺丰标快 | I45: 寄转第三方 | J45: 11.00 | K45: 0.00 | L45: 11.00 | M45: 邹小华 | N45: 运费 | O45: 取宝-物流服务 | P45: 186****6788‎‎‎‬‬‬ | Q45: 东莞市中汇信息技术有限公司
A46: 44 | B46: 12-03 | C46: SF3262028718391 | D46: 东莞 | E46: 东莞 | F46: 邹小华 | G46: 1.000 | H46: 顺丰标快 | I46: 寄转第三方 | J46: 11.00 | K46: 0.00 | L46: 11.00 | M46: 邹小华 | N46: 运费 | O46: 取宝-物流服务 | P46: 186****6788‎‎‎‬‬‬ | Q46: 东莞市中汇信息技术有限公司
A47: 45 | B47: 12-03 | C47: SF3262372954357 | D47: 雅安 | E47: 成都/资阳/眉山 | F47: 文刚 | G47: 0.000 | H47: 顺丰标快 | I47: 寄付 | J47: 3.00 | K47: 0.00 | L47: 3.00 | M47: 文刚 | N47: 收件微派 | O47: 立充充电宝取机柜-物流服务 | P47: 184****1003‎‎‎‬‬‬
A48: 46 | B48: 12-03 | C48: SF3274904297678 | D48: 东莞 | E48: 东莞 | F48: 邹小华 | G48: 1.000 | H48: 顺丰标快 | I48: 寄转第三方 | J48: 11.00 | K48: 0.00 | L48: 11.00 | M48: 邹小华 | N48: 运费 | O48: 取宝-物流服务 | P48: 186****6788‎‎‎‬‬‬ | Q48: 东莞市中汇信息技术有限公司
A49: 47 | B49: 12-03 | C49: SF3274976461103 | D49: 东莞 | E49: 东莞 | F49: 邹小华 | G49: 2.300 | H49: 顺丰标快 | I49: 寄转第三方 | J49: 12.00 | K49: 0.00 | L49: 12.00 | M49: 邹小华 | N49: 运费 | O49: 立充充电宝取机柜-物流服务 | P49: 186****6788‎‎‎‬‬‬ | Q49: 东莞市中汇信息技术有限公司
A50: 48 | B50: 12-03 | C50: SF3274976461103 | D50: 东莞 | E50: 东莞 | F50: 邹小华 | G50: 0.000 | H50: 顺丰标快 | I50: 寄转第三方 | J50: 3.00 | K50: 0.00 | L50: 3.00 | M50: 邹小华 | N50: 包装服务 | O50: 立充充电宝取机柜-物流服务 | P50: 186****6788‎‎‎‬‬‬ | Q50: 东莞市中汇信息技术有限公司
A51: 49 | B51: 12-03 | C51: SF3274990520130 | D51: 东莞 | E51: 惠州 | F51: 石湾美宜佳便利店(蓝湾半岛店粤20946) | G51: 1.000 | H51: 顺丰标快 | I51: 寄转第三方 | J51: 12.00 | K51: 0.00 | L51: 12.00 | M51: 邹小华 | N51: 运费 | O51: 补宝-物流服务 | P51: 186****6788‎‎‎‬‬‬ | Q51: 东莞市中汇信息技术有限公司
A52: 50 | B52: 12-04 | C52: SF3262016306209 | D52: 东莞 | E52: 东莞 | F52: 邹小华 | G52: 0.000 | H52: 顺丰标快 | I52: 寄付 | J52: 6.00 | K52: 0.00 | L52: 6.00 | M52: 邹小华 | N52: 收件微派 | O52: 取宝-物流服务 | P52: 186****6788‎‎‎‬‬‬ | Q52: 东莞市中汇信息技术有限公司
A53: 51 | B53: 12-04 | C53: SF3262016306218 | D53: 东莞 | E53: 东莞 | F53: 邹小华 | G53: 0.000 | H53: 顺丰标快 | I53: 寄付 | J53: 6.00 | K53: 0.00 | L53: 6.00 | M53: 邹小华 | N53: 收件微派 | O53: 取宝-物流服务 | P53: 186****6788‎‎‎‬‬‬ | Q53: 东莞市中汇信息技术有限公司
A54: 52 | B54: 12-04 | C54: SF3262025177518 | D54: 东莞 | E54: 东莞 | F54: 邹小华 | G54: 0.000 | H54: 顺丰标快 | I54: 寄付 | J54: 3.00 | K54: 0.00 | L54: 3.00 | M54: 邹小华 | N54: 收件微派 | O54: 立充充电宝取机柜-物流服务 | P54: 186****6788‎‎‎‬‬‬ | Q54: 东莞市中汇信息技术有限公司
A55: 53 | B55: 12-04 | C55: SF3262025177572 | D55: 东莞 | E55: 东莞 | F55: 邹小华 | G55: 0.000 | H55: 顺丰标快 | I55: 寄付 | J55: 3.00 | K55: 0.00 | L55: 3.00 | M55: 邹小华 | N55: 收件微派 | O55: 立充充电宝取机柜-物流服务 | P55: 186****6788‎‎‎‬‬‬ | Q55: 东莞市中汇信息技术有限公司
A56: 54 | B56: 12-04 | C56: SF3262025177660 | D56: 东莞 | E56: 东莞 | F56: 邹小华 | G56: 0.000 | H56: 顺丰标快 | I56: 寄付 | J56: 3.00 | K56: 0.00 | L56: 3.00 | M56: 邹小华 | N56: 收件微派 | O56: 立充充电宝取机柜-物流服务 | P56: 186****6788‎‎‎‬‬‬ | Q56: 东莞市中汇信息技术有限公司
A57: 55 | B57: 12-04 | C57: SF3262028718328 | D57: 东莞 | E57: 东莞 | F57: 邹小华 | G57: 0.000 | H57: 顺丰标快 | I57: 寄付 | J57: 6.00 | K57: 0.00 | L57: 6.00 | M57: 邹小华 | N57: 收件微派 | O57: 取宝-物流服务 | P57: 186****6788‎‎‎‬‬‬ | Q57: 东莞市中汇信息技术有限公司
A58: 56 | B58: 12-04 | C58: SF3262028718391 | D58: 东莞 | E58: 东莞 | F58: 邹小华 | G58: 0.000 | H58: 顺丰标快 | I58: 寄付 | J58: 6.00 | K58: 0.00 | L58: 6.00 | M58: 邹小华 | N58: 收件微派 | O58: 取宝-物流服务 | P58: 186****6788‎‎‎‬‬‬ | Q58: 东莞市中汇信息技术有限公司
A59: 57 | B59: 12-04 | C59: SF3274904297678 | D59: 东莞 | E59: 东莞 | F59: 邹小华 | G59: 0.000 | H59: 顺丰标快 | I59: 寄付 | J59: 6.00 | K59: 0.00 | L59: 6.00 | M59: 邹小华 | N59: 收件微派 | O59: 取宝-物流服务 | P59: 186****6788‎‎‎‬‬‬ | Q59: 东莞市中汇信息技术有限公司
A60: 58 | B60: 12-04 | C60: SF3274976461103 | D60: 东莞 | E60: 东莞 | F60: 邹小华 | G60: 0.000 | H60: 顺丰标快 | I60: 寄付 | J60: 3.00 | K60: 0.00 | L60: 3.00 | M60: 邹小华 | N60: 收件微派 | O60: 立充充电宝取机柜-物流服务 | P60: 186****6788‎‎‎‬‬‬ | Q60: 东莞市中汇信息技术有限公司
A61: 59 | B61: 12-05 | C61: SF3262146754955 | D61: 乌鲁木齐 | E61: 成都/资阳/眉山 | F61: 阿贞 | G61: 1.000 | H61: 顺丰标快 | I61: 寄转第三方 | J61: 20.00 | K61: 0.00 | L61: 20.00 | M61: 阿贞 | N61: 运费 | O61: 取宝-物流服务 | P61: 166****7945‎‎‎‬‬‬
A62: 60 | B62: 12-05 | C62: SF3262146754955 | D62: 乌鲁木齐 | E62: 成都/资阳/眉山 | F62: 阿贞 | G62: 0.000 | H62: 顺丰标快 | I62: 寄转第三方 | J62: 1.00 | K62: 0.00 | L62: 1.00 | M62: 阿贞 | N62: 包装服务 | O62: 取宝-物流服务 | P62: 166****7945‎‎‎‬‬‬
A63: 61 | B63: 12-05 | C63: SF3262146754991 | D63: 乌鲁木齐 | E63: 成都/资阳/眉山 | F63: 阿贞 | G63: 1.000 | H63: 顺丰标快 | I63: 寄转第三方 | J63: 20.00 | K63: 0.00 | L63: 20.00 | M63: 阿贞 | N63: 运费 | O63: 取宝-物流服务 | P63: 166****7945‎‎‎‬‬‬
A64: 62 | B64: 12-05 | C64: SF3262146754991 | D64: 乌鲁木齐 | E64: 成都/资阳/眉山 | F64: 阿贞 | G64: 0.000 | H64: 顺丰标快 | I64: 寄转第三方 | J64: 1.00 | K64: 0.00 | L64: 1.00 | M64: 阿贞 | N64: 包装服务 | O64: 取宝-物流服务 | P64: 166****7945‎‎‎‬‬‬
A65: 63 | B65: 12-05 | C65: SF3262146773901 | D65: 乌鲁木齐 | E65: 成都/资阳/眉山 | F65: 阿贞 | G65: 1.000 | H65: 顺丰标快 | I65: 寄转第三方 | J65: 20.00 | K65: 0.00 | L65: 20.00 | M65: 阿贞 | N65: 运费 | O65: 取宝-物流服务 | P65: 166****7945‎‎‎‬‬‬
A66: 64 | B66: 12-05 | C66: SF3262146773901 | D66: 乌鲁木齐 | E66: 成都/资阳/眉山 | F66: 阿贞 | G66: 0.000 | H66: 顺丰标快 | I66: 寄转第三方 | J66: 1.00 | K66: 0.00 | L66: 1.00 | M66: 阿贞 | N66: 包装服务 | O66: 取宝-物流服务 | P66: 166****7945‎‎‎‬‬‬
A67: 65 | B67: 12-05 | C67: SF3262146923178 | D67: 乌鲁木齐 | E67: 成都/资阳/眉山 | F67: 阿贞 | G67: 1.000 | H67: 顺丰标快 | I67: 寄转第三方 | J67: 20.00 | K67: 0.00 | L67: 20.00 | M67: 阿贞 | N67: 运费 | O67: 立充充电宝取机柜-物流服务 | P67: 166****7945‎‎‎‬‬‬
A68: 66 | B68: 12-05 | C68: SF3262146923178 | D68: 乌鲁木齐 | E68: 成都/资阳/眉山 | F68: 阿贞 | G68: 0.000 | H68: 顺丰标快 | I68: 寄转第三方 | J68: 1.00 | K68: 0.00 | L68: 1.00 | M68: 阿贞 | N68: 包装服务 | O68: 立充充电宝取机柜-物流服务 | P68: 166****7945‎‎‎‬‬‬
A69: 67 | B69: 12-05 | C69: SF3262146923187 | D69: 乌鲁木齐 | E69: 成都/资阳/眉山 | F69: 阿贞 | G69: 2.500 | H69: 顺丰标快 | I69: 寄转第三方 | J69: 32.00 | K69: 0.00 | L69: 32.00 | M69: 阿贞 | N69: 运费 | O69: 立充充电宝取机柜-物流服务 | P69: 166****7945‎‎‎‬‬‬
A70: 68 | B70: 12-05 | C70: SF3262146923187 | D70: 乌鲁木齐 | E70: 成都/资阳/眉山 | F70: 阿贞 | G70: 0.000 | H70: 顺丰标快 | I70: 寄转第三方 | J70: 4.00 | K70: 0.00 | L70: 4.00 | M70: 阿贞 | N70: 包装服务 | O70: 立充充电宝取机柜-物流服务 | P70: 166****7945‎‎‎‬‬‬
A71: 69 | B71: 12-05 | C71: SF3262608338851 | D71: 乌鲁木齐 | E71: 成都/资阳/眉山 | F71: 阿贞 | G71: 1.000 | H71: 顺丰标快 | I71: 寄转第三方 | J71: 20.00 | K71: 0.00 | L71: 20.00 | M71: 阿贞 | N71: 运费 | O71: 立充充电宝取机柜-物流服务 | P71: 166****7945‎‎‎‬‬‬
A72: 70 | B72: 12-05 | C72: SF3262608338851 | D72: 乌鲁木齐 | E72: 成都/资阳/眉山 | F72: 阿贞 | G72: 0.000 | H72: 顺丰标快 | I72: 寄转第三方 | J72: 2.00 | K72: 0.00 | L72: 2.00 | M72: 阿贞 | N72: 包装服务 | O72: 立充充电宝取机柜-物流服务 | P72: 166****7945‎‎‎‬‬‬
... A92: 90 | B92: 12-05 | C92: SF3274708420578 | D92: 乌鲁木齐 | E92: 成都/资阳/眉山 | F92: 阿贞 | G92: 0.000 | H92: 顺丰标快 | I92: 寄转第三方 | J92: 4.00 | K92: 0.00 | L92: 4.00 | M92: 阿贞 | N92: 包装服务 | O92: 取宝-物流服务 | P92: 166****7945‎‎‎‬‬‬
A93: 91 | B93: 12-05 | C93: SF3274990520130 | D93: 东莞 | E93: 惠州 | F93: 石湾美宜佳便利店(蓝湾半岛店粤20946) | G93: 0.000 | H93: 顺丰标快 | I93: 寄付 | J93: 6.00 | K93: 0.00 | L93: 6.00 | M93: 邹小华 | N93: 派件微派 | O93: 补宝-物流服务 | P93: 186****6788‎‎‎‬‬‬ | Q93: 东莞市中汇信息技术有限公司
A94: 92 | B94: 12-06 | C94: SF3262146754955 | D94: 乌鲁木齐 | E94: 成都/资阳/眉山 | F94: 阿贞 | G94: 0.000 | H94: 顺丰标快 | I94: 寄付 | J94: 6.00 | K94: 0.00 | L94: 6.00 | M94: 阿贞 | N94: 收件微派 | O94: 取宝-物流服务 | P94: 166****7945‎‎‎‬‬‬
A95: 93 | B95: 12-06 | C95: SF3262146754991 | D95: 乌鲁木齐 | E95: 成都/资阳/眉山 | F95: 阿贞 | G95: 0.000 | H95: 顺丰标快 | I95: 寄付 | J95: 6.00 | K95: 0.00 | L95: 6.00 | M95: 阿贞 | N95: 收件微派 | O95: 取宝-物流服务 | P95: 166****7945‎‎‎‬‬‬
A96: 94 | B96: 12-06 | C96: SF3262146773901 | D96: 乌鲁木齐 | E96: 成都/资阳/眉山 | F96: 阿贞 | G96: 0.000 | H96: 顺丰标快 | I96: 寄付 | J96: 6.00 | K96: 0.00 | L96: 6.00 | M96: 阿贞 | N96: 收件微派 | O96: 取宝-物流服务 | P96: 166****7945‎‎‎‬‬‬
A97: 95 | B97: 12-06 | C97: SF3262146923178 | D97: 乌鲁木齐 | E97: 成都/资阳/眉山 | F97: 阿贞 | G97: 0.000 | H97: 顺丰标快 | I97: 寄付 | J97: 3.00 | K97: 0.00 | L97: 3.00 | M97: 阿贞 | N97: 收件微派 | O97: 立充充电宝取机柜-物流服务 | P97: 166****7945‎‎‎‬‬‬
A98: 96 | B98: 12-06 | C98: SF3262146923187 | D98: 乌鲁木齐 | E98: 成都/资阳/眉山 | F98: 阿贞 | G98: 0.000 | H98: 顺丰标快 | I98: 寄付 | J98: 3.00 | K98: 0.00 | L98: 3.00 | M98: 阿贞 | N98: 收件微派 | O98: 立充充电宝取机柜-物流服务 | P98: 166****7945‎‎‎‬‬‬
A99: 97 | B99: 12-06 | C99: SF3262608338851 | D99: 乌鲁木齐 | E99: 成都/资阳/眉山 | F99: 阿贞 | G99: 0.000 | H99: 顺丰标快 | I99: 寄付 | J99: 3.00 | K99: 0.00 | L99: 3.00 | M99: 阿贞 | N99: 收件微派 | O99: 立充充电宝取机柜-物流服务 | P99: 166****7945‎‎‎‬‬‬
A100: 98 | B100: 12-06 | C100: SF3262727180607 | D100: 东莞 | E100: 东莞 | F100: 邹小华 | G100: 1.000 | H100: 顺丰标快 | I100: 寄转第三方 | J100: 11.00 | K100: 0.00 | L100: 11.00 | M100: 邹小华 | N100: 运费 | O100: 取宝-物流服务 | P100: 186****6788‎‎‎‬‬‬ | Q100: 东莞市中汇信息技术有限公司
A101: 99 | B101: 12-06 | C101: SF3262727180607 | D101: 东莞 | E101: 东莞 | F101: 邹小华 | G101: 0.000 | H101: 顺丰标快 | I101: 寄转第三方 | J101: 1.00 | K101: 0.00 | L101: 1.00 | M101: 邹小华 | N101: 包装服务 | O101: 取宝-物流服务 | P101: 186****6788‎‎‎‬‬‬ | Q101: 东莞市中汇信息技术有限公司
A102: 100 | B102: 12-06 | C102: SF3262727180661 | D102: 东莞 | E102: 东莞 | F102: 邹小华 | G102: 1.000 | H102: 顺丰标快 | I102: 寄转第三方 | J102: 11.00 | K102: 0.00 | L102: 11.00 | M102: 邹小华 | N102: 运费 | O102: 取宝-物流服务 | P102: 186****6788‎‎‎‬‬‬ | Q102: 东莞市中汇信息技术有限公司
A103: 101 | B103: 12-06 | C103: SF3262727180661 | D103: 东莞 | E103: 东莞 | F103: 邹小华 | G103: 0.000 | H103: 顺丰标快 | I103: 寄转第三方 | J103: 1.00 | K103: 0.00 | L103: 1.00 | M103: 邹小华 | N103: 包装服务 | O103: 取宝-物流服务 | P103: 186****6788‎‎‎‬‬‬ | Q103: 东莞市中汇信息技术有限公司
A104: 102 | B104: 12-06 | C104: SF3262727683329 | D104: 东莞 | E104: 东莞 | F104: 邹小华 | G104: 3.000 | H104: 顺丰标快 | I104: 寄转第三方 | J104: 13.00 | K104: 0.00 | L104: 13.00 | M104: 邹小华 | N104: 运费 | O104: 立充充电宝取机柜-物流服务 | P104: 186****6788‎‎‎‬‬‬ | Q104: 东莞市中汇信息技术有限公司
A105: 103 | B105: 12-06 | C105: SF3262727683329 | D105: 东莞 | E105: 东莞 | F105: 邹小华 | G105: 0.000 | H105: 顺丰标快 | I105: 寄转第三方 | J105: 5.00 | K105: 0.00 | L105: 5.00 | M105: 邹小华 | N105: 包装服务 | O105: 立充充电宝取机柜-物流服务 | P105: 186****6788‎‎‎‬‬‬ | Q105: 东莞市中汇信息技术有限公司
A106: 104 | B106: 12-06 | C106: SF3262863515431 | D106: 成都/资阳/眉山 | E106: 成都/资阳/眉山 | F106: 代俊峰 | G106: 0.000 | H106: 顺丰标快 | I106: 寄付 | J106: 6.00 | K106: 0.00 | L106: 6.00 | M106: 江源 | N106: 收件微派 | O106: 取宝-物流服务 | P106: 186****8030‎‎‎‬‬‬
A107: 105 | B107: 12-06 | C107: SF3274239917142 | D107: 乌鲁木齐 | E107: 成都/资阳/眉山 | F107: 阿贞 | G107: 0.000 | H107: 顺丰标快 | I107: 寄付 | J107: 6.00 | K107: 0.00 | L107: 6.00 | M107: 阿贞 | N107: 收件微派 | O107: 取宝-物流服务 | P107: 166****7945‎‎‎‬‬‬
A108: 106 | B108: 12-06 | C108: SF3274239917973 | D108: 乌鲁木齐 | E108: 成都/资阳/眉山 | F108: 阿贞 | G108: 0.000 | H108: 顺丰标快 | I108: 寄付 | J108: 6.00 | K108: 0.00 | L108: 6.00 | M108: 阿贞 | N108: 收件微派 | O108: 取宝-物流服务 | P108: 166****7945‎‎‎‬‬‬
A109: 107 | B109: 12-06 | C109: SF3274418514967 | D109: 成都/资阳/眉山 | E109: 成都/资阳/眉山 | F109: 代俊峰 | G109: 0.000 | H109: 顺丰标快 | I109: 寄付 | J109: 6.00 | K109: 0.00 | L109: 6.00 | M109: 江源 | N109: 收件微派 | O109: 取宝-物流服务 | P109: 186****8030‎‎‎‬‬‬
A110: 108 | B110: 12-06 | C110: SF3274418591644 | D110: 成都/资阳/眉山 | E110: 成都/资阳/眉山 | F110: 代俊峰 | G110: 0.000 | H110: 顺丰标快 | I110: 寄付 | J110: 3.00 | K110: 0.00 | L110: 3.00 | M110: 江源 | N110: 收件微派 | O110: 立充充电宝取机柜-物流服务 | P110: 186****8030‎‎‎‬‬‬
A111: 109 | B111: 12-06 | C111: SF3274475500278 | D111: 秦皇岛 | E111: 沈阳/铁岭/抚顺 | F111: 辽宁深蓝 | G111: 0.000 | H111: 顺丰标快 | I111: 寄付 | J111: 3.00 | K111: 0.00 | L111: 3.00 | M111: 贾微 | N111: 收件微派 | O111: 立充充电宝取机柜-物流服务 | P111: 150****3407‎‎‎‬‬‬
A112: 110 | B112: 12-06 | C112: SF3274708420302 | D112: 乌鲁木齐 | E112: 成都/资阳/眉山 | F112: 阿贞 | G112: 0.000 | H112: 顺丰标快 | I112: 寄付 | J112: 6.00 | K112: 0.00 | L112: 6.00 | M112: 阿贞 | N112: 收件微派 | O112: 取宝-物流服务 | P112: 166****7945‎‎‎‬‬‬
A113: 111 | B113: 12-06 | C113: SF3274708420578 | D113: 乌鲁木齐 | E113: 成都/资阳/眉山 | F113: 阿贞 | G113: 0.000 | H113: 顺丰标快 | I113: 寄付 | J113: 6.00 | K113: 0.00 | L113: 6.00 | M113: 阿贞 | N113: 收件微派 | O113: 取宝-物流服务 | P113: 166****7945‎‎‎‬‬‬
A114: 112 | B114: 12-07 | C114: SF3262727180607 | D114: 东莞 | E114: 东莞 | F114: 邹小华 | G114: 0.000 | H114: 顺丰标快 | I114: 寄付 | J114: 6.00 | K114: 0.00 | L114: 6.00 | M114: 邹小华 | N114: 收件微派 | O114: 取宝-物流服务 | P114: 186****6788‎‎‎‬‬‬ | Q114: 东莞市中汇信息技术有限公司
A115: 113 | B115: 12-07 | C115: SF3262727180661 | D115: 东莞 | E115: 东莞 | F115: 邹小华 | G115: 0.000 | H115: 顺丰标快 | I115: 寄付 | J115: 6.00 | K115: 0.00 | L115: 6.00 | M115: 邹小华 | N115: 收件微派 | O115: 取宝-物流服务 | P115: 186****6788‎‎‎‬‬‬ | Q115: 东莞市中汇信息技术有限公司
A116: 114 | B116: 12-07 | C116: SF3262727683329 | D116: 东莞 | E116: 东莞 | F116: 邹小华 | G116: 0.000 | H116: 顺丰标快 | I116: 寄付 | J116: 3.00 | K116: 0.00 | L116: 3.00 | M116: 邹小华 | N116: 收件微派 | O116: 立充充电宝取机柜-物流服务 | P116: 186****6788‎‎‎‬‬‬ | Q116: 东莞市中汇信息技术有限公司
A117: 115 | B117: 12-07 | C117: SF3274239917151 | D117: 乌鲁木齐 | E117: 成都/资阳/眉山 | F117: 阿贞 | G117: 0.000 | H117: 顺丰标快 | I117: 寄付 | J117: 6.00 | K117: 0.00 | L117: 6.00 | M117: 阿贞 | N117: 收件微派 | O117: 取宝-物流服务 | P117: 166****7945‎‎‎‬‬‬
A118: 116 | B118: 12-07 | C118: SF3274418514921 | D118: 成都/资阳/眉山 | E118: 成都/资阳/眉山 | F118: 代俊峰 | G118: 0.000 | H118: 顺丰标快 | I118: 寄付 | J118: 6.00 | K118: 0.00 | L118: 6.00 | M118: 江源 | N118: 收件微派 | O118: 取宝-物流服务 | P118: 186****8030‎‎‎‬‬‬
A119: 117 | B119: 12-08 | C119: SF3269240753364 | D119: 东莞 | E119: 东莞 | F119: 企石好想来省钱超市便利店 | G119: 1.000 | H119: 顺丰标快 | I119: 寄转第三方 | J119: 11.00 | K119: 0.00 | L119: 11.00 | M119: 邹小华 | N119: 运费 | O119: 补宝-物流服务 | P119: 186****6788‎‎‎‬‬‬ | Q119: 东莞市中汇信息技术有限公司
...
